Workbook
Name CYC_INGRESO: 'Burger-F7-F8'!$N$5:$N$66
Name F5_INGRESO: 'AFI-F5'!$N$5:$N$72
Name CYC_VENDEDOR: 'GB4'!$P$5:$P$34
Name F4_SALDO: 'AFI-F4'!$O$5:$O$72
Name BD_TABLA: Base_General!$B$3:$X$989
Name KAMADO_SALDO: #REF!
Name CYC_INGRESO: 'CyC-F11-F12'!$N$5:$N$66
Name CYC_SALDO: 'GN-Completo'!$O$5:$O$66
Name Online_INGRESO: ONLINE!$N$5:$N$204
Name F4_VENDEDOR: 'AFI-F4'!$P$5:$P$72
Name KAMADO_VENDEDOR: #REF!
Name CYC_SALDO: 'GB2'!$O$5:$O$34
Name MARINA_VENDEDOR: Corporativo!$P$5:$P$14
Name CYC_VENDEDOR: 'CyC-F11-F12'!$P$5:$P$66
Name F3_VENDEDOR: 'AFI-F3'!$P$5:$P$72
Name MARINA_VENDEDOR: 'Burger-F9-F10'!$P$5:$P$66
Name CYC_SALDO: 'GB4'!$O$5:$O$34
Name CYC_VENDEDOR: 'GB1'!$Q$5:$Q$34
Name F1_VENDEDOR: 'AFI-F1'!$P$5:$P$72
Name CYC_SALDO: 'CyC-F11-F12'!$O$5:$O$66
Name CYC_SALDO: 'GB3'!$O$5:$O$34
Name F2_VENDEDOR: 'AFI-F2'!$Q$5:$Q$72
Name BaseDatos: Base_General!$B$3:$X$928
Name Online_VENDEDOR: ONLINE!$P$5:$P$204
Name CYC_INGRESO: 'GB2'!$N$5:$N$34
Name CYC_SALDO: 'GB1'!$P$5:$P$34
Name F3_SALDO: 'AFI-F3'!$O$5:$O$72
Name F1_INGRESO: 'AFI-F1'!$N$5:$N$72
Name F5_VENDEDOR: 'AFI-F5'!$P$5:$P$72
Name F6_SALDO: 'AFI-F6'!$O$5:$O$72
Name F2_SALDO: 'AFI-F2'!$P$5:$P$72
Name F5_SALDO: 'AFI-F5'!$O$5:$O$72
Name F2_INGRESO: 'AFI-F2'!$N$5:$N$72
Name CYC_INGRESO: 'GB1'!$N$5:$N$34
Name F6_VENDEDOR: 'AFI-F6'!$P$5:$P$72
Name CUENTAS: VARIABLE!$B$4:$B$15
Name VENDEDOR: VARIABLE!$D$4:$D$15
Name KAMADO_INGRESO: #REF!
Name CYC_VENDEDOR: 'GB2'!$P$5:$P$34
Name MARINA_INGRESO: 'Burger-F9-F10'!$N$5:$N$66
Name CYC_VENDEDOR: 'GB3'!$P$5:$P$34
Name CYC_INGRESO: 'GB3'!$N$5:$N$34
Name CYC_INGRESO: 'GB4'!$N$5:$N$34
Name F4_INGRESO: 'AFI-F4'!$N$5:$N$72
Name SITUACION: VARIABLE!$F$4:$F$7
Name CYC_INGRESO: 'GN-Completo'!$N$5:$N$66
Name F1_SALDO: 'AFI-F1'!$O$5:$O$72
Name F3_INGRESO: 'AFI-F3'!$N$5:$N$72
Name F6_INGRESO: 'AFI-F6'!$N$5:$N$72
Name CYC_SALDO: 'Burger-F7-F8'!$O$5:$O$66
Name MARINA_SALDO: Corporativo!$O$5:$O$14
Name CYC_VENDEDOR: 'Burger-F7-F8'!$P$5:$P$66
Name TALLERES: VARIABLE!$H$4:$H$8
Name MARINA_INGRESO: Corporativo!$N$5:$N$14
Name CYC_VENDEDOR: 'GN-Completo'!$P$5:$P$66
Name MARINA_SALDO: 'Burger-F9-F10'!$O$5:$O$66

Sheet Base_General
B3: ID | C3: MES | D3: SEMANA | E3: DIA | F3: FECHA_dia | G3: PRODUCTO | H3: PROD FECHA | I3: FE_ REGISTRO | J3: DNI | K3: NOMBRES Y APELLIDOS | L3: EMAIL | M3: DISTRITO | N3: WSP | O3: F1 | P3: F2 | Q3: MONTO | R3: xCOBRAR | S3: ESTADO | T3: CUENTA | U3: INGRESO | V3: SALDO | W3: VENDEDOR | X3: TOTAL
B4: 1 | C4: =TEXT(I4,"Mmmm") -> diciembre | D4: =WEEKNUM(I4) -> 51 | E4: =TEXT(I4,"DDDD") -> miércoles | F4: =DAY(I4) -> 17 | G4: AFI | H4: ='AFI-F1'!$G$3 -> 45661 | I4: ='AFI-F1'!B5 -> 46008 | J4: ='AFI-F1'!C5 -> 72041694 | K4: ='AFI-F1'!D5 -> Sebastian Castillo | L4: ='AFI-F1'!E5 -> sebastiancm@outlook.com | M4: ='AFI-F1'!F5 -> BARRANCO | N4: ='AFI-F1'!G5 -> 998 690 869 | O4: ='AFI-F1'!H5 -> X | P4: ='AFI-F1'!I5 | ... X4: ='AFI-F1'!Q5 -> 250
B5: =B4+1 -> 2 | C5: =TEXT(I5,"Mmmm") -> diciembre | D5: =WEEKNUM(I5) -> 51 | E5: =TEXT(I5,"DDDD") -> sábado | F5: =DAY(I5) -> 20 | G5: AFI | H5: ='AFI-F1'!$G$3 -> 45661 | I5: ='AFI-F1'!B6 -> 46011 | J5: ='AFI-F1'!C6 -> 75931158 | K5: ='AFI-F1'!D6 -> Daniel Rojas Salas | L5: ='AFI-F1'!E6 -> juanchadrs@gmail.com | M5: ='AFI-F1'!F6 -> la victoria | N5: ='AFI-F1'!G6 | O5: ='AFI-F1'!H6 -> X | P5: ='AFI-F1'!I6 | ... X5: ='AFI-F1'!Q6 -> 190
B6: =B5+1 -> 3 | C6: =TEXT(I6,"Mmmm") -> diciembre | D6: =WEEKNUM(I6) -> 51 | E6: =TEXT(I6,"DDDD") -> sábado | F6: =DAY(I6) -> 20 | G6: AFI | H6: ='AFI-F1'!$G$3 -> 45661 | I6: ='AFI-F1'!B7 -> 46011 | J6: ='AFI-F1'!C7 -> 25631173 | K6: ='AFI-F1'!D7 -> Miriam Salas Guevara | L6: ='AFI-F1'!E7 -> elysalas2004@hotmail.com | M6: ='AFI-F1'!F7 -> villa el salvador | N6: ='AFI-F1'!G7 | O6: ='AFI-F1'!H7 -> X | P6: ='AFI-F1'!I7 | ... X6: ='AFI-F1'!Q7 -> 190
B7: =B6+1 -> 4 | C7: =TEXT(I7,"Mmmm") -> diciembre | D7: =WEEKNUM(I7) -> 52 | E7: =TEXT(I7,"DDDD") -> sábado | F7: =DAY(I7) -> 30 | G7: AFI | H7: ='AFI-F1'!$G$3 -> 45661 | I7: ='AFI-F1'!B8 | J7: ='AFI-F1'!C8 | K7: ='AFI-F1'!E8 | L7: ='AFI-F1'!E8 | M7: ='AFI-F1'!F8 | N7: ='AFI-F1'!G8 | O7: ='AFI-F1'!H8 | P7: ='AFI-F1'!I8 | Q7: ='AFI-F1'!J8 | R7: ='AFI-F1'!K8 | S7: ='AFI-F1'!L8 | ... X7: ='AFI-F1'!Q8 -> 0
B8: =B7+1 -> 5 | C8: =TEXT(I8,"Mmmm") -> noviembre | D8: =WEEKNUM(I8) -> 46 | E8: =TEXT(I8,"DDDD") -> domingo | F8: =DAY(I8) -> 9 | G8: AFI | H8: ='AFI-F1'!$G$3 -> 45661 | I8: ='AFI-F1'!B9 -> 45970 | J8: ='AFI-F1'!C9 -> 75728889 | K8: ='AFI-F1'!D9 -> Juan Carlos Vidal Molina | L8: ='AFI-F1'!E9 -> hellenleon7@gmail.com | M8: ='AFI-F1'!F9 -> CHACLACAYO | N8: ='AFI-F1'!G9 -> 989 356 823 | O8: ='AFI-F1'!H9 -> X | P8: ='AFI-F1'!I9 | ... X8: ='AFI-F1'!Q9 -> 220
B9: =B8+1 -> 6 | C9: =TEXT(I9,"Mmmm") -> diciembre | D9: =WEEKNUM(I9) -> 52 | E9: =TEXT(I9,"DDDD") -> viernes | F9: =DAY(I9) -> 26 | G9: AFI | H9: ='AFI-F1'!$G$3 -> 45661 | I9: ='AFI-F1'!B10 -> 46017 | J9: ='AFI-F1'!C10 -> 44000113 | K9: ='AFI-F1'!D10 -> CESAR KENNY YACARINI PEREYRA | L9: ='AFI-F1'!E10 -> ckyacariniman2@gmail.com | M9: ='AFI-F1'!F10 -> SJL | N9: ='AFI-F1'!G10 -> 947 169 905 | O9: ='AFI-F1'!H10 -> X | P9: ='AFI-F1'!I10 | ... X9: ='AFI-F1'!Q10 -> 190
B10: =B9+1 -> 7 | C10: =TEXT(I10,"Mmmm") -> diciembre | D10: =WEEKNUM(I10) -> 52 | E10: =TEXT(I10,"DDDD") -> viernes | F10: =DAY(I10) -> 26 | G10: AFI | H10: ='AFI-F1'!$G$3 -> 45661 | I10: ='AFI-F1'!B11 -> 46017 | J10: ='AFI-F1'!C11 -> 43619681 | K10: ='AFI-F1'!D11 -> Ronald elvis quispe gil | L10: ='AFI-F1'!E11 -> Reqg_672@hotmail.com | M10: ='AFI-F1'!F11 -> SJL | N10: ='AFI-F1'!G11 | O10: ='AFI-F1'!H11 -> X | P10: ='AFI-F1'!I11 | ... X10: ='AFI-F1'!Q11 -> 190
B11: =B10+1 -> 8 | C11: =TEXT(I11,"Mmmm") -> diciembre | D11: =WEEKNUM(I11) -> 52 | E11: =TEXT(I11,"DDDD") -> viernes | F11: =DAY(I11) -> 26 | G11: AFI | H11: ='AFI-F1'!$G$3 -> 45661 | I11: ='AFI-F1'!B12 -> 46017 | J11: ='AFI-F1'!C12 -> 43943113 | K11: ='AFI-F1'!D12 -> Flor de maria Guevara | L11: ='AFI-F1'!E12 -> Gerencia@imelin.com.pe | M11: ='AFI-F1'!F12 -> SJL | N11: ='AFI-F1'!G12 | O11: ='AFI-F1'!H12 -> X | P11: ='AFI-F1'!I12 | ... X11: ='AFI-F1'!Q12 -> 190
B12: =B11+1 -> 9 | C12: =TEXT(I12,"Mmmm") -> diciembre | D12: =WEEKNUM(I12) -> 53 | E12: =TEXT(I12,"DDDD") -> lunes | F12: =DAY(I12) -> 29 | G12: AFI | H12: ='AFI-F1'!$G$3 -> 45661 | I12: ='AFI-F1'!B13 -> 46020 | J12: ='AFI-F1'!C13 | K12: ='AFI-F1'!D13 -> Franco Nieto Ponce | L12: ='AFI-F1'!E13 | M12: ='AFI-F1'!F13 | N12: ='AFI-F1'!G13 | O12: ='AFI-F1'!H13 -> x | P12: ='AFI-F1'!I13 | ... X12: ='AFI-F1'!Q13 -> 190
B13: =B12+1 -> 10 | C13: =TEXT(I13,"Mmmm") -> diciembre | D13: =WEEKNUM(I13) -> 53 | E13: =TEXT(I13,"DDDD") -> lunes | F13: =DAY(I13) -> 29 | G13: AFI | H13: ='AFI-F1'!$G$3 -> 45661 | I13: ='AFI-F1'!B14 -> 46020 | J13: ='AFI-F1'!C14 | K13: ='AFI-F1'!D14 -> Luis Enrique Nieto Arauco | L13: ='AFI-F1'!E14 | M13: ='AFI-F1'!F14 | N13: ='AFI-F1'!G14 | O13: ='AFI-F1'!H14 -> x | P13: ='AFI-F1'!I14 | ... X13: ='AFI-F1'!Q14 -> 190
B14: =B13+1 -> 11 | C14: =TEXT(I14,"Mmmm") -> diciembre | D14: =WEEKNUM(I14) -> 53 | E14: =TEXT(I14,"DDDD") -> lunes | F14: =DAY(I14) -> 29 | G14: AFI | H14: ='AFI-F1'!$G$3 -> 45661 | I14: ='AFI-F1'!B15 -> 46020 | J14: ='AFI-F1'!C15 | K14: ='AFI-F1'!D15 -> Gladys Montes | L14: ='AFI-F1'!E15 | M14: ='AFI-F1'!F15 -> SJL | N14: ='AFI-F1'!G15 | O14: ='AFI-F1'!H15 -> x | P14: ='AFI-F1'!I15 | ... X14: ='AFI-F1'!Q15 -> 175
B15: =B14+1 -> 12 | C15: =TEXT(I15,"Mmmm") -> diciembre | D15: =WEEKNUM(I15) -> 53 | E15: =TEXT(I15,"DDDD") -> lunes | F15: =DAY(I15) -> 29 | G15: AFI | H15: ='AFI-F1'!$G$3 -> 45661 | I15: ='AFI-F1'!B16 -> 46020 | J15: ='AFI-F1'!C16 | K15: ='AFI-F1'!D16 -> Fernando Alfredo Auqui Cerron | L15: ='AFI-F1'!E16 | M15: ='AFI-F1'!F16 -> SJL | N15: ='AFI-F1'!G16 | O15: ='AFI-F1'!H16 -> x | P15: ='AFI-F1'!I16 | ... X15: ='AFI-F1'!Q16 -> 175
B16: =B15+1 -> 13 | C16: =TEXT(I16,"Mmmm") -> diciembre | D16: =WEEKNUM(I16) -> 53 | E16: =TEXT(I16,"DDDD") -> lunes | F16: =DAY(I16) -> 29 | G16: AFI | H16: ='AFI-F1'!$G$3 -> 45661 | I16: ='AFI-F1'!B17 -> 46020 | J16: ='AFI-F1'!C17 | K16: ='AFI-F1'!D17 -> Gianfranco Auqui Guerrero | L16: ='AFI-F1'!E17 | M16: ='AFI-F1'!F17 -> SJL | N16: ='AFI-F1'!G17 | O16: ='AFI-F1'!H17 -> x | P16: ='AFI-F1'!I17 | ... X16: ='AFI-F1'!Q17 -> 175
B17: =B16+1 -> 14 | C17: =TEXT(I17,"Mmmm") -> diciembre | D17: =WEEKNUM(I17) -> 53 | E17: =TEXT(I17,"DDDD") -> lunes | F17: =DAY(I17) -> 29 | G17: AFI | H17: ='AFI-F1'!$G$3 -> 45661 | I17: ='AFI-F1'!B18 -> 46020 | J17: ='AFI-F1'!C18 | K17: ='AFI-F1'!D18 -> Germán Auqui Cerrón | L17: ='AFI-F1'!E18 | M17: ='AFI-F1'!F18 -> SJL | N17: ='AFI-F1'!G18 | O17: ='AFI-F1'!H18 -> x | P17: ='AFI-F1'!I18 | ... X17: ='AFI-F1'!Q18 -> 175
B18: =B17+1 -> 15 | C18: =TEXT(I18,"Mmmm") -> diciembre | D18: =WEEKNUM(I18) -> 53 | E18: =TEXT(I18,"DDDD") -> martes | F18: =DAY(I18) -> 30 | G18: AFI | H18: ='AFI-F1'!$G$3 -> 45661 | I18: ='AFI-F1'!B19 -> 46021 | J18: ='AFI-F1'!C19 -> 49035262 | K18: ='AFI-F1'!D19 -> Rafael Antony Urbina Peña | L18: ='AFI-F1'!E19 -> rafaelurbi24@gmail.com | M18: ='AFI-F1'!F19 -> LOS OLIVOS | N18: ='AFI-F1'!G19 | O18: ='AFI-F1'!H19 -> X | P18: ='AFI-F1'!I19 | ... X18: ='AFI-F1'!Q19 -> 350
B19: =B18+1 -> 16 | C19: =TEXT(I19,"Mmmm") -> diciembre | D19: =WEEKNUM(I19) -> 53 | E19: =TEXT(I19,"DDDD") -> miércoles | F19: =DAY(I19) -> 31 | G19: AFI | H19: ='AFI-F1'!$G$3 -> 45661 | I19: ='AFI-F1'!B20 -> 46022 | J19: ='AFI-F1'!C20 -> 71486933 | K19: ='AFI-F1'!D20 -> Roberto Benites Aguilar | L19: ='AFI-F1'!E20 -> benites.07@hotmail.com | M19: ='AFI-F1'!F20 | N19: ='AFI-F1'!G20 | O19: ='AFI-F1'!H20 -> x | P19: ='AFI-F1'!I20 | ... X19: ='AFI-F1'!Q20 -> 220
... B71: =B70+1 -> 68 | C71: =TEXT(I71,"Mmmm") -> diciembre | D71: =WEEKNUM(I71) -> 52 | E71: =TEXT(I71,"DDDD") -> sábado | F71: =DAY(I71) -> 30 | G71: AFI | H71: ='AFI-F1'!$G$3 -> 45661 | I71: ='AFI-F1'!B72 | J71: ='AFI-F1'!C72 | K71: ='AFI-F1'!D72 | L71: ='AFI-F1'!E72 | M71: ='AFI-F1'!F72 | N71: ='AFI-F1'!G72 | O71: ='AFI-F1'!H72 | P71: ='AFI-F1'!I72 | ... X71: ='AFI-F1'!Q72 -> 0
B72: 1 | C72: =TEXT(I72,"Mmmm") -> diciembre | D72: =WEEKNUM(I72) -> 49 | E72: =TEXT(I72,"DDDD") -> martes | F72: =DAY(I72) -> 2 | G72: AFI | H72: ='AFI-F2'!$G$3 -> 45668 | I72: ='AFI-F2'!B5 -> 45993 | J72: ='AFI-F2'!C5 -> 47078798 | K72: ='AFI-F2'!D5 -> Anthony Molina Heredia | L72: ='AFI-F2'!E5 -> anthony.molinah@gmail.com | M72: ='AFI-F2'!F5 -> VMT | N72: ='AFI-F2'!G5 -> 968 358 245 | O72: ='AFI-F2'!H5 | P72: ='AFI-F2'!I5 -> X | ... U72: ='AFI-F2'!N5 -> 220 | V72: ='AFI-F2'!P5 | W72: ='AFI-F2'!Q5 -> Yadhira | X72: ='AFI-F2'!R5 -> 220
B73: =B72+1 -> 2 | C73: =TEXT(I73,"Mmmm") -> diciembre | D73: =WEEKNUM(I73) -> 51 | E73: =TEXT(I73,"DDDD") -> miércoles | F73: =DAY(I73) -> 17 | G73: AFI | H73: ='AFI-F2'!$G$3 -> 45668 | I73: ='AFI-F2'!B6 -> 46008 | J73: ='AFI-F2'!C6 -> 44681923 | K73: ='AFI-F2'!D6 -> Rodrigo Bustamante Moquillaza | L73: ='AFI-F2'!E6 -> Roodj88@gmail.com | M73: ='AFI-F2'!F6 -> SURQUILLO | N73: ='AFI-F2'!G6 -> 995 586 556 | O73: ='AFI-F2'!H6 | P73: ='AFI-F2'!I6 -> X | ... U73: ='AFI-F2'!N6 -> 200 | V73: ='AFI-F2'!P6 | W73: ='AFI-F2'!Q6 -> Yadhira | X73: ='AFI-F2'!R6 -> 355
B74: =B73+1 -> 3 | C74: =TEXT(I74,"Mmmm") -> diciembre | D74: =WEEKNUM(I74) -> 51 | E74: =TEXT(I74,"DDDD") -> miércoles | F74: =DAY(I74) -> 17 | G74: AFI | H74: ='AFI-F2'!$G$3 -> 45668 | I74: ='AFI-F2'!B7 -> 46008 | J74: ='AFI-F2'!C7 | K74: ='AFI-F2'!D7 -> Philip Wenter Bustamante | L74: ='AFI-F2'!E7 -> Roodj88@gmail.com | M74: ='AFI-F2'!F7 -> SURQUILLO | N74: ='AFI-F2'!G7 -> 995 586 556 | O74: ='AFI-F2'!H7 | P74: ='AFI-F2'!I7 -> X | ... U74: ='AFI-F2'!N7 -> 200 | V74: ='AFI-F2'!P7 | W74: ='AFI-F2'!Q7 -> Yadhira | X74: ='AFI-F2'!R7 -> 355
B75: =B74+1 -> 4 | C75: =TEXT(I75,"Mmmm") -> diciembre | D75: =WEEKNUM(I75) -> 51 | E75: =TEXT(I75,"DDDD") -> miércoles | F75: =DAY(I75) -> 17 | G75: AFI | H75: ='AFI-F2'!$G$3 -> 45668 | I75: ='AFI-F2'!B8 -> 46008 | J75: ='AFI-F2'!C8 -> 72495808 | K75: ='AFI-F2'!D8 -> Sebastian Matias Prada Fernandez | L75: ='AFI-F2'!E8 -> Matias_pf_21@hotmail.com | M75: ='AFI-F2'!F8 -> LA VICTORIA | N75: ='AFI-F2'!G8 -> 954 532 968 | O75: ='AFI-F2'!H8 -> X | P75: ='AFI-F2'!I8 -> X | ... U75: ='AFI-F2'!N8 -> 190 | V75: ='AFI-F2'!P8 | W75: ='AFI-F2'!Q8 -> Yadhira | X75: ='AFI-F2'!R8 -> 380
B76: =B75+1 -> 5 | C76: =TEXT(I76,"Mmmm") -> diciembre | D76: =WEEKNUM(I76) -> 51 | E76: =TEXT(I76,"DDDD") -> miércoles | F76: =DAY(I76) -> 17 | G76: AFI | H76: ='AFI-F2'!$G$3 -> 45668 | I76: ='AFI-F2'!B9 -> 46008 | J76: ='AFI-F2'!C9 -> 09594474 | K76: ='AFI-F2'!D9 -> Jorge Fernandez Huaman | L76: ='AFI-F2'!E9 -> Matias_pf_21@hotmail.com | M76: ='AFI-F2'!F9 -> LA VICTORIA | N76: ='AFI-F2'!G9 -> 954 532 968 | O76: ='AFI-F2'!H9 -> X | P76: ='AFI-F2'!I9 | ... U76: ='AFI-F2'!N9 -> 95 | V76: ='AFI-F2'!P9 | W76: ='AFI-F2'!Q9 -> Yadhira | X76: ='AFI-F2'!R9 -> 190
B77: =B76+1 -> 6 | C77: =TEXT(I77,"Mmmm") -> diciembre | D77: =WEEKNUM(I77) -> 52 | E77: =TEXT(I77,"DDDD") -> martes | F77: =DAY(I77) -> 23 | G77: AFI | H77: ='AFI-F2'!$G$3 -> 45668 | I77: ='AFI-F2'!B10 -> 46014 | J77: ='AFI-F2'!C10 -> 44889118 | K77: ='AFI-F2'!D10 -> Miguel Ángel Requiz Alanís | L77: ='AFI-F2'!E10 -> Miguel.requiz10@gmail.com | M77: ='AFI-F2'!F10 -> SJL | N77: ='AFI-F2'!G10 -> 975 575 476 | O77: ='AFI-F2'!H10 -> X | P77: ='AFI-F2'!I10 -> X | ... U77: ='AFI-F2'!N10 -> 360 | V77: ='AFI-F2'!P10 | W77: ='AFI-F2'!Q10 -> Yadhira | X77: ='AFI-F2'!R10 -> 360
B78: =B77+1 -> 7 | C78: =TEXT(I78,"Mmmm") -> diciembre | D78: =WEEKNUM(I78) -> 52 | E78: =TEXT(I78,"DDDD") -> martes | F78: =DAY(I78) -> 23 | G78: AFI | H78: ='AFI-F2'!$G$3 -> 45668 | I78: ='AFI-F2'!B11 -> 46014 | J78: ='AFI-F2'!C11 -> 43045566 | K78: ='AFI-F2'!D11 -> Carlos Miguel Olivares Pérez | L78: ='AFI-F2'!E11 -> Miguel.requiz10@gmail.com | M78: ='AFI-F2'!F11 -> CHICLAYO | N78: ='AFI-F2'!G11 -> 975 575 476 | O78: ='AFI-F2'!H11 -> X | P78: ='AFI-F2'!I11 -> X | ... U78: ='AFI-F2'!N11 -> 360 | V78: ='AFI-F2'!P11 | W78: ='AFI-F2'!Q11 -> Yadhira | X78: ='AFI-F2'!R11 -> 360
B79: =B78+1 -> 8 | C79: =TEXT(I79,"Mmmm") -> diciembre | D79: =WEEKNUM(I79) -> 51 | E79: =TEXT(I79,"DDDD") -> sábado | F79: =DAY(I79) -> 20 | G79: AFI | H79: ='AFI-F2'!$G$3 -> 45668 | I79: ='AFI-F2'!B12 -> 46011 | J79: ='AFI-F2'!C12 | K79: ='AFI-F2'!D12 -> Aldo Augusto Di liberto Roldán | L79: ='AFI-F2'!E12 -> aldodilibertoroldan@gmail.com | M79: ='AFI-F2'!F12 -> CHORRILLOS | N79: ='AFI-F2'!G12 -> 991385736 | O79: ='AFI-F2'!H12 -> X | P79: ='AFI-F2'!I12 | ... U79: ='AFI-F2'!N12 -> 95 | V79: ='AFI-F2'!P12 | W79: ='AFI-F2'!Q12 -> Yadhira | X79: ='AFI-F2'!R12 -> 190
B80: =B79+1 -> 9 | C80: =TEXT(I80,"Mmmm") -> diciembre | D80: =WEEKNUM(I80) -> 51 | E80: =TEXT(I80,"DDDD") -> sábado | F80: =DAY(I80) -> 20 | G80: AFI | H80: ='AFI-F2'!$G$3 -> 45668 | I80: ='AFI-F2'!B13 -> 46011 | J80: ='AFI-F2'!C13 | K80: ='AFI-F2'!D13 -> Yames Vicente di liberto Roldán | L80: ='AFI-F2'!E13 -> aldodilibertoroldan@gmail.com | M80: ='AFI-F2'!F13 -> CHORRILLOS | N80: ='AFI-F2'!G13 -> 991385736 | O80: ='AFI-F2'!H13 -> X | P80: ='AFI-F2'!I13 | ... U80: ='AFI-F2'!N13 -> 95 | V80: ='AFI-F2'!P13 | W80: ='AFI-F2'!Q13 -> Yadhira | X80: ='AFI-F2'!R13 -> 190
B81: =B80+1 -> 10 | C81: =TEXT(I81,"Mmmm") -> diciembre | D81: =WEEKNUM(I81) -> 53 | E81: =TEXT(I81,"DDDD") -> miércoles | F81: =DAY(I81) -> 30 | G81: AFI | H81: ='AFI-F2'!$G$3 -> 45668 | I81: ='AFI-F2'!B14 -> 46386 | J81: ='AFI-F2'!C14 -> 72616360 | K81: ='AFI-F2'!D14 -> Enrique Raynor La Torre Alarcón | L81: ='AFI-F2'!E14 -> enriquelta169@gmail.com | M81: ='AFI-F2'!F14 -> SAN BORJA | N81: ='AFI-F2'!G14 -> 966 922 334 | O81: ='AFI-F2'!H14 -> X | P81: ='AFI-F2'!I14 -> X | ... U81: ='AFI-F2'!N14 -> 380 | V81: ='AFI-F2'!P14 | W81: ='AFI-F2'!Q14 -> Greici | X81: ='AFI-F2'!R14 -> 380
B82: =B81+1 -> 11 | C82: =TEXT(I82,"Mmmm") -> diciembre | D82: =WEEKNUM(I82) -> 53 | E82: =TEXT(I82,"DDDD") -> martes | F82: =DAY(I82) -> 30 | G82: AFI | H82: ='AFI-F2'!$G$3 -> 45668 | I82: ='AFI-F2'!B15 -> 46021 | J82: ='AFI-F2'!C15 -> 49035262 | K82: ='AFI-F2'!D15 -> Rafael Antony Urbina Peña | L82: ='AFI-F2'!E15 -> rafaelurbi24@gmail.com | M82: ='AFI-F2'!F15 -> LOS OLIVOS | N82: ='AFI-F2'!G15 -> 927 235 029 | O82: ='AFI-F2'!H15 | P82: ='AFI-F2'!I15 -> X | ... U82: ='AFI-F2'!N15 -> 0 | V82: ='AFI-F2'!P15 | W82: ='AFI-F2'!Q15 -> Yadhira | X82: ='AFI-F2'!R15 -> 0
B83: =B82+1 -> 12 | C83: =TEXT(I83,"Mmmm") -> diciembre | D83: =WEEKNUM(I83) -> 53 | E83: =TEXT(I83,"DDDD") -> martes | F83: =DAY(I83) -> 30 | G83: AFI | H83: ='AFI-F2'!$G$3 -> 45668 | I83: ='AFI-F2'!B16 -> 46021 | J83: ='AFI-F2'!C16 -> 49032421 | K83: ='AFI-F2'!D16 -> Pierre Neyra | L83: ='AFI-F2'!E16 -> pierre.neyrape@gmail.com | M83: ='AFI-F2'!F16 -> MIRAFLORES | N83: ='AFI-F2'!G16 -> 954 134 851 | O83: ='AFI-F2'!H16 -> X | P83: ='AFI-F2'!I16 | ... U83: ='AFI-F2'!N16 -> 181.58 | V83: ='AFI-F2'!P16 | W83: ='AFI-F2'!Q16 -> Yadhira | X83: ='AFI-F2'!R16 -> 181.58
B84: =B83+1 -> 13 | C84: =TEXT(I84,"Mmmm") -> diciembre | D84: =WEEKNUM(I84) -> 53 | E84: =TEXT(I84,"DDDD") -> martes | F84: =DAY(I84) -> 30 | G84: AFI | H84: ='AFI-F2'!$G$3 -> 45668 | I84: ='AFI-F2'!B17 -> 46021 | J84: ='AFI-F2'!C17 -> 73185937 | K84: ='AFI-F2'!D17 -> Marieta Calderon | L84: ='AFI-F2'!E17 -> marietacristina@hotmail.com | M84: ='AFI-F2'!F17 -> MIRAFLORES | N84: ='AFI-F2'!G17 -> 954 134 851 | O84: ='AFI-F2'!H17 -> X | P84: ='AFI-F2'!I17 | ... U84: ='AFI-F2'!N17 -> 181.58 | V84: ='AFI-F2'!P17 | W84: ='AFI-F2'!Q17 -> Yadhira | X84: ='AFI-F2'!R17 -> 181.58
... B139: =B138+1 -> 68 | C139: =TEXT(I139,"Mmmm") -> diciembre | D139: =WEEKNUM(I139) -> 52 | E139: =TEXT(I139,"DDDD") -> sábado | F139: =DAY(I139) -> 30 | G139: AFI | H139: ='AFI-F2'!$G$3 -> 45668 | I139: ='AFI-F2'!B72 | J139: ='AFI-F2'!C72 | K139: ='AFI-F2'!D72 | L139: ='AFI-F2'!E72 | M139: ='AFI-F2'!F72 | N139: ='AFI-F2'!G72 | O139: ='AFI-F2'!H72 | P139: ='AFI-F2'!I72 | ... U139: ='AFI-F2'!N72 | V139: ='AFI-F2'!P72 | W139: ='AFI-F2'!Q72 | X139: ='AFI-F2'!R72 -> 0
B140: 1 | C140: =TEXT(I140,"Mmmm") -> diciembre | D140: =WEEKNUM(I140) -> 52 | E140: =TEXT(I140,"DDDD") -> martes | F140: =DAY(I140) -> 23 | G140: AFI | H140: ='AFI-F3'!$G$3 -> 45674 | I140: ='AFI-F3'!B5 -> 46014 | J140: ='AFI-F3'!C5 -> 41864072 | K140: ='AFI-F3'!D5 -> Alan Paul Otiniano Azahuanche | L140: ='AFI-F3'!E5 -> apoa315@hotmail.com | M140: ='AFI-F3'!F5 -> SURCO | N140: ='AFI-F3'!G5 -> 949 271 885 | O140: ='AFI-F3'!H5 -> X | P140: ='AFI-F3'!I5 | ... X140: ='AFI-F3'!Q5 -> 220
B141: =B140+1 -> 2 | C141: =TEXT(I141,"Mmmm") -> diciembre | D141: =WEEKNUM(I141) -> 52 | E141: =TEXT(I141,"DDDD") -> martes | F141: =DAY(I141) -> 23 | G141: AFI | H141: ='AFI-F3'!$G$3 -> 45674 | I141: ='AFI-F3'!B6 -> 46014 | J141: ='AFI-F3'!C6 -> 09954438 | K141: ='AFI-F3'!D6 -> Walter Peralta | L141: ='AFI-F3'!E6 -> Carolina.velosa@icloud.com | M141: ='AFI-F3'!F6 -> SAN BORJA | N141: ='AFI-F3'!G6 -> 987 737 748 | O141: ='AFI-F3'!H6 | P141: ='AFI-F3'!I6 -> X | ... X141: ='AFI-F3'!Q6 -> 220
B142: =B141+1 -> 3 | C142: =TEXT(I142,"Mmmm") -> diciembre | D142: =WEEKNUM(I142) -> 51 | E142: =TEXT(I142,"DDDD") -> jueves | F142: =DAY(I142) -> 18 | G142: AFI | H142: ='AFI-F3'!$G$3 -> 45674 | I142: ='AFI-F3'!B7 -> 46009 | J142: ='AFI-F3'!C7 -> 46649174 | K142: ='AFI-F3'!D7 -> Jonathan Marrou | L142: ='AFI-F3'!E7 -> Jonathan.marrou@gmail.com | M142: ='AFI-F3'!F7 -> SURCO | N142: ='AFI-F3'!G7 -> FB | O142: ='AFI-F3'!H7 | P142: ='AFI-F3'!I7 -> X | ... X142: ='AFI-F3'!Q7 -> 190
B143: =B142+1 -> 4 | C143: =TEXT(I143,"Mmmm") -> diciembre | D143: =WEEKNUM(I143) -> 51 | E143: =TEXT(I143,"DDDD") -> jueves | F143: =DAY(I143) -> 18 | G143: AFI | H143: ='AFI-F3'!$G$3 -> 45674 | I143: ='AFI-F3'!B8 -> 46009 | J143: ='AFI-F3'!C8 -> 10303242 | K143: ='AFI-F3'!D8 -> Ricardo Marrou | L143: ='AFI-F3'!E8 -> Ricardo.jonico@gmail.com | M143: ='AFI-F3'!F8 -> SURCO | N143: ='AFI-F3'!G8 -> FB | O143: ='AFI-F3'!H8 | P143: ='AFI-F3'!I8 -> X | ... X143: ='AFI-F3'!Q8 -> 190
B144: =B143+1 -> 5 | C144: =TEXT(I144,"Mmmm") -> diciembre | D144: =WEEKNUM(I144) -> 52 | E144: =TEXT(I144,"DDDD") -> martes | F144: =DAY(I144) -> 23 | G144: AFI | H144: ='AFI-F3'!$G$3 -> 45674 | I144: ='AFI-F3'!B9 -> 46014 | J144: ='AFI-F3'!C9 -> 44273674 | K144: ='AFI-F3'!D9 -> Ivan Salsavilca Faustino | L144: ='AFI-F3'!E9 -> ivansalsavilca@gmail.com | M144: ='AFI-F3'!F9 | N144: ='AFI-F3'!G9 | O144: ='AFI-F3'!H9 -> x | P144: ='AFI-F3'!I9 -> x | ... X144: ='AFI-F3'!Q9 -> 380
B145: =B144+1 -> 6 | C145: =TEXT(I145,"Mmmm") -> enero | D145: =WEEKNUM(I145) -> 1 | E145: =TEXT(I145,"DDDD") -> viernes | F145: =DAY(I145) -> 2 | G145: AFI | H145: ='AFI-F3'!$G$3 -> 45674 | I145: ='AFI-F3'!B10 -> 46024 | J145: ='AFI-F3'!C10 -> 77059170 | K145: ='AFI-F3'!D10 -> Nicolas Gámez | L145: ='AFI-F3'!E10 -> Nicogamez1008@gmail.com | M145: ='AFI-F3'!F10 -> Chorrillos | N145: ='AFI-F3'!G10 -> 924 714 156 | O145: ='AFI-F3'!H10 -> X | P145: ='AFI-F3'!I10 -> x | ... X145: ='AFI-F3'!Q10 -> 380
B146: =B145+1 -> 7 | C146: =TEXT(I146,"Mmmm") -> enero | D146: =WEEKNUM(I146) -> 2 | E146: =TEXT(I146,"DDDD") -> lunes | F146: =DAY(I146) -> 5 | G146: AFI | H146: ='AFI-F3'!$G$3 -> 45674 | I146: ='AFI-F3'!B11 -> 46027 | J146: ='AFI-F3'!C11 -> 42126105 | K146: ='AFI-F3'!D11 -> Manuel Buendia | L146: ='AFI-F3'!E11 -> Mbuendia4@gmail.com | M146: ='AFI-F3'!F11 -> CHACLACAYO | N146: ='AFI-F3'!G11 -> 961 082 768 | O146: ='AFI-F3'!H11 -> X | P146: ='AFI-F3'!I11 -> X | ... X146: ='AFI-F3'!Q11 -> 350
B147: =B146+1 -> 8 | C147: =TEXT(I147,"Mmmm") -> enero | D147: =WEEKNUM(I147) -> 2 | E147: =TEXT(I147,"DDDD") -> lunes | F147: =DAY(I147) -> 5 | G147: AFI | H147: ='AFI-F3'!$G$3 -> 45674 | I147: ='AFI-F3'!B12 -> 46027 | J147: ='AFI-F3'!C12 -> 41758472 | K147: ='AFI-F3'!D12 -> Liselle Prieto | L147: ='AFI-F3'!E12 -> Lisibuendia28@gmail.com | M147: ='AFI-F3'!F12 -> CHACLACAYO | N147: ='AFI-F3'!G12 -> 961 082 768 | O147: ='AFI-F3'!H12 -> X | P147: ='AFI-F3'!I12 -> X | ... X147: ='AFI-F3'!Q12 -> 350
B148: =B147+1 -> 9 | C148: =TEXT(I148,"Mmmm") -> diciembre | D148: =WEEKNUM(I148) -> 51 | E148: =TEXT(I148,"DDDD") -> lunes | F148: =DAY(I148) -> 15 | G148: AFI | H148: ='AFI-F3'!$G$3 -> 45674 | I148: ='AFI-F3'!B13 -> 46006 | J148: ='AFI-F3'!C13 -> 10734077 | K148: ='AFI-F3'!D13 -> Sandro León Anfossi | L148: ='AFI-F3'!E13 -> luciapari87@outlook.com | M148: ='AFI-F3'!F13 -> SURCO | N148: ='AFI-F3'!G13 -> 957 799 157 | O148: ='AFI-F3'!H13 -> X | P148: ='AFI-F3'!I13 | ... X148: ='AFI-F3'!Q13 -> 0
B149: =B148+1 -> 10 | C149: =TEXT(I149,"Mmmm") -> enero | D149: =WEEKNUM(I149) -> 2 | E149: =TEXT(I149,"DDDD") -> martes | F149: =DAY(I149) -> 6 | G149: AFI | H149: ='AFI-F3'!$G$3 -> 45674 | I149: ='AFI-F3'!B14 -> 46028 | J149: ='AFI-F3'!C14 -> 41570562 | K149: ='AFI-F3'!D14 -> Willy rabanal calderon | L149: ='AFI-F3'!E14 -> Rabanalwilly@gmail.com | M149: ='AFI-F3'!F14 -> Callao | N149: ='AFI-F3'!G14 -> 991 049 152 | O149: ='AFI-F3'!H14 -> x | P149: ='AFI-F3'!I14 -> x | ... X149: ='AFI-F3'!Q14 -> 380
B150: =B149+1 -> 11 | C150: =TEXT(I150,"Mmmm") -> enero | D150: =WEEKNUM(I150) -> 2 | E150: =TEXT(I150,"DDDD") -> martes | F150: =DAY(I150) -> 6 | G150: AFI | H150: ='AFI-F3'!$G$3 -> 45674 | I150: ='AFI-F3'!B15 -> 46028 | J150: ='AFI-F3'!C15 -> 48129640 | K150: ='AFI-F3'!D15 -> Bryan Ochoa Salas | L150: ='AFI-F3'!E15 -> bochoa@pucp.pe | M150: ='AFI-F3'!F15 -> Breña | N150: ='AFI-F3'!G15 -> 917 880 991 | O150: ='AFI-F3'!H15 -> x | P150: ='AFI-F3'!I15 | ... X150: ='AFI-F3'!Q15 -> 175
B151: =B150+1 -> 12 | C151: =TEXT(I151,"Mmmm") -> enero | D151: =WEEKNUM(I151) -> 2 | E151: =TEXT(I151,"DDDD") -> martes | F151: =DAY(I151) -> 6 | G151: AFI | H151: ='AFI-F3'!$G$3 -> 45674 | I151: ='AFI-F3'!B16 -> 46028 | J151: ='AFI-F3'!C16 -> 70605782 | K151: ='AFI-F3'!D16 -> Néstor Walter Villegas Macedo | L151: ='AFI-F3'!E16 -> nestor_vm1994@hotmail.com | M151: ='AFI-F3'!F16 -> Lince | N151: ='AFI-F3'!G16 -> 917 880 991 | O151: ='AFI-F3'!H16 -> x | P151: ='AFI-F3'!I16 | ... X151: ='AFI-F3'!Q16 -> 175
B152: =B151+1 -> 13 | C152: =TEXT(I152,"Mmmm") -> enero | D152: =WEEKNUM(I152) -> 2 | E152: =TEXT(I152,"DDDD") -> martes | F152: =DAY(I152) -> 6 | G152: AFI | H152: ='AFI-F3'!$G$3 -> 45674 | I152: ='AFI-F3'!B17 -> 46028 | J152: ='AFI-F3'!C17 -> 40298292 | K152: ='AFI-F3'!D17 -> Carlos Cuadra Macedo | L152: ='AFI-F3'!E17 -> carlonchocuadra@gmail.com | M152: ='AFI-F3'!F17 -> Lince | N152: ='AFI-F3'!G17 -> 917 880 991 | O152: ='AFI-F3'!H17 -> x | P152: ='AFI-F3'!I17 | ... X152: ='AFI-F3'!Q17 -> 175
... B207: =B206+1 -> 68 | C207: =TEXT(I207,"Mmmm") -> diciembre | D207: =WEEKNUM(I207) -> 52 | E207: =TEXT(I207,"DDDD") -> sábado | F207: =DAY(I207) -> 30 | G207: AFI | H207: ='AFI-F3'!$G$3 -> 45674 | I207: ='AFI-F3'!B72 | J207: ='AFI-F3'!C72 | K207: ='AFI-F3'!D72 | L207: ='AFI-F3'!E72 | M207: ='AFI-F3'!F72 | N207: ='AFI-F3'!G72 | O207: ='AFI-F3'!H72 | P207: ='AFI-F3'!I72 | ... X207: ='AFI-F3'!Q72 -> 0
B208: 1 | C208: =TEXT(I208,"Mmmm") -> diciembre | D208: =WEEKNUM(I208) -> 50 | E208: =TEXT(I208,"DDDD") -> martes | F208: =DAY(I208) -> 9 | G208: AFI | H208: ='AFI-F4'!$G$3 -> 45682 | I208: ='AFI-F4'!B5 -> 46000 | J208: ='AFI-F4'!C5 -> 44412013 | K208: ='AFI-F4'!D5 -> Nazaret judith abad zarco | L208: ='AFI-F4'!E5 -> Nazaret_abad@hotmail.com | M208: ='AFI-F4'!F5 -> SAN MIGUEL | N208: ='AFI-F4'!G5 -> 976 096 059 | O208: ='AFI-F4'!H5 -> X | P208: ='AFI-F4'!I5 | ... X208: ='AFI-F4'!Q5 -> 190
B209: =B208+1 -> 2 | C209: =TEXT(I209,"Mmmm") -> diciembre | D209: =WEEKNUM(I209) -> 50 | E209: =TEXT(I209,"DDDD") -> martes | F209: =DAY(I209) -> 9 | G209: AFI | H209: ='AFI-F4'!$G$3 -> 45682 | I209: ='AFI-F4'!B6 -> 46000 | J209: ='AFI-F4'!C6 -> 10562497 | K209: ='AFI-F4'!D6 -> Rubén Abad Zarco | L209: ='AFI-F4'!E6 -> Nazaret_abad@hotmail.com | M209: ='AFI-F4'!F6 -> SAN MIGUEL | N209: ='AFI-F4'!G6 -> 976 096 059 | O209: ='AFI-F4'!H6 -> X | P209: ='AFI-F4'!I6 | ... X209: ='AFI-F4'!Q6 -> 190
B210: =B209+1 -> 3 | C210: =TEXT(I210,"Mmmm") -> enero | D210: =WEEKNUM(I210) -> 1 | E210: =TEXT(I210,"DDDD") -> viernes | F210: =DAY(I210) -> 2 | G210: AFI | H210: ='AFI-F4'!$G$3 -> 45682 | I210: ='AFI-F4'!B7 -> 46024 | J210: ='AFI-F4'!C7 -> 76197577 | K210: ='AFI-F4'!D7 -> Anderson Achata | L210: ='AFI-F4'!E7 -> andersonachata@gmail.com | M210: ='AFI-F4'!F7 -> SAN LUIS | N210: ='AFI-F4'!G7 -> 913 872 010 | O210: ='AFI-F4'!H7 -> X | P210: ='AFI-F4'!I7 | ... X210: ='AFI-F4'!Q7 -> 190
B211: =B210+1 -> 4 | C211: =TEXT(I211,"Mmmm") -> enero | D211: =WEEKNUM(I211) -> 1 | E211: =TEXT(I211,"DDDD") -> sábado | F211: =DAY(I211) -> 3 | G211: AFI | H211: ='AFI-F4'!$G$3 -> 45682 | I211: ='AFI-F4'!B8 -> 46025 | J211: ='AFI-F4'!C8 -> 41735143 | K211: ='AFI-F4'!D8 -> Danilo Fernando Yánac Talaverano | L211: ='AFI-F4'!E8 -> Dyanact@gmail.com | M211: ='AFI-F4'!F8 -> LOS OLIVOS | N211: ='AFI-F4'!G8 -> 949 727 949 | O211: ='AFI-F4'!H8 -> X | P211: ='AFI-F4'!I8 | ... X211: ='AFI-F4'!Q8 -> 110
B212: =B211+1 -> 5 | C212: =TEXT(I212,"Mmmm") -> diciembre | D212: =WEEKNUM(I212) -> 52 | E212: =TEXT(I212,"DDDD") -> sábado | F212: =DAY(I212) -> 27 | G212: AFI | H212: ='AFI-F4'!$G$3 -> 45682 | I212: ='AFI-F4'!B9 -> 46018 | J212: ='AFI-F4'!C9 -> 40893521 | K212: ='AFI-F4'!D9 -> Rolando Farfán Gutiérrez | L212: ='AFI-F4'!E9 -> Rolandofarfang@gmail.com | M212: ='AFI-F4'!F9 -> CERCADO | N212: ='AFI-F4'!G9 -> 999 143 296 | O212: ='AFI-F4'!H9 | P212: ='AFI-F4'!I9 -> X | ... X212: ='AFI-F4'!Q9 -> 175
B213: =B212+1 -> 6 | C213: =TEXT(I213,"Mmmm") -> diciembre | D213: =WEEKNUM(I213) -> 52 | E213: =TEXT(I213,"DDDD") -> sábado | F213: =DAY(I213) -> 30 | G213: AFI | H213: ='AFI-F4'!$G$3 -> 45682 | I213: ='AFI-F4'!B10 | J213: ='AFI-F4'!C10 | K213: ='AFI-F4'!D10 | L213: ='AFI-F4'!E10 | M213: ='AFI-F4'!F10 | N213: ='AFI-F4'!G10 | O213: ='AFI-F4'!H10 | P213: ='AFI-F4'!I10 | ... X213: ='AFI-F4'!Q10 -> 0
B214: =B213+1 -> 7 | C214: =TEXT(I214,"Mmmm") -> enero | D214: =WEEKNUM(I214) -> 2 | E214: =TEXT(I214,"DDDD") -> martes | F214: =DAY(I214) -> 6 | G214: AFI | H214: ='AFI-F4'!$G$3 -> 45682 | I214: ='AFI-F4'!B11 -> 46028 | J214: ='AFI-F4'!C11 -> 44384611 | K214: ='AFI-F4'!D11 -> LUIGGI VIGO PESANTES | L214: ='AFI-F4'!E11 -> luiggijvp@gmail.com | M214: ='AFI-F4'!F11 -> PUEBLO LIBRE | N214: ='AFI-F4'!G11 | O214: ='AFI-F4'!H11 | P214: ='AFI-F4'!I11 -> X | ... X214: ='AFI-F4'!Q11 -> 200
B215: =B214+1 -> 8 | C215: =TEXT(I215,"Mmmm") -> enero | D215: =WEEKNUM(I215) -> 2 | E215: =TEXT(I215,"DDDD") -> viernes | F215: =DAY(I215) -> 9 | G215: AFI | H215: ='AFI-F4'!$G$3 -> 45682 | I215: ='Burger-F7-F8'!B24 -> 46031 | J215: ='Burger-F7-F8'!C24 -> 41914080 | K215: ='Burger-F7-F8'!D24 -> Yulisa Quispe Cuba | L215: ='Burger-F7-F8'!E24 | M215: ='Burger-F7-F8'!F24 -> EL AGUSTINO | N215: ='AFI-F4'!G12 -> 961377923 | O215: ='AFI-F4'!H12 | P215: ='AFI-F4'!I12 -> x | Q215: ='AFI-F4'!J12 -> 220 | R215: ='AFI-F4'!K12 | S215: ='AFI-F4'!L12 -> PAGO | T215: ='AFI-F4'!M12 -> YAPE JL | U215: ='AFI-F4'!N12 -> 220 | ... X215: ='AFI-F4'!Q12 -> 220
B216: =B215+1 -> 9 | C216: =TEXT(I216,"Mmmm") -> enero | D216: =WEEKNUM(I216) -> 3 | E216: =TEXT(I216,"DDDD") -> lunes | F216: =DAY(I216) -> 12 | G216: AFI | H216: ='AFI-F4'!$G$3 -> 45682 | I216: ='AFI-F4'!B13 -> 46034 | J216: ='AFI-F4'!C13 -> 70342491 | K216: ='AFI-F4'!D13 -> Jandir Rivera Quispe | L216: ='AFI-F4'!E13 -> jandir.rivera10@gmail.com | M216: ='AFI-F4'!F13 -> San Bartolo | N216: ='AFI-F4'!G13 -> 987552563 | O216: ='AFI-F4'!H13 -> X | P216: ='AFI-F4'!I13 | ... X216: ='AFI-F4'!Q13 -> 0
B217: =B216+1 -> 10 | C217: =TEXT(I217,"Mmmm") -> enero | D217: =WEEKNUM(I217) -> 3 | E217: =TEXT(I217,"DDDD") -> sábado | F217: =DAY(I217) -> 17 | G217: AFI | H217: ='AFI-F4'!$G$3 -> 45682 | I217: ='AFI-F4'!B63 -> 46039 | J217: ='AFI-F4'!C63 | K217: ='AFI-F4'!D63 -> Percy Alonso Alama Porras | L217: ='AFI-F4'!E63 -> betty2535@hotmail.com | M217: ='AFI-F4'!F63 -> BARRANCO | N217: ='AFI-F4'!G63 -> 995 747 995 | O217: ='AFI-F4'!H63 -> X | P217: ='AFI-F4'!I63 | ... S217: ='AFI-F4'!L63 -> COBR | T217: ='AFI-F4'!M14 -> YAPE JL | U217: ='AFI-F4'!N14 -> 0 | V217: ='AFI-F4'!O14 | W217: ='AFI-F4'!P14 -> Yadhira | X217: ='AFI-F4'!Q14 -> 0
B218: =B217+1 -> 11 | C218: =TEXT(I218,"Mmmm") -> enero | D218: =WEEKNUM(I218) -> 3 | E218: =TEXT(I218,"DDDD") -> sábado | F218: =DAY(I218) -> 17 | G218: AFI | H218: ='AFI-F4'!$G$3 -> 45682 | I218: ='AFI-F4'!B64 -> 46039 | J218: ='AFI-F4'!C64 | K218: ='AFI-F4'!D64 -> CAMILA MAYHUA ALVARADO | L218: ='AFI-F4'!E64 -> betty2535@hotmail.com | M218: ='AFI-F4'!F64 -> BARRANCO | N218: ='AFI-F4'!G64 | O218: ='AFI-F4'!H64 -> X | P218: ='AFI-F4'!I64 | ... S218: ='AFI-F4'!L64 -> COBR | T218: ='AFI-F4'!M15 -> YAPE JL | U218: ='AFI-F4'!N15 -> 0 | V218: ='AFI-F4'!O15 | W218: ='AFI-F4'!P15 -> Yadhira | X218: ='AFI-F4'!Q15 -> 0
B219: =B218+1 -> 12 | C219: =TEXT(I219,"Mmmm") -> enero | D219: =WEEKNUM(I219) -> 3 | E219: =TEXT(I219,"DDDD") -> lunes | F219: =DAY(I219) -> 12 | G219: AFI | H219: ='AFI-F4'!$G$3 -> 45682 | I219: ='AFI-F4'!B16 -> 46034 | J219: ='AFI-F4'!C16 -> 40493159 | K219: ='AFI-F4'!D16 -> Manuel Grados Morales | L219: ='AFI-F4'!E16 -> manuel.grados.gm@gmail.com | M219: ='AFI-F4'!F16 -> SAN ISIDRO | N219: ='AFI-F4'!G16 -> 954 580 454 | O219: ='AFI-F4'!H16 -> X | P219: ='AFI-F4'!I16 | ... X219: ='AFI-F4'!Q16 -> 190
B220: =B219+1 -> 13 | C220: =TEXT(I220,"Mmmm") -> enero | D220: =WEEKNUM(I220) -> 3 | E220: =TEXT(I220,"DDDD") -> lunes | F220: =DAY(I220) -> 12 | G220: AFI | H220: ='AFI-F4'!$G$3 -> 45682 | I220: ='AFI-F4'!B17 -> 46034 | J220: ='AFI-F4'!C17 -> 45909459 | K220: ='AFI-F4'!D17 -> Jonathan Ramírez Flor | L220: ='AFI-F4'!E17 -> joramirezf@hotmail.com | M220: ='AFI-F4'!F17 -> JESUS MARIA | N220: ='AFI-F4'!G17 -> 954 580 454 | O220: ='AFI-F4'!H17 -> X | P220: ='AFI-F4'!I17 | ... X220: ='AFI-F4'!Q17 -> 190
B221: =B220+1 -> 14 | C221: =TEXT(I221,"Mmmm") -> enero | D221: =WEEKNUM(I221) -> 3 | E221: =TEXT(I221,"DDDD") -> martes | F221: =DAY(I221) -> 13 | G221: AFI | H221: ='AFI-F4'!$G$3 -> 45682 | I221: ='AFI-F4'!B18 -> 46035 | J221: ='AFI-F4'!C18 -> 47575960 | K221: ='AFI-F4'!D18 -> Abdul Kazan Espinoza Guerra | L221: ='AFI-F4'!E18 -> Ka.carmed@gmail.com | M221: ='AFI-F4'!F18 -> RIMAC | N221: ='AFI-F4'!G18 -> 970 345 673 | O221: ='AFI-F4'!H18 -> X | P221: ='AFI-F4'!I18 | ... X221: ='AFI-F4'!Q18 -> 190
B222: =B221+1 -> 15 | C222: =TEXT(I222,"Mmmm") -> enero | D222: =WEEKNUM(I222) -> 3 | E222: =TEXT(I222,"DDDD") -> martes | F222: =DAY(I222) -> 13 | G222: AFI | H222: ='AFI-F4'!$G$3 -> 45682 | I222: ='AFI-F4'!B19 -> 46035 | J222: ='AFI-F4'!C19 -> 15753576 | K222: ='AFI-F4'!D19 -> Jaime Raúl Santa Cruz Culquicondor | L222: ='AFI-F4'!E19 -> Jaimesantacruz2306@gmail.com | M222: ='AFI-F4'!F19 -> HUARAL | N222: ='AFI-F4'!G19 -> 998 341 966 | O222: ='AFI-F4'!H19 -> X | P222: ='AFI-F4'!I19 -> X | ... X222: ='AFI-F4'!Q19 -> 360
B223: =B222+1 -> 16 | C223: =TEXT(I223,"Mmmm") -> enero | D223: =WEEKNUM(I223) -> 3 | E223: =TEXT(I223,"DDDD") -> miércoles | F223: =DAY(I223) -> 14 | G223: AFI | H223: ='AFI-F4'!$G$3 -> 45682 | I223: ='AFI-F4'!B20 -> 46036 | J223: ='AFI-F4'!C20 -> 10114558 | K223: ='AFI-F4'!D20 -> Ricardo Francisco Florian | L223: ='AFI-F4'!E20 -> francisco.rm@pucp.pe | M223: ='AFI-F4'!F20 -> SJL | N223: ='AFI-F4'!G20 -> 986 601 138 | O223: ='AFI-F4'!H20 -> X | P223: ='AFI-F4'!I20 | ... X223: ='AFI-F4'!Q20 -> 180
B224: =B223+1 -> 17 | C224: =TEXT(I224,"Mmmm") -> enero | D224: =WEEKNUM(I224) -> 3 | E224: =TEXT(I224,"DDDD") -> miércoles | F224: =DAY(I224) -> 14 | G224: AFI | H224: ='AFI-F4'!$G$3 -> 45682 | I224: ='AFI-F4'!B21 -> 46036 | J224: ='AFI-F4'!C21 -> 75527342 | K224: ='AFI-F4'!D21 -> Manuel Francisco Davalos | L224: ='AFI-F4'!E21 -> francisco.rm@pucp.pe | M224: ='AFI-F4'!F21 -> SJL | N224: ='AFI-F4'!G21 -> 986 601 138 | O224: ='AFI-F4'!H21 -> X | P224: ='AFI-F4'!I21 | ... X224: ='AFI-F4'!Q21 -> 180
B225: =B224+1 -> 18 | C225: =TEXT(I225,"Mmmm") -> enero | D225: =WEEKNUM(I225) -> 3 | E225: =TEXT(I225,"DDDD") -> martes | F225: =DAY(I225) -> 13 | G225: AFI | H225: ='AFI-F4'!$G$3 -> 45682 | I225: ='AFI-F4'!B22 -> 46035 | J225: ='AFI-F4'!C22 -> 42084574 | K225: ='AFI-F4'!D22 -> Cesar La Rosa-Sánchez Cordero | L225: ='AFI-F4'!E22 -> cesarlarosa_20@yahoo.com.pe | M225: ='AFI-F4'!F22 | N225: ='AFI-F4'!G22 | O225: ='AFI-F4'!H22 -> x | P225: ='AFI-F4'!I22 -> x | ... X225: ='AFI-F4'!Q22 -> 380
B226: =B225+1 -> 19 | C226: =TEXT(I226,"Mmmm") -> enero | D226: =WEEKNUM(I226) -> 3 | E226: =TEXT(I226,"DDDD") -> miércoles | F226: =DAY(I226) -> 14 | G226: AFI | H226: ='AFI-F4'!$G$3 -> 45682 | I226: ='AFI-F4'!B23 -> 46036 | J226: ='AFI-F4'!C23 -> 61802066 | K226: ='AFI-F4'!D23 -> Alexander Zambrano Vizcarra | L226: ='AFI-F4'!E23 | M226: ='AFI-F4'!F23 -> San Juan de Miraflores | N226: ='AFI-F4'!G23 | O226: ='AFI-F4'!H23 -> x | P226: ='AFI-F4'!I23 | ... X226: ='AFI-F4'!Q23 -> 190
B227: =B226+1 -> 20 | C227: =TEXT(I227,"Mmmm") -> enero | D227: =WEEKNUM(I227) -> 3 | E227: =TEXT(I227,"DDDD") -> miércoles | F227: =DAY(I227) -> 14 | G227: AFI | H227: ='AFI-F4'!$G$3 -> 45682 | I227: ='AFI-F4'!B24 -> 46036 | J227: ='AFI-F4'!C24 -> 61741943 | K227: ='AFI-F4'!D24 -> Fabricio Urbina Zambrano | L227: ='AFI-F4'!E24 | M227: ='AFI-F4'!F24 -> San Juan de Miraflores | N227: ='AFI-F4'!G24 | O227: ='AFI-F4'!H24 -> x | P227: ='AFI-F4'!I24 | ... X227: ='AFI-F4'!Q24 -> 190
B228: =B227+1 -> 21 | C228: =TEXT(I228,"Mmmm") -> enero | D228: =WEEKNUM(I228) -> 3 | E228: =TEXT(I228,"DDDD") -> miércoles | F228: =DAY(I228) -> 14 | G228: AFI | H228: ='AFI-F4'!$G$3 -> 45682 | I228: ='AFI-F4'!B25 -> 46036 | J228: ='AFI-F4'!C25 -> 70919834 | K228: ='AFI-F4'!D25 -> Carlos Eduardo Cumpa alayo | L228: ='AFI-F4'!E25 | M228: ='AFI-F4'!F25 -> San Juan de lurigancho | N228: ='AFI-F4'!G25 | O228: ='AFI-F4'!H25 -> x | P228: ='AFI-F4'!I25 | ... X228: ='AFI-F4'!Q25 -> 200
B229: =B228+1 -> 22 | C229: =TEXT(I229,"Mmmm") -> enero | D229: =WEEKNUM(I229) -> 3 | E229: =TEXT(I229,"DDDD") -> miércoles | F229: =DAY(I229) -> 14 | G229: AFI | H229: ='AFI-F4'!$G$3 -> 45682 | I229: ='AFI-F4'!B26 -> 46036 | J229: ='AFI-F4'!C26 -> 25728595 | K229: ='AFI-F4'!D26 -> Juan Augusto Arrunátegui Paiva | L229: ='AFI-F4'!E26 -> arrunateguijuan@gmail.com | M229: ='AFI-F4'!F26 -> Pueblo Libre | N229: ='AFI-F4'!G26 | O229: ='AFI-F4'!H26 -> x | P229: ='AFI-F4'!I26 | ... X229: ='AFI-F4'!Q26 -> 190
B230: =B229+1 -> 23 | C230: =TEXT(I230,"Mmmm") -> enero | D230: =WEEKNUM(I230) -> 3 | E230: =TEXT(I230,"DDDD") -> miércoles | F230: =DAY(I230) -> 14 | G230: AFI | H230: ='AFI-F4'!$G$3 -> 45682 | I230: ='AFI-F4'!B27 -> 46036 | J230: ='AFI-F4'!C27 -> 73171842 | K230: ='AFI-F4'!D27 -> César Augusto Arrunátegui Vásquez | L230: ='AFI-F4'!E27 -> arrunateguijuan@gmail.com | M230: ='AFI-F4'!F27 -> Pueblo libre | N230: ='AFI-F4'!G27 | O230: ='AFI-F4'!H27 -> x | P230: ='AFI-F4'!I27 -> x | ... X230: ='AFI-F4'!Q27 -> 380
... B275: =B274+1 -> 68 | C275: =TEXT(I275,"Mmmm") -> diciembre | D275: =WEEKNUM(I275) -> 52 | E275: =TEXT(I275,"DDDD") -> sábado | F275: =DAY(I275) -> 30 | G275: AFI | H275: ='AFI-F4'!$G$3 -> 45682 | I275: ='AFI-F4'!B72 | J275: ='AFI-F4'!C72 | K275: ='AFI-F4'!D72 | L275: ='AFI-F4'!E72 | M275: ='AFI-F4'!F72 | N275: ='AFI-F4'!G72 | O275: ='AFI-F4'!H72 | P275: ='AFI-F4'!I72 | ... X275: ='AFI-F4'!Q72 -> 0
B276: 1 | C276: =TEXT(I276,"Mmmm") -> enero | D276: =WEEKNUM(I276) -> 1 | E276: =TEXT(I276,"DDDD") -> viernes | F276: =DAY(I276) -> 2 | G276: AFI | H276: ='AFI-F5'!$G$3 -> 45688 | I276: ='AFI-F5'!B5 -> 46024 | J276: ='AFI-F5'!C5 -> 76197577 | K276: ='AFI-F5'!D5 -> Anderson Achata | L276: ='AFI-F5'!E5 -> andersonachata@gmail.com | M276: ='AFI-F5'!F5 -> SAN LUIS | N276: ='AFI-F5'!G5 -> 913 872 010 | O276: ='AFI-F5'!H5 -> X | P276: ='AFI-F5'!I5 | ... X276: ='AFI-F5'!Q5 -> 190
B277: =B276+1 -> 2 | C277: =TEXT(I277,"Mmmm") -> enero | D277: =WEEKNUM(I277) -> 1 | E277: =TEXT(I277,"DDDD") -> sábado | F277: =DAY(I277) -> 3 | G277: AFI | H277: ='AFI-F5'!$G$3 -> 45688 | I277: ='AFI-F5'!B6 -> 46025 | J277: ='AFI-F5'!C6 -> 41735143 | K277: ='AFI-F5'!D6 -> Danilo Fernando Yánac Talaverano | L277: ='AFI-F5'!E6 -> Dyanact@gmail.com | M277: ='AFI-F5'!F6 -> LOS OLIVOS | N277: ='AFI-F5'!G6 -> 949 727 949 | O277: ='AFI-F5'!H6 -> X | P277: ='AFI-F5'!I6 | ... X277: ='AFI-F5'!Q6 -> 0
B278: =B277+1 -> 3 | C278: =TEXT(I278,"Mmmm") -> enero | D278: =WEEKNUM(I278) -> 3 | E278: =TEXT(I278,"DDDD") -> sábado | F278: =DAY(I278) -> 17 | G278: AFI | H278: ='AFI-F5'!$G$3 -> 45688 | I278: ='AFI-F4'!B63 -> 46039 | J278: ='AFI-F4'!C63 | K278: ='AFI-F4'!D63 -> Percy Alonso Alama Porras | L278: ='AFI-F4'!E63 -> betty2535@hotmail.com | M278: ='AFI-F4'!F63 -> BARRANCO | N278: ='AFI-F4'!G63 -> 995 747 995 | O278: ='AFI-F4'!H63 -> X | P278: ='AFI-F5'!I7 -> x | Q278: ='AFI-F5'!J7 -> 0 | R278: ='AFI-F5'!K7 | S278: ='AFI-F5'!L7 | T278: ='AFI-F5'!M7 | U278: ='AFI-F5'!N7 -> 0 | V278: ='AFI-F5'!O7 | W278: ='AFI-F5'!P7 -> Yadhira | X278: ='AFI-F5'!Q7 -> 0
B279: =B278+1 -> 4 | C279: =TEXT(I279,"Mmmm") -> enero | D279: =WEEKNUM(I279) -> 3 | E279: =TEXT(I279,"DDDD") -> sábado | F279: =DAY(I279) -> 17 | G279: AFI | H279: ='AFI-F5'!$G$3 -> 45688 | I279: ='AFI-F4'!B64 -> 46039 | J279: ='AFI-F4'!C64 | K279: ='AFI-F4'!D64 -> CAMILA MAYHUA ALVARADO | L279: ='AFI-F4'!E64 -> betty2535@hotmail.com | M279: ='AFI-F4'!F64 -> BARRANCO | N279: ='AFI-F4'!G64 | O279: ='AFI-F4'!H64 -> X | P279: ='AFI-F5'!I8 | Q279: ='AFI-F5'!J8 | R279: ='AFI-F5'!K8 | S279: ='AFI-F5'!L8 | T279: ='AFI-F5'!M8 | U279: ='AFI-F5'!N8 | V279: ='AFI-F5'!O8 | W279: ='AFI-F5'!P8 | X279: ='AFI-F5'!Q8 -> 0
B280: =B279+1 -> 5 | C280: =TEXT(I280,"Mmmm") -> enero | D280: =WEEKNUM(I280) -> 2 | E280: =TEXT(I280,"DDDD") -> jueves | F280: =DAY(I280) -> 8 | G280: AFI | H280: ='AFI-F5'!$G$3 -> 45688 | I280: ='AFI-F5'!B9 -> 46030 | J280: ='AFI-F5'!C9 -> 46063723 | K280: ='AFI-F5'!D9 -> carlos ore yufre | L280: ='AFI-F5'!E9 -> carlosyufre29@gmail.com | M280: ='AFI-F5'!F9 -> los olivos | N280: ='AFI-F5'!G9 -> 948350215 | O280: ='AFI-F5'!H9 | P280: ='AFI-F5'!I9 -> X | ... X280: ='AFI-F5'!Q9 -> 0
B281: =B280+1 -> 6 | C281: =TEXT(I281,"Mmmm") -> enero | D281: =WEEKNUM(I281) -> 4 | E281: =TEXT(I281,"DDDD") -> martes | F281: =DAY(I281) -> 20 | G281: AFI | H281: ='AFI-F5'!$G$3 -> 45688 | I281: ='AFI-F5'!B10 -> 46042 | J281: ='AFI-F5'!C10 -> 20063027 | K281: ='AFI-F5'!D10 -> Irene Delma Calderón Marcos | L281: ='AFI-F5'!E10 -> irene_delma11@hotmail.com | M281: ='AFI-F5'!F10 -> CERCADO | N281: ='AFI-F5'!G10 -> 982 593 099 | O281: ='AFI-F5'!H10 -> X | P281: ='AFI-F5'!I10 | ... X281: ='AFI-F5'!Q10 -> 380
B282: =B281+1 -> 7 | C282: =TEXT(I282,"Mmmm") -> enero | D282: =WEEKNUM(I282) -> 4 | E282: =TEXT(I282,"DDDD") -> martes | F282: =DAY(I282) -> 20 | G282: AFI | H282: ='AFI-F5'!$G$3 -> 45688 | I282: ='AFI-F5'!B11 -> 46042 | J282: ='AFI-F5'!C11 -> 41455446 | K282: ='AFI-F5'!D11 -> Eder Genaro Estrada Montañez | L282: ='AFI-F5'!E11 -> eder16221@gmail.com | M282: ='AFI-F5'!F11 -> Callao | N282: ='AFI-F5'!G11 -> 51977709418 | O282: ='AFI-F5'!H11 | P282: ='AFI-F5'!I11 -> x | ... X282: ='AFI-F5'!Q11 -> 190
B283: =B282+1 -> 8 | C283: =TEXT(I283,"Mmmm") -> enero | D283: =WEEKNUM(I283) -> 4 | E283: =TEXT(I283,"DDDD") -> martes | F283: =DAY(I283) -> 20 | G283: AFI | H283: ='AFI-F5'!$G$3 -> 45688 | I283: ='AFI-F5'!B12 -> 46042 | J283: ='AFI-F5'!C12 -> 44211612 | K283: ='AFI-F5'!D12 -> Victor Caballero | L283: ='AFI-F5'!E12 -> victorcaballeror@gmail.com | M283: ='AFI-F5'!F12 -> san Borja | N283: ='AFI-F5'!G12 -> 51944252125 | O283: ='AFI-F5'!H12 | P283: ='AFI-F5'!I12 -> x | ... X283: ='AFI-F5'!Q12 -> 0
B284: =B283+1 -> 9 | C284: =TEXT(I284,"Mmmm") -> enero | D284: =WEEKNUM(I284) -> 4 | E284: =TEXT(I284,"DDDD") -> miércoles | F284: =DAY(I284) -> 21 | G284: AFI | H284: ='AFI-F5'!$G$3 -> 45688 | I284: ='AFI-F5'!B13 -> 46043 | J284: ='AFI-F5'!C13 -> 10117893 | K284: ='AFI-F5'!D13 -> Juan Valencia León | L284: ='AFI-F5'!E13 -> jvl.juanvalencialeon@gmail.com | M284: ='AFI-F5'!F13 -> SJL | N284: ='AFI-F5'!G13 -> 962 075 283 | O284: ='AFI-F5'!H13 | P284: ='AFI-F5'!I13 -> x | ... X284: ='AFI-F5'!Q13 -> 195
B285: =B284+1 -> 10 | C285: =TEXT(I285,"Mmmm") -> enero | D285: =WEEKNUM(I285) -> 4 | E285: =TEXT(I285,"DDDD") -> miércoles | F285: =DAY(I285) -> 21 | G285: AFI | H285: ='AFI-F5'!$G$3 -> 45688 | I285: ='AFI-F4'!B52 -> 46043 | J285: ='AFI-F4'!C52 -> 41202552 | K285: ='AFI-F4'!D52 -> José Andrés Ventura Panta | L285: ='AFI-F4'!E52 -> Karina.chz@hotmail.com | M285: ='AFI-F5'!F13 -> SJL | N285: ='AFI-F4'!G52 -> 960 258 096 | O285: ='AFI-F4'!H52 | P285: ='AFI-F5'!I14 -> X | Q285: ='AFI-F5'!J14 -> 175 | R285: ='AFI-F5'!K14 -> 175 | S285: ='AFI-F5'!L14 -> COBR | T285: ='AFI-F5'!M14 -> PLIN JL | U285: ='AFI-F5'!N14 -> 175 | V285: ='AFI-F5'!O14 -> 175 | W285: ='AFI-F5'!P14 -> Sofia | X285: ='AFI-F5'!Q14 -> 350
B286: =B285+1 -> 11 | C286: =TEXT(I286,"Mmmm") -> enero | D286: =WEEKNUM(I286) -> 4 | E286: =TEXT(I286,"DDDD") -> miércoles | F286: =DAY(I286) -> 21 | G286: AFI | H286: ='AFI-F5'!$G$3 -> 45688 | I286: ='AFI-F4'!B53 -> 46043 | J286: ='AFI-F4'!C53 -> 004684587 | K286: ='AFI-F4'!D53 -> Anna Karina Colmenares Hernández | L286: ='AFI-F4'!E53 -> Karina.chz@hotmail.com | M286: ='AFI-F4'!F53 -> MIRAFLORES | N286: ='AFI-F4'!G53 -> 960 258 096 | O286: ='AFI-F4'!H53 | P286: ='AFI-F5'!I15 -> X | Q286: ='AFI-F5'!J15 -> 175 | R286: ='AFI-F5'!K15 -> 175 | S286: ='AFI-F5'!L15 -> COBR | T286: ='AFI-F5'!M15 -> PLIN JL | U286: ='AFI-F5'!N15 -> 175 | V286: ='AFI-F5'!O15 -> 175 | W286: ='AFI-F5'!P15 -> Sofia | X286: ='AFI-F5'!Q15 -> 350
B287: =B286+1 -> 12 | C287: =TEXT(I287,"Mmmm") -> enero | D287: =WEEKNUM(I287) -> 4 | E287: =TEXT(I287,"DDDD") -> jueves | F287: =DAY(I287) -> 22 | G287: AFI | H287: ='AFI-F5'!$G$3 -> 45688 | I287: ='AFI-F5'!B16 -> 46044 | J287: ='AFI-F5'!C16 -> 20538382598 | K287: ='AFI-F5'!D16 -> César Domínguez Añanca | L287: ='AFI-F5'!E16 -> serfafain.sac@hotmail.com | M287: ='AFI-F5'!F16 -> Callao | N287: ='AFI-F5'!G16 -> 51998294866 | O287: ='AFI-F5'!H16 | P287: ='AFI-F5'!I16 -> X | ... X287: ='AFI-F5'!Q16 -> 200
B288: =B287+1 -> 13 | C288: =TEXT(I288,"Mmmm") -> diciembre | D288: =WEEKNUM(I288) -> 52 | E288: =TEXT(I288,"DDDD") -> sábado | F288: =DAY(I288) -> 30 | G288: AFI | H288: ='AFI-F5'!$G$3 -> 45688 | I288: ='AFI-F5'!B17 | J288: ='AFI-F5'!C17 | K288: ='AFI-F5'!D17 | L288: ='AFI-F5'!E17 | M288: ='AFI-F5'!F17 | N288: ='AFI-F5'!G17 | O288: ='AFI-F5'!H17 | P288: ='AFI-F5'!I17 | ... X288: ='AFI-F5'!Q17 -> 180
B289: =B288+1 -> 14 | C289: =TEXT(I289,"Mmmm") -> enero | D289: =WEEKNUM(I289) -> 4 | E289: =TEXT(I289,"DDDD") -> viernes | F289: =DAY(I289) -> 23 | G289: AFI | H289: ='AFI-F5'!$G$3 -> 45688 | I289: ='AFI-F5'!B18 -> 46045 | J289: ='AFI-F5'!C18 -> 44767965 | K289: ='AFI-F5'!D18 -> Massiel Karolina Ayala Guerra | L289: ='AFI-F5'!E18 | M289: ='AFI-F5'!F18 | N289: ='AFI-F5'!G18 | O289: ='AFI-F5'!H18 | P289: ='AFI-F5'!I18 -> x | ... X289: ='AFI-F5'!Q18 -> 0
B290: =B289+1 -> 15 | C290: =TEXT(I290,"Mmmm") -> enero | D290: =WEEKNUM(I290) -> 4 | E290: =TEXT(I290,"DDDD") -> sábado | F290: =DAY(I290) -> 24 | G290: AFI | H290: ='AFI-F5'!$G$3 -> 45688 | I290: ='AFI-F5'!B19 -> 46046 | J290: ='AFI-F5'!C19 -> 41855242 | K290: ='AFI-F5'!D18 -> Massiel Karolina Ayala Guerra | L290: ='AFI-F5'!E19 -> Jimmijoel123@hotmail.com | M290: ='AFI-F5'!F19 -> Huacho | N290: ='AFI-F5'!G19 -> 934091909 | O290: ='AFI-F5'!H19 -> X | P290: ='AFI-F5'!I19 -> X | Q290: ='AFI-F5'!J19 -> 200 | R290: ='AFI-F5'!K19 -> 150 | S290: ='AFI-F5'!L19 -> COBR | ... X290: ='AFI-F5'!Q19 -> 350
B291: =B290+1 -> 16 | C291: =TEXT(I291,"Mmmm") -> enero | D291: =WEEKNUM(I291) -> 5 | E291: =TEXT(I291,"DDDD") -> domingo | F291: =DAY(I291) -> 25 | G291: AFI | H291: ='AFI-F5'!$G$3 -> 45688 | I291: ='AFI-F5'!B20 -> 46047 | J291: ='AFI-F5'!C20 -> 40 767009 | K291: ='AFI-F5'!D20 -> Angela Geraldine quiñones granados | L291: ='AFI-F5'!E20 -> Jimmijoel123@hotmail.com | M291: ='AFI-F5'!F20 -> Huacho | N291: ='AFI-F5'!G20 -> 934091909 | O291: ='AFI-F5'!H20 -> X | P291: ='AFI-F5'!I20 -> X | ... X291: ='AFI-F5'!Q20 -> 350
B292: =B291+1 -> 17 | C292: =TEXT(I292,"Mmmm") -> enero | D292: =WEEKNUM(I292) -> 4 | E292: =TEXT(I292,"DDDD") -> sábado | F292: =DAY(I292) -> 24 | G292: AFI | H292: ='AFI-F5'!$G$3 -> 45688 | I292: ='AFI-F5'!B21 -> 46046 | J292: ='AFI-F5'!C21 -> 72190417 | K292: ='AFI-F5'!D21 -> Omar Bruno Guillén Sánchez | L292: ='AFI-F5'!E21 -> brunohuarcaya2@gmail.com | M292: ='AFI-F5'!F21 -> SJM | N292: ='AFI-F5'!G21 | O292: ='AFI-F5'!H21 | P292: ='AFI-F5'!I21 -> x | ... X292: ='AFI-F5'!Q21 -> 0
B293: =B292+1 -> 18 | C293: =TEXT(I293,"Mmmm") -> enero | D293: =WEEKNUM(I293) -> 5 | E293: =TEXT(I293,"DDDD") -> domingo | F293: =DAY(I293) -> 25 | G293: AFI | H293: ='AFI-F5'!$G$3 -> 45688 | I293: ='AFI-F5'!B22 -> 46047 | J293: ='AFI-F5'!C22 | K293: ='AFI-F5'!D22 -> wilbert palomino | L293: ='AFI-F5'!E22 -> wpa.rocaalta@gmail.com | M293: ='AFI-F5'!F22 -> El Agustino | N293: ='AFI-F5'!G22 -> 51987402177 | O293: ='AFI-F5'!H22 | P293: ='AFI-F5'!I22 -> x | ... X293: ='AFI-F5'!Q22 -> 190
B294: =B293+1 -> 19 | C294: =TEXT(I294,"Mmmm") -> enero | D294: =WEEKNUM(I294) -> 5 | E294: =TEXT(I294,"DDDD") -> lunes | F294: =DAY(I294) -> 26 | G294: AFI | H294: ='AFI-F5'!$G$3 -> 45688 | I294: ='AFI-F5'!B23 -> 46048 | J294: ='AFI-F5'!C23 -> *08537300 | K294: ='AFI-F5'!D23 -> Fabio Martin Vilca Romero | L294: ='AFI-F5'!E23 -> vrmartin1966@gmail.com | M294: ='AFI-F5'!F23 -> Pueblo Libre | N294: ='AFI-F5'!G23 -> 998 177 293 | O294: ='AFI-F5'!H23 -> x | P294: ='AFI-F5'!I23 | ... X294: ='AFI-F5'!Q23 -> 150
B295: =B294+1 -> 20 | C295: =TEXT(I295,"Mmmm") -> enero | D295: =WEEKNUM(I295) -> 5 | E295: =TEXT(I295,"DDDD") -> lunes | F295: =DAY(I295) -> 26 | G295: AFI | H295: ='AFI-F5'!$G$3 -> 45688 | I295: ='AFI-F5'!B24 -> 46048 | J295: ='AFI-F5'!C24 -> ⁠15434915 | K295: ='AFI-F5'!D24 -> Alicia Ysabel Huaman Álvarez | L295: ='AFI-F5'!E24 -> 4. ⁠omar_antonio_2015@hotmail.com | M295: ='AFI-F5'!F24 -> Surco | N295: ='AFI-F5'!G24 -> 970 363 381 | O295: ='AFI-F5'!H24 -> x | P295: ='AFI-F5'!I24 | ... X295: ='AFI-F5'!Q24 -> 380
B296: =B295+1 -> 21 | C296: =TEXT(I296,"Mmmm") -> enero | D296: =WEEKNUM(I296) -> 5 | E296: =TEXT(I296,"DDDD") -> martes | F296: =DAY(I296) -> 27 | G296: AFI | H296: ='AFI-F5'!$G$3 -> 45688 | I296: ='AFI-F5'!B25 -> 46049 | J296: ='AFI-F5'!C25 -> 42949843 | K296: ='AFI-F5'!D25 -> Jesús Ángel Ramos Salas | L296: ='AFI-F5'!E25 -> ramossalasjesus@gmail.com | M296: ='AFI-F5'!F25 -> Villa el Salvador | N296: ='AFI-F5'!G25 -> 987 351 312 | O296: ='AFI-F5'!H25 | P296: ='AFI-F5'!I25 -> x | ... X296: ='AFI-F5'!Q25 -> 220
B297: =B296+1 -> 22 | C297: =TEXT(I297,"Mmmm") -> enero | D297: =WEEKNUM(I297) -> 5 | E297: =TEXT(I297,"DDDD") -> martes | F297: =DAY(I297) -> 27 | G297: AFI | H297: ='AFI-F5'!$G$3 -> 45688 | I297: ='AFI-F5'!B26 -> 46049 | J297: ='AFI-F5'!C26 -> 43889926 | K297: ='AFI-F5'!D26 -> Nikola Vera Torres | L297: ='AFI-F5'!E26 -> Nikolavera26@gmail.com | M297: ='AFI-F5'!F26 -> SJM | N297: ='AFI-F5'!G26 -> 938 375 442 | O297: ='AFI-F5'!H26 -> X | P297: ='AFI-F5'!I26 | ... X297: ='AFI-F5'!Q26 -> 82.5
B298: =B297+1 -> 23 | C298: =TEXT(I298,"Mmmm") -> enero | D298: =WEEKNUM(I298) -> 5 | E298: =TEXT(I298,"DDDD") -> martes | F298: =DAY(I298) -> 27 | G298: AFI | H298: ='AFI-F5'!$G$3 -> 45688 | I298: ='AFI-F5'!B27 -> 46049 | J298: ='AFI-F5'!C27 -> 81007981 | K298: ='AFI-F5'!D27 -> Megan Vera Tapia | L298: ='AFI-F5'!E27 -> Nikolavera26@gmail.com | M298: ='AFI-F5'!F27 -> SJM | N298: ='AFI-F5'!G27 -> 938 375 442 | O298: ='AFI-F5'!H27 -> X | P298: ='AFI-F5'!I27 | ... X298: ='AFI-F5'!Q27 -> 82.5
B299: =B298+1 -> 24 | C299: =TEXT(I299,"Mmmm") -> enero | D299: =WEEKNUM(I299) -> 5 | E299: =TEXT(I299,"DDDD") -> martes | F299: =DAY(I299) -> 27 | G299: AFI | H299: ='AFI-F5'!$G$3 -> 45688 | I299: ='AFI-F5'!B28 -> 46049 | J299: ='AFI-F5'!C28 -> 42506745 | K299: ='AFI-F5'!D28 -> Santiago Alex Loayza Briceño | L299: ='AFI-F5'!E28 -> saloayzab@gmail.com | M299: ='AFI-F5'!F28 -> Trujillo | N299: ='AFI-F5'!G28 -> 942 839 138 | O299: ='AFI-F5'!H28 -> x | P299: ='AFI-F5'!I28 -> x | ... X299: ='AFI-F5'!Q28 -> 380
B300: =B299+1 -> 25 | C300: =TEXT(I300,"Mmmm") -> enero | D300: =WEEKNUM(I300) -> 5 | E300: =TEXT(I300,"DDDD") -> martes | F300: =DAY(I300) -> 27 | G300: AFI | H300: ='AFI-F5'!$G$3 -> 45688 | I300: ='AFI-F5'!B29 -> 46049 | J300: ='AFI-F5'!C29 -> 47428047 | K300: ='AFI-F5'!D29 -> José Freundt Montoya | L300: ='AFI-F5'!E29 -> Je.freundt@hotmail.com | M300: ='AFI-F5'!F29 -> LINCE | N300: ='AFI-F5'!G29 -> 944 368 518 | O300: ='AFI-F5'!H29 -> X | P300: ='AFI-F5'!I29 | ... X300: ='AFI-F5'!Q29 -> 200
B301: =B300+1 -> 26 | C301: =TEXT(I301,"Mmmm") -> enero | D301: =WEEKNUM(I301) -> 5 | E301: =TEXT(I301,"DDDD") -> martes | F301: =DAY(I301) -> 27 | G301: AFI | H301: ='AFI-F5'!$G$3 -> 45688 | I301: ='AFI-F5'!B30 -> 46049 | J301: ='AFI-F5'!C30 -> 48263528 | K301: ='AFI-F5'!D30 -> Mercy Apaza Cayó | L301: ='AFI-F5'!E30 -> mercyapazacayod@gmail.com | M301: ='AFI-F5'!F30 | N301: ='AFI-F5'!G30 -> 982 022 591 | O301: ='AFI-F5'!H30 -> x | P301: ='AFI-F5'!I30 -> x | ... X301: ='AFI-F5'!Q30 -> 380
B302: =B301+1 -> 27 | C302: =TEXT(I302,"Mmmm") -> enero | D302: =WEEKNUM(I302) -> 5 | E302: =TEXT(I302,"DDDD") -> miércoles | F302: =DAY(I302) -> 28 | G302: AFI | H302: ='AFI-F5'!$G$3 -> 45688 | I302: ='AFI-F5'!B31 -> 46050 | J302: ='AFI-F5'!C31 -> *08057676 | K302: ='AFI-F5'!D31 -> Cornelio ortiz jaimes | L302: ='AFI-F5'!E31 -> cimacorsac@hotmail.com | M302: ='AFI-F5'!F31 -> Puente Piedra | N302: ='AFI-F5'!G31 | O302: ='AFI-F5'!H31 -> x | P302: ='AFI-F5'!I31 | ... X302: ='AFI-F5'!Q31 -> 220
... B336: =B335+1 -> 61 | C336: =TEXT(I336,"Mmmm") -> enero | D336: =WEEKNUM(I336) -> 5 | E336: =TEXT(I336,"DDDD") -> sábado | F336: =DAY(I336) -> 31 | G336: AFI | H336: ='AFI-F5'!$G$3 -> 45688 | I336: ='AFI-F5'!B65 -> 46053 | J336: ='AFI-F5'!C65 | K336: ='AFI-F5'!D65 -> ALISON PALOMINO | L336: ='AFI-F5'!E65 | M336: ='AFI-F5'!F65 | N336: ='AFI-F5'!G65 | O336: ='AFI-F5'!H65 -> X | P336: ='AFI-F5'!I65 | ... X336: ='AFI-F5'!Q65 -> 190
B337: =B336+1 -> 62 | C337: =TEXT(I337,"Mmmm") -> enero | D337: =WEEKNUM(I337) -> 5 | E337: =TEXT(I337,"DDDD") -> viernes | F337: =DAY(I337) -> 30 | G337: AFI | H337: ='AFI-F5'!$G$3 -> 45688 | I337: ='AFI-F5'!B64 -> 46052 | J337: ='AFI-F5'!C66 | K337: ='AFI-F5'!D64 -> Frank Goytisolo Ruiz | L337: ='AFI-F5'!E66 | M337: ='AFI-F5'!F66 | N337: ='AFI-F5'!G66 | O337: ='AFI-F5'!H66 -> X | P337: ='AFI-F5'!I66 | Q337: ='AFI-F5'!J66 -> 190 | R337: ='AFI-F5'!K66 | S337: ='AFI-F5'!L66 -> PAGO | ... X337: ='AFI-F5'!Q66 -> 190
B338: =B337+1 -> 63 | C338: =TEXT(I338,"Mmmm") -> diciembre | D338: =WEEKNUM(I338) -> 52 | E338: =TEXT(I338,"DDDD") -> sábado | F338: =DAY(I338) -> 30 | G338: AFI | H338: ='AFI-F5'!$G$3 -> 45688 | I338: ='AFI-F5'!B67 | J338: ='AFI-F5'!C67 | K338: ='AFI-F5'!D67 | L338: ='AFI-F5'!E67 | M338: ='AFI-F5'!F67 | N338: ='AFI-F5'!G67 | O338: ='AFI-F5'!H67 | P338: ='AFI-F5'!I67 | ... X338: ='AFI-F5'!Q67 -> 0
...

Sheet TD
B2: 1 TD - VENTA ACTUAL POR VENDEDOR GENERAL
B19: 2 TD - VENTA ACTUAL POR PRODUCTO GENERAL
B35: 3 TD - RESUMEN DE VENTA ACTUAL POR PRODUCTO | F35: 4 TD - RESUMEN DE VENTA ACTUAL POR VENDEDOR
B48: 5 TD - VENTA SEMANAL PRODUCTOS
B63: 6 TD - VENTA SEMANAL ASESOR

Sheet AFI-F1
A1: -
A2: CONTROL DE REGISTRO PARTICIPANTES
A3: PARRILLERO AFICIONADO | G3: 45661
A4: ID | B4: FE_ REGISTRO | C4: DNI | D4: NOMBRES Y APELLIDOS | E4: EMAIL | F4: DISTRITO | G4: WSP | H4: BB1 | I4: BB2 | J4: MONTO | K4: xCOBRAR | L4: ESTADO | M4: CUENTA | N4: INGRESO | O4: SALDO | P4: VENDEDOR | Q4: TOTAL | R4: OBSERVACION
A5: 1 | B5: 46008 | C5: 72041694 | D5: Sebastian Castillo | E5: sebastiancm@outlook.com | F5: BARRANCO | G5: 998 690 869 | H5: X | J5: 250 | L5: PAGO | M5: YAPE JL | N5: 250 | P5: Yadhira | Q5: =N5+O5 -> 250
A6: =A5+1 -> 2 | B6: 46011 | C6: 75931158 | D6: Daniel Rojas Salas | E6: juanchadrs@gmail.com | F6: la victoria | H6: X | J6: 190 | L6: PAGO | M6: YAPE JL | N6: 190 | P6: Greici | Q6: =N6+O6 -> 190
A7: =A6+1 -> 3 | B7: 46011 | C7: 25631173 | D7: Miriam Salas Guevara | E7: elysalas2004@hotmail.com | F7: villa el salvador | H7: X | J7: 190 | L7: PAGO | M7: YAPE JL | N7: 190 | P7: Greici | Q7: =N7+O7 -> 190
A8: =A7+1 -> 4 | Q8: =N8+O8 -> 0 | R8: paso para 11/01
A9: =A8+1 -> 5 | B9: 45970 | C9: 75728889 | D9: Juan Carlos Vidal Molina | E9: hellenleon7@gmail.com | F9: CHACLACAYO | G9: 989 356 823 | H9: X | J9: 110 | K9: 110 | L9: COBR | M9: YAPE JL | N9: 110 | O9: 110 | P9: Yadhira | Q9: =N9+O9 -> 220
A10: =A9+1 -> 6 | B10: 46017 | C10: 44000113 | D10: CESAR KENNY YACARINI PEREYRA | E10: ckyacariniman2@gmail.com | F10: SJL | G10: 947 169 905 | H10: X | J10: 95 | K10: 95 | L10: COBR | M10: PLIN JL | N10: 95 | O10: 95 | P10: Greici | Q10: =N10+O10 -> 190
A11: =A10+1 -> 7 | B11: 46017 | C11: 43619681 | D11: Ronald elvis quispe gil | E11: Reqg_672@hotmail.com | F11: SJL | H11: X | J11: 95 | K11: 95 | L11: COBR | M11: PLIN JL | N11: 95 | O11: 95 | P11: Greici | Q11: =N11+O11 -> 190
A12: =A11+1 -> 8 | B12: 46017 | C12: 43943113 | D12: Flor de maria Guevara | E12: Gerencia@imelin.com.pe | F12: SJL | H12: X | J12: 95 | K12: 95 | L12: COBR | M12: PLIN JL | N12: 95 | O12: 95 | P12: Greici | Q12: =N12+O12 -> 190
A13: =A12+1 -> 9 | B13: 46020 | D13: Franco Nieto Ponce | H13: x | J13: 190 | L13: PAGO | M13: PLIN JL | N13: 190 | P13: Katherine | Q13: =N13+O13 -> 190
A14: =A13+1 -> 10 | B14: 46020 | D14: Luis Enrique Nieto Arauco | H14: x | J14: 190 | L14: PAGO | M14: PLIN JL | N14: 190 | P14: Katherine | Q14: =N14+O14 -> 190
A15: =A14+1 -> 11 | B15: 46020 | D15: Gladys Montes | F15: SJL | H15: x | J15: 50 | K15: 125 | L15: COBR | M15: PLIN JL | N15: 50 | O15: 125 | P15: Katherine | Q15: =N15+O15 -> 175
A16: =A15+1 -> 12 | B16: 46020 | D16: Fernando Alfredo Auqui Cerron | F16: SJL | H16: x | J16: 50 | K16: 125 | L16: COBR | M16: PLIN JL | N16: 50 | O16: 125 | P16: Katherine | Q16: =N16+O16 -> 175
A17: =A16+1 -> 13 | B17: 46020 | D17: Gianfranco Auqui Guerrero | F17: SJL | H17: x | J17: 50 | K17: 125 | L17: COBR | M17: PLIN JL | N17: 50 | O17: 125 | P17: Katherine | Q17: =N17+O17 -> 175
A18: =A17+1 -> 14 | B18: 46020 | D18: Germán Auqui Cerrón | F18: SJL | H18: x | J18: 50 | K18: 125 | L18: COBR | M18: PLIN JL | N18: 50 | O18: 125 | P18: Katherine | Q18: =N18+O18 -> 175
A19: =A18+1 -> 15 | B19: 46021 | C19: 49035262 | D19: Rafael Antony Urbina Peña | E19: rafaelurbi24@gmail.com | F19: LOS OLIVOS | H19: X | J19: 350 | L19: PAGO | M19: YAPE JL | N19: 350 | P19: Yadhira | Q19: =N19+O19 -> 350
A20: =A19+1 -> 16 | B20: 46022 | C20: 71486933 | D20: Roberto Benites Aguilar | E20: benites.07@hotmail.com | H20: x | J20: 220 | L20: PAGO | M20: YAPE JL | N20: 220 | P20: Katherine | Q20: =N20+O20 -> 220
A21: =A20+1 -> 17 | B21: 46022 | C21: 46910475 | D21: Ernesto De La Cruz | E21: ernesto199124@hotmail.com | F21: Chosica | H21: x | J21: 190 | L21: PAGO | M21: YAPE JL | N21: 190 | P21: Katherine | Q21: =N21+O21 -> 190
A22: =A21+1 -> 18 | B22: 46022 | D22: Hugo De La Cruz | F22: Chosica | H22: x | J22: 100 | L22: PAGO | M22: YAPE JL | N22: 100 | P22: Katherine | Q22: =N22+O22 -> 100
A23: =A22+1 -> 19 | B23: 46024 | C23: 40677695 | D23: Antonio Lora | E23: antoniolorac@gmail.com | F23: SURCO | H23: X | J23: 190 | L23: PAGO | M23: PLIN JL | N23: 190 | P23: Yadhira | Q23: =N23+O23 -> 190
A24: =A23+1 -> 20 | B24: 46024 | C24: 08553072 | D24: Luis Lora Reyes | E24: antoniolorac@gmail.com | F24: SURCO | H24: X | J24: 190 | L24: PAGO | M24: PLIN JL | N24: 190 | P24: Yadhira | Q24: =N24+O24 -> 190
A25: =A24+1 -> 21 | B25: 46024 | C25: 44041233 | D25: Rosa Juana Mogrovejo Sihue | E25: msk.rosa@gmail.com | F25: San Juan de Lurigancho | G25: 960 142 095 | H25: x | J25: 95 | K25: 95 | L25: COBR | M25: PLIN JL | N25: 95 | O25: 95 | P25: Sofia | Q25: =N25+O25 -> 190
A26: =A25+1 -> 22 | B26: 46025 | C26: 09312996 | D26: Hernán Vidal Ulloa | E26: havu20@gmail.com | F26: La Molina | G26: 965 007 792 | H26: x | J26: 190 | L26: PAGO | M26: YAPE JL | N26: 190 | P26: Sofia | Q26: =N26+O26 -> 190
A27: =A26+1 -> 23 | B27: 46024 | C27: 71460870 | D27: Gustavo Enrique Benites Aguilar | E27: gustavo.gba07@hotmail.com | F27: LINCE | G27: 991 714 494 | H27: X | J27: 220 | L27: PAGO | M27: PLIN JL | N27: 220 | P27: Yadhira | Q27: =N27+O27 -> 220
A28: =A27+1 -> 24 | B28: 46024 | C28: 42296972 | D28: Jose Gabriel Janampa Osores | E28: janampaosores@gmail.com | H28: x | J28: 190 | L28: PAGO | M28: PLIN JL | N28: 190 | P28: Katherine | Q28: =N28+O28 -> 190
A29: =A28+1 -> 25 | B29: 46024 | C29: 47162607 | D29: Deessiree Menendez ortiz | E29: deessiree16@hotmail.com | F29: CALLAO | G29: 958 154 071 | H29: X | J29: 175 | K29: 175 | L29: COBR | M29: MERC-PAG | N29: 167.2 | O29: 167.2 | P29: Yadhira | Q29: =N29+O29 -> 334.4
A30: =A29+1 -> 26 | B30: 46024 | C30: 41397674 | D30: Arnaldo Guardamino cavezas | E30: Arn_g2005@hotmail | F30: CALLAO | G30: 958 154 071 | H30: X | J30: 175 | K30: 175 | L30: COBR | M30: MERC-PAG | N30: 167.2 | O30: 167.2 | P30: Yadhira | Q30: =N30+O30 -> 334.4
A31: =A30+1 -> 27 | B31: 46024 | C31: 72413600 | D31: Daniel Ricardo moran Chávez | E31: danielpupunovich5@hotmail.com | G31: 988 766 216 | H31: X | J31: 190 | L31: PAGO | M31: PLIN JL | N31: 190 | P31: Yadhira | Q31: =N31+O31 -> 190
A32: =A31+1 -> 28 | B32: 46024 | D32: Frank Alonso Bautista Cucho | H32: x | J32: 190 | L32: PAGO | M32: PLIN JL | N32: 190 | P32: Katherine | Q32: =N32+O32 -> 190
A33: =A32+1 -> 29 | B33: 46024 | C33: 71523029 | D33: Aaron Castillo | H33: x | J33: 190 | L33: PAGO | M33: YAPE JL | N33: 190 | P33: Katherine | Q33: =N33+O33 -> 190
A34: =A33+1 -> 30 | B34: 46024 | C34: 40697850 | D34: Sergio Armando Lopez Saldaña | E34: Sergio.lsaldana@gmail.com | F34: Victoria | G34: 987 809 308 | H34: x | J34: 190 | L34: PAGO | M34: YAPE JL | N34: 190 | P34: Sofia | Q34: =N34+O34 -> 190
A35: =A34+1 -> 31 | B35: 46024 | C35: 07524459 | D35: José pineda sifuentes | E35: jose.pineda@ae.edu.pe | F35: SAN ISIDRO | G35: 981 398 282 | H35: X | J35: 175 | L35: PAGO | M35: PLIN JL | N35: 175 | P35: Yadhira | Q35: =N35+O35 -> 175
A36: =A35+1 -> 32 | B36: 46024 | D36: Ana Paula Pineda | F36: SAN ISIDRO | H36: X | J36: 100 | L36: PAGO | M36: PLIN JL | N36: 100 | P36: Yadhira | Q36: =N36+O36 -> 100 | R36: MENOR DE 10 AÑOS
A37: =A36+1 -> 33 | B37: 46024 | C37: 42048172 | D37: Luis Esteban Ramos Nicoll | E37: luisramosnicoll@gmail.com | H37: x | J37: 180 | L37: PAGO | M37: BCP JL | N37: 180 | P37: Katherine | Q37: =N37+O37 -> 180
A38: =A37+1 -> 34 | B38: 46025 | C38: 32992113 | D38: Herbert Ricardo Arroyo Vilchez | E38: hricardoarroyov@gmail.com | F38: VES | G38: 976 352 593 | H38: X | J38: 95 | K38: 95 | L38: COBR | M38: PLIN JL | N38: 95 | O38: 95 | P38: Yadhira | Q38: =N38+O38 -> 190
A39: =A38+1 -> 35 | B39: 46025 | C39: 16683079 | D39: Ruth Goyzueta Valencia | E39: rmgvalencia@hotmail.com | F39: La Molina | G39: 965 007 792 | H39: x | J39: 190 | L39: PAGO | M39: YAPE JL | N39: 190 | P39: Sofia | Q39: =N39+O39 -> 190
A40: =A39+1 -> 36 | B40: 46025 | C40: 10116845 | D40: Isabel Cecilia granza toro | F40: EL AGUSTINO | G40: 951 684 925 | H40: X | J40: 220 | L40: PAGO | M40: BCP EPP | N40: 220 | P40: Yadhira | Q40: =N40+O40 -> 220
A41: =A40+1 -> 37 | B41: 46025 | D41: Ana Isabel Tello granza | F41: EL AGUSTINO | G41: 951 684 925 | H41: X | J41: 220 | L41: PAGO | M41: BCP EPP | N41: 220 | P41: Yadhira | Q41: =N41+O41 -> 220
A42: =A41+1 -> 38 | B42: 46384 | D42: FRANCIS GARCÍA ARISTA | H42: X | J42: 190 | L42: PAGO | M42: PLIN JL | N42: 190 | P42: Katherine | Q42: =N42+O42 -> 190
A43: =A42+1 -> 39 | B43: 46032 | D43: ROLANDO | H43: X | J43: 0 | L43: PAGO | N43: 0 | P43: Greici | Q43: =N43+O43 -> 0
A44: =A43+1 -> 40 | Q44: =N44+O44 -> 0
A45: =A44+1 -> 41 | Q45: =N45+O45 -> 0
A46: =A45+1 -> 42 | Q46: =N46+O46 -> 0
A47: =A46+1 -> 43 | Q47: =N47+O47 -> 0
A48: =A47+1 -> 44 | Q48: =N48+O48 -> 0
A49: =A48+1 -> 45 | Q49: =N49+O49 -> 0
A50: =A49+1 -> 46 | Q50: =N50+O50 -> 0
A51: =A50+1 -> 47 | Q51: =N51+O51 -> 0
A52: =A51+1 -> 48 | Q52: =N52+O52 -> 0
A53: =A52+1 -> 49 | Q53: =N53+O53 -> 0
A54: =A53+1 -> 50 | Q54: =N54+O54 -> 0
A55: =A54+1 -> 51 | Q55: =N55+O55 -> 0
... A72: =A71+1 -> 68 | Q72: =N72+O72 -> 0
G73: Total Registrados | H73: =COUNTIF(H4:H72,"X") -> 38 | I73: =COUNTIF(I4:I72,"X") -> 0 | J73: =SUM(J4:J72) -> 6020 | K73: =SUM(K4:K72) -> 1435 | N73: =SUM(N4:N72) -> 6004.4 | O73: =SUM(O4:O72) -> 1419.4
G74: Total Cupos | H74: 34 | I74: 34 | J74: =SUM(J73:K73) -> 7455 | N74: =SUM(N73:O73) -> 7423.8
G75: Cupos Libres | H75: =H74-H73 -> -4 | I75: =I74-I73 -> 34 | J75: Total Venta Fecha | N75: Venta Final Fecha
H76: 200 | I76: 200 | T76: -
H77: =H75*H76 -> -800 | I77: =I75*I76 -> 6800
H78: =H77+I77 -> 6000

Sheet AFI-F2
A2: CONTROL DE REGISTRO PARTICIPANTES
A3: PARRILLERO AFICIONADO | G3: 45668
A4: ID | B4: FE_ REGISTRO | C4: DNI | D4: NOMBRES Y APELLIDOS | E4: EMAIL | F4: DISTRITO | H4: BB1 | I4: BB2 | J4: MONTO | K4: xCOBRAR | L4: ESTADO | M4: CUENTA | N4: INGRESO | P4: SALDO | Q4: VENDEDOR | R4: TOTAL | S4: OBSERVACION
A5: 1 | B5: 45993 | C5: 47078798 | D5: Anthony Molina Heredia | E5: anthony.molinah@gmail.com | F5: VMT | G5: 968 358 245 | I5: X | J5: 220 | L5: PAGO | M5: YAPE JL | N5: 220 | Q5: Yadhira | R5: =N5+P5 -> 220 | S5: PAGO POR SEPARADO EL 02/12 Y 19/12
A6: =A5+1 -> 2 | B6: 46008 | C6: 44681923 | D6: Rodrigo Bustamante Moquillaza | E6: Roodj88@gmail.com | F6: SURQUILLO | G6: 995 586 556 | I6: X | J6: 200 | K6: 155 | L6: COBR | M6: YAPE JL | N6: 200 | O6: 155 | Q6: Yadhira | R6: =N6+O6 -> 355
A7: =A6+1 -> 3 | B7: 46008 | D7: Philip Wenter Bustamante | E7: Roodj88@gmail.com | F7: SURQUILLO | G7: 995 586 556 | I7: X | J7: 200 | K7: 155 | L7: COBR | M7: YAPE JL | N7: 200 | O7: 155 | Q7: Yadhira | R7: =N7+O7 -> 355
A8: =A7+1 -> 4 | B8: 46008 | C8: 72495808 | D8: Sebastian Matias Prada Fernandez | E8: Matias_pf_21@hotmail.com | F8: LA VICTORIA | G8: 954 532 968 | H8: X | I8: X | J8: 380 | K8: 190 | L8: PAGO | M8: YAPE JL | N8: 190 | O8: 190 | Q8: Yadhira | R8: =N8+O8 -> 380 | S8: CPMPLETO PAGO EL 09/01
A9: =A8+1 -> 5 | B9: 46008 | C9: 09594474 | D9: Jorge Fernandez Huaman | E9: Matias_pf_21@hotmail.com | F9: LA VICTORIA | G9: 954 532 968 | H9: X | J9: 190 | K9: 95 | L9: PAGO | M9: YAPE JL | N9: 95 | O9: 95 | Q9: Yadhira | R9: =N9+O9 -> 190 | S9: CPMPLETO PAGO EL 09/01
A10: =A9+1 -> 6 | B10: 46014 | C10: 44889118 | D10: Miguel Ángel Requiz Alanís | E10: Miguel.requiz10@gmail.com | F10: SJL | G10: 975 575 476 | H10: X | I10: X | J10: 360 | L10: PAGO | M10: BCP EPP | N10: 360 | Q10: Yadhira | R10: =N10+P10 -> 360
A11: =A10+1 -> 7 | B11: 46014 | C11: 43045566 | D11: Carlos Miguel Olivares Pérez | E11: Miguel.requiz10@gmail.com | F11: CHICLAYO | G11: 975 575 476 | H11: X | I11: X | J11: 360 | L11: PAGO | M11: YAPE JL | N11: 360 | Q11: Yadhira | R11: =N11+P11 -> 360
A12: =A11+1 -> 8 | B12: 46011 | D12: Aldo Augusto Di liberto Roldán | E12: aldodilibertoroldan@gmail.com | F12: CHORRILLOS | G12: 991385736 | H12: X | J12: 95 | K12: 95 | L12: PAGO | M12: BCP EPP | N12: 95 | O12: 95 | Q12: Yadhira | R12: =N12+O12 -> 190
A13: =A12+1 -> 9 | B13: 46011 | D13: Yames Vicente di liberto Roldán | E13: aldodilibertoroldan@gmail.com | F13: CHORRILLOS | G13: 991385736 | H13: X | J13: 95 | K13: 95 | L13: PAGO | M13: BCP EPP | N13: 95 | O13: 95 | Q13: Yadhira | R13: =N13+O13 -> 190
A14: =A13+1 -> 10 | B14: 46386 | C14: 72616360 | D14: Enrique Raynor La Torre Alarcón | E14: enriquelta169@gmail.com | F14: SAN BORJA | G14: 966 922 334 | H14: X | I14: X | J14: 380 | L14: PAGO | M14: YAPE JL | N14: 380 | Q14: Greici | R14: =N14+P14 -> 380
A15: =A14+1 -> 11 | B15: 46021 | C15: 49035262 | D15: Rafael Antony Urbina Peña | E15: rafaelurbi24@gmail.com | F15: LOS OLIVOS | G15: 927 235 029 | I15: X | J15: 0 | L15: PAGO | M15: YAPE JL | N15: 0 | Q15: Yadhira | R15: =N15+P15 -> 0 | S15: PAGO 2 CLASES EL 30/12
A16: =A15+1 -> 12 | B16: 46021 | C16: 49032421 | D16: Pierre Neyra | E16: pierre.neyrape@gmail.com | F16: MIRAFLORES | G16: 954 134 851 | H16: X | J16: 190 | L16: PAGO | M16: MERC-PAG | N16: 181.58 | Q16: Yadhira | R16: =N16+P16 -> 181.58
A17: =A16+1 -> 13 | B17: 46021 | C17: 73185937 | D17: Marieta Calderon | E17: marietacristina@hotmail.com | F17: MIRAFLORES | G17: 954 134 851 | H17: X | J17: 190 | L17: PAGO | M17: MERC-PAG | N17: 181.58 | Q17: Yadhira | R17: =N17+P17 -> 181.58
A18: =A17+1 -> 14 | B18: 46014 | D18: Sergio Jesús Casas Arroyo | F18: Villa María del Triunfo | H18: x | J18: 220 | L18: PAGO | M18: YAPE JL | N18: 220 | Q18: Katherine | R18: =N18+P18 -> 220
A19: =A18+1 -> 15 | B19: 46024 | C19: 42296972 | D19: Jose Gabriel Janampa Osores | E19: janampaosores@gmail.com | I19: x | J19: 190 | L19: PAGO | M19: PLIN JL | N19: 190 | Q19: Katherine | R19: =N19+P19 -> 190
A20: =A19+1 -> 16 | B20: 46022 | C20: 70945763 | D20: kevin alarico cieza | E20: kevinalarico@gmail.com | F20: SMP | H20: X | I20: X | J20: 100 | K20: 250 | L20: COBR | M20: PLIN JL | N20: 100 | O20: 0 | Q20: Greici | R20: =N20+P20 -> 100
A21: =A20+1 -> 17 | B21: 46022 | C21: 47628203 | D21: Juan Carlos Bustamante Merino | E21: Juanca.busta.mer09@gmail.com | F21: SMP | H21: X | I21: X | J21: 100 | K21: 250 | L21: COBR | M21: PLIN JL | N21: 100 | O21: 0 | Q21: Greici | R21: =N21+P21 -> 100
A22: =A21+1 -> 18 | B22: 46024 | C22: 72413600 | D22: Daniel Ricardo moran Chávez | E22: danielpupunovich5@hotmail.com | G22: 988 766 216 | I22: X | J22: 190 | L22: PAGO | M22: PLIN JL | N22: 190 | Q22: Yadhira | R22: =N22+P22 -> 190
A23: =A22+1 -> 19 | B23: 46024 | C23: 71523029 | D23: Aaron Castillo | R23: =N23+P23 -> 0
A24: =A23+1 -> 20 | B24: 46024 | C24: 40697850 | D24: Sergio Armando Lopez Saldaña | E24: Sergio.lsaldana@gmail.com | F24: Victoria | G24: 987 809 308 | I24: X | J24: 190 | L24: PAGO | M24: YAPE JL | N24: 190 | Q24: Sofia | R24: =N24+P24 -> 190
A25: =A24+1 -> 21 | B25: 46024 | C25: 07524459 | D25: José pineda sifuentes | E25: jose.pineda@ae.edu.pe | F25: SAN ISIDRO | G25: 981 398 282 | I25: X | J25: 175 | L25: PAGO | M25: PLIN JL | N25: 175 | Q25: Yadhira | R25: =N25+P25 -> 175
A26: =A25+1 -> 22 | B26: 46024 | D26: Ana Paula Pineda | F26: SAN ISIDRO | I26: X | J26: 100 | L26: PAGO | M26: PLIN JL | N26: 100 | Q26: Yadhira | R26: =N26+P26 -> 100 | S26: MENOR DE 10 AÑOS
A27: =A26+1 -> 23 | B27: 46024 | C27: 42048172 | D27: Luis Esteban Ramos Nicoll | E27: luisramosnicoll@gmail.com | I27: x | J27: 180 | L27: PAGO | M27: BCP JL | N27: 180 | Q27: Katherine | R27: =N27+P27 -> 180
A28: =A27+1 -> 24 | B28: 46024 | C28: 08870972 | D28: José Martin Quineche Sánchez | E28: martinj_98@hotmail.com | F28: Callao | G28: 997 126 675 | H28: X | J28: 100 | K28: 100 | L28: COBR | M28: YAPE JL | N28: 100 | O28: 100 | Q28: Tania | R28: =N28+O28 -> 200
A29: =A28+1 -> 25 | B29: 46025 | C29: 45479473 | D29: Deivy wilson rios anco | E29: Wilsonuni@gmail.com | F29: SAN LUIS | G29: 936 613 646 | H29: X | I29: X | J29: 380 | L29: PAGO | M29: MERC-PAG | N29: 363.16 | Q29: Yadhira | R29: =N29+P29 -> 363.16
A30: =A29+1 -> 26 | B30: 46025 | C30: ⁠45526454 | D30: David Guardia Menendez | E30: ⁠guardiamd@gmail.com | F30: SURCO | G30: 987 760 144 | H30: X | J30: 175 | K30: 175 | L30: COBR | M30: MERC-PAG | N30: 167.2 | O30: 167.2 | Q30: Yadhira | R30: =N30+O30 -> 334.4
A31: =A30+1 -> 27 | B31: 46025 | C31: 45786136 | D31: Lourdes Franco Vidal | E31: ⁠guardiamd@gmail.com | F31: SURCO | G31: 987 760 144 | H31: X | J31: 175 | K31: 175 | L31: COBR | M31: MERC-PAG | N31: 167.2 | O31: 167.2 | Q31: Yadhira | R31: =N31+O31 -> 334.4
A32: =A31+1 -> 28 | B32: 46025 | C32: 45592753 | D32: Jorge Araujo | E32: Jorgearaujo13@hotmail.com | I32: x | J32: 220 | L32: PAGO | M32: YAPE JL | N32: 220 | Q32: Katherine | R32: =N32+P32 -> 220
A33: =A32+1 -> 29 | B33: 46027 | C33: 44784709 | D33: José Ernesto Rodríguez Marcelo | F33: breña | H33: x | J33: 200 | L33: PAGO | M33: YAPE JL | N33: 200 | Q33: Katherine | R33: =N33+P33 -> 200
A34: =A33+1 -> 30 | B34: 46027 | D34: María Quiroga | E34: marijo51290@gmail.com | I34: x | J34: 190 | L34: PAGO | M34: YAPE JL | N34: 190 | Q34: Katherine | R34: =N34+P34 -> 190
A35: =A34+1 -> 31 | B35: 46027 | D35: Carlos Gil | E35: marijo51290@gmail.com | I35: x | J35: 190 | L35: PAGO | M35: YAPE JL | N35: 190 | Q35: Katherine | R35: =N35+P35 -> 190
A36: =A35+1 -> 32 | B36: 46027 | D36: Diego Miletich | E36: patriciaarz@yahoo.es | F36: san miguel | I36: x | J36: 95 | K36: 95 | L36: COBR | M36: YAPE JL | N36: 95 | O36: 95 | Q36: Katherine | R36: =N36+O36 -> 190
A37: =A36+1 -> 33 | B37: 46027 | D37: Mirko Miletich | E37: patriciaarz@yahoo.es | F37: san miguel | I37: x | J37: 95 | K37: 95 | L37: COBR | M37: YAPE JL | N37: 95 | O37: 95 | Q37: Katherine | R37: =N37+O37 -> 190
A38: =A37+1 -> 34 | B38: 46026 | C38: 41577290 | D38: Manuel Mori Mideyros | E38: j.chefmori@gmail.com | F38: SAN MARTIN | G38: 945 841 782 | H38: X | I38: X | J38: 380 | L38: PAGO | M38: PLIN JL | N38: 380 | Q38: Yadhira | R38: =N38+P38 -> 380
A39: =A38+1 -> 35 | B39: 46027 | C39: 003012946 | D39: Ambioris Peña | E39: ambiorisellince@gmail.com | F39: SURCO | G39: 940 114 314 | H39: X | I39: X | J39: 380 | L39: PAGO | M39: PLIN JL | N39: 380 | Q39: Yadhira | R39: =N39+P39 -> 380
A40: =A39+1 -> 36 | B40: 46027 | D40: Walter Castro vargas | E40: waltercv2002@hotmail.com | H40: x | I40: x | J40: 330 | K40: 20 | L40: COBR | M40: BCP JL | N40: 330 | O40: 20 | Q40: Katherine | R40: =N40+O40 -> 350
A41: =A40+1 -> 37 | B41: 46027 | D41: Walter Castro Ugarte | E41: waltercv2002@hotmail.com | H41: x | I41: x | J41: 330 | K41: 20 | L41: COBR | M41: BCP JL | N41: 330 | O41: 20 | Q41: Katherine | R41: =N41+O41 -> 350
A42: =A41+1 -> 38 | B42: 46028 | C42: 46641938 | D42: Ivan Irwin Espinoza Revolo | I42: x | J42: 95 | K42: 95 | L42: COBR | M42: YAPE JL | N42: 95 | O42: 95 | Q42: Katherine | R42: =N42+O42 -> 190
A43: =A42+1 -> 39 | B43: 46028 | C43: 71089810 | D43: Guadalupe Ivana Tarazona Velarde | I43: x | J43: 95 | K43: 95 | L43: COBR | M43: YAPE JL | N43: 95 | O43: 95 | Q43: Katherine | R43: =N43+O43 -> 190
A44: =A43+1 -> 40 | B44: 46029 | C44: 40262423 | D44: Carlos Meza Gamero | E44: bertha_gamboa@yahoo.com | F44: Ica | G44: 956 683 082 | H44: x | I44: x | J44: 380 | L44: PAGO | M44: YAPE JL | N44: 380 | Q44: Sofia | R44: =N44+P44 -> 380
A45: =A44+1 -> 41 | B45: 46029 | C45: 10602143 | D45: RODOLFO Vladimir Cajahuanca Ydone | F45: ATE | G45: 955 854 644 | H45: X | J45: 100 | K45: 100 | L45: COBR | M45: YAPE JL | N45: 100 | O45: 100 | Q45: Yadhira | R45: =N45+O45 -> 200
A46: =A45+1 -> 42 | B46: 46029 | C46: 01216344 | D46: Zhituo Wang | E46: zhituobanco@gmail.com | F46: SAN ISIDRO | G46: 978 839 327 | H46: X | I46: X | J46: 380 | L46: PAGO | M46: BBVA JL | N46: 380 | Q46: Yadhira | R46: =N46+P46 -> 380 | S46: PAGO QR
A47: =A46+1 -> 43 | B47: 46029 | C47: 74034992 | D47: Alvaro Macuri | H47: x | J47: 220 | L47: PAGO | M47: YAPE JL | N47: 220 | Q47: Katherine | R47: =N47+P47 -> 220
A48: =A47+1 -> 44 | B48: 46029 | C48: 43373830 | D48: Miguel Angel Romero quero | E48: zeepaciente@gmail.com | F48: LA MOLINA | G48: 902 090 772 | H48: X | J48: 100 | K48: 100 | L48: COBR | M48: YAPE JL | N48: 100 | O48: 100 | Q48: Yadhira | R48: =N48+O48 -> 200
A49: =A48+1 -> 45 | B49: 46027 | C49: 44049748 | D49: Miguel arellano chunga | E49: marellanoch@gmail.com | F49: SURCO | G49: 926648844 | H49: X | J49: 95 | K49: 95 | L49: COBR | M49: YAPE JL | N49: 95 | O49: 95 | Q49: Greici | R49: =N49+O49 -> 190
A50: =A49+1 -> 46 | B50: 46027 | C50: 43855684 | D50: Angel Gonzales Ramos | F50: SURCO | H50: X | J50: 95 | K50: 95 | L50: COBR | M50: YAPE JL | N50: 95 | O50: 95 | Q50: Greici | R50: =N50+O50 -> 190
A51: =A50+1 -> 47 | B51: 46029 | C51: 73345092 | D51: María Fernanda Ushiñahua Meza | E51: mariafeushi.94@gmail.com | F51: CINEGUILLA | G51: 955 468 683 | I51: X | J51: 90 | K51: 90 | L51: COBR | M51: YAPE JL | N51: 90 | O51: 90 | Q51: Yadhira | R51: =N51+O51 -> 180
A52: =A51+1 -> 48 | B52: 46029 | C52: 44846202 | D52: Jonathan Donovan Choquehuanca Condori | E52: mariafeushi.94@gmail.com | F52: CINEGUILLA | G52: 955 468 683 | I52: X | J52: 90 | K52: 90 | L52: COBR | M52: YAPE JL | N52: 90 | O52: 90 | Q52: Yadhira | R52: =N52+O52 -> 180
A53: =A52+1 -> 49 | B53: 46030 | C53: 41411344 | D53: Juan Edgar Tito Cornejo | E53: liliana.benitoz@gmail.com | F53: SANTA ANITA | G53: 993 793 101 | H53: X | J53: 95 | K53: 95 | L53: COBR | M53: BBVA JL | N53: 95 | O53: 95 | Q53: Yadhira | R53: =N53+O53 -> 190
A54: =A53+1 -> 50 | B54: 46030 | C54: 70435293 | D54: Liliana Benito Zurita | E54: liliana.benitoz@gmail.com | F54: SANTA ANITA | G54: 993 793 101 | H54: X | J54: 95 | K54: 95 | L54: COBR | M54: BBVA JL | N54: 95 | O54: 95 | Q54: Yadhira | R54: =N54+O54 -> 190
A55: =A54+1 -> 51 | B55: 46029 | C55: 74095604 | D55: Alexander Platero Mamani | E55: Alexanderplatero200q@gmail.com | I55: x | J55: 220 | L55: PAGO | M55: YAPE JL | N55: 220 | Q55: Katherine | R55: =N55+P55 -> 220
A56: =A55+1 -> 52 | B56: 46030 | D56: Mariana Barrera Cravero | E56: marianabarrera@yahoo.com | F56: MIRAFLORES | G56: 995 745 088 | H56: X | J56: 220 | L56: PAGO | M56: YAPE JL | N56: 220 | Q56: Yadhira | R56: =N56+P56 -> 220
A57: =A56+1 -> 53 | B57: 46030 | C57: 43676825 | D57: Juan Carlos Achiri Ccapa | E57: Juan.carlos.achiri@gmail.com | F57: COMAS | G57: 964 322 942 | H57: X | J57: 50 | K57: 150 | L57: COBR | M57: YAPE JL | N57: 50 | O57: 150 | Q57: Yadhira | R57: =N57+O57 -> 200
A58: =A57+1 -> 54 | B58: 46029 | C58: 48605650 | D58: Daniel Gómez Muñante | I58: x | J58: 220 | L58: PAGO | M58: YAPE JL | N58: 220 | Q58: Katherine | R58: =N58+P58 -> 220
A59: =A58+1 -> 55 | B59: 46030 | C59: *07200287 | D59: Flor de maria vega zapata | F59: San borja | G59: 999989977 | H59: x | J59: 220 | L59: PAGO | M59: YAPE JL | N59: 220 | Q59: Gabriela | R59: =N59+P59 -> 220
A60: =A59+1 -> 56 | B60: 46033 | D60: JOSUE DEL VALLE | H60: X | J60: 180 | K60: 180 | L60: PAGO | M60: YAPE JL | N60: 180 | O60: 180 | Q60: JL | R60: =N60+O60 -> 360
A61: =A60+1 -> 57 | R61: =N61+P61 -> 0
A62: =A61+1 -> 58 | R62: =N62+P62 -> 0
A63: =A62+1 -> 59 | R63: =N63+P63 -> 0
A64: =A63+1 -> 60 | R64: =N64+P64 -> 0
A65: =A64+1 -> 61 | R65: =N65+P65 -> 0
A66: =A65+1 -> 62 | R66: =N66+P66 -> 0
A67: =A66+1 -> 63 | R67: =N67+P67 -> 0
A68: =A67+1 -> 64 | R68: =N68+P68 -> 0
A69: =A68+1 -> 65 | R69: =N69+P69 -> 0
A70: =A69+1 -> 66 | R70: =N70+P70 -> 0
A71: =A70+1 -> 67 | R71: =N71+P71 -> 0
A72: =A71+1 -> 68 | R72: =N72+P72 -> 0 | S72: OBSERVACION
G73: Total Registrados | H73: =COUNTIF(H4:H72,"X") -> 34 | I73: =COUNTIF(I4:I72,"X") -> 34 | J73: =SUM(J4:J72) -> 10585 | K73: =SUM(K4:K72) -> 3245 | N73: =SUM(N4:N72) -> 10250.72 | P73: =SUM(P4:P72) -> 0
G74: Total Cupos | H74: 34 | I74: 34 | J74: =SUM(J73:K73) -> 13830 | N74: =SUM(N73:P73) -> 10250.72
G75: Cupos Libres | H75: =H74-H73 -> 0 | I75: =I74-I73 -> 0 | J75: Total Venta Fecha | N75: Venta Final Fecha
H76: 200 | I76: 200 | U76: -
H77: =H75*H76 -> 0 | I77: =I75*I76 -> 0
H78: =H77+I77 -> 0

Sheet AFI-F3
A2: CONTROL DE REGISTRO PARTICIPANTES
A3: PARRILLERO AFICIONADO | G3: 45674
A4: ID | B4: FE_ REGISTRO | C4: DNI | D4: NOMBRES Y APELLIDOS | E4: EMAIL | F4: DISTRITO | G4: WSP | H4: BB2 | I4: BB1 | J4: MONTO | K4: xCOBRAR | L4: ESTADO | M4: CUENTA | N4: INGRESO | O4: SALDO | P4: VENDEDOR | Q4: TOTAL | R4: OBSERVACION
A5: 1 | B5: 46014 | C5: 41864072 | D5: Alan Paul Otiniano Azahuanche | E5: apoa315@hotmail.com | F5: SURCO | G5: 949 271 885 | H5: X | J5: 110 | K5: 110 | L5: COBR | M5: YAPE JL | N5: 110 | O5: 110 | P5: Yadhira | Q5: =N5+O5 -> 220 | R5: OBSERVACION
A6: =A5+1 -> 2 | B6: 46014 | C6: 09954438 | D6: Walter Peralta | E6: Carolina.velosa@icloud.com | F6: SAN BORJA | G6: 987 737 748 | I6: X | J6: 220 | L6: PAGO | M6: YAPE JL | N6: 220 | P6: Yadhira | Q6: =N6+O6 -> 220
A7: =A6+1 -> 3 | B7: 46009 | C7: 46649174 | D7: Jonathan Marrou | E7: Jonathan.marrou@gmail.com | F7: SURCO | G7: FB | I7: X | J7: 190 | L7: PAGO | M7: BCP EPP | N7: 190 | P7: Yadhira | Q7: =N7+O7 -> 190
A8: =A7+1 -> 4 | B8: 46009 | C8: 10303242 | D8: Ricardo Marrou | E8: Ricardo.jonico@gmail.com | F8: SURCO | G8: FB | I8: X | J8: 190 | L8: PAGO | M8: BCP EPP | N8: 190 | P8: Yadhira | Q8: =N8+O8 -> 190
A9: =A8+1 -> 5 | B9: 46014 | C9: 44273674 | D9: Ivan Salsavilca Faustino | E9: ivansalsavilca@gmail.com | H9: x | I9: x | J9: 380 | L9: PAGO | M9: YAPE JL | N9: 380 | P9: Katherine | Q9: =N9+O9 -> 380
A10: =A9+1 -> 6 | B10: 46024 | C10: 77059170 | D10: Nicolas Gámez | E10: Nicogamez1008@gmail.com | F10: Chorrillos | G10: 924 714 156 | H10: X | I10: x | J10: 220 | K10: 160 | L10: COBR | M10: PLIN JL | N10: 220 | O10: 160 | P10: Sofia | Q10: =N10+O10 -> 380 | R10: COMPLETARA PAGO 04/01
A11: =A10+1 -> 7 | B11: 46027 | C11: 42126105 | D11: Manuel Buendia | E11: Mbuendia4@gmail.com | F11: CHACLACAYO | G11: 961 082 768 | H11: X | I11: X | J11: 175 | K11: 175 | L11: COBR | M11: BCP EPP | N11: 175 | O11: 175 | P11: Yadhira | Q11: =N11+O11 -> 350
A12: =A11+1 -> 8 | B12: 46027 | C12: 41758472 | D12: Liselle Prieto | E12: Lisibuendia28@gmail.com | F12: CHACLACAYO | G12: 961 082 768 | H12: X | I12: X | J12: 175 | K12: 175 | L12: COBR | M12: BCP EPP | N12: 175 | O12: 175 | P12: Yadhira | Q12: =N12+O12 -> 350
A13: =A12+1 -> 9 | B13: 46006 | C13: 10734077 | D13: Sandro León Anfossi | E13: luciapari87@outlook.com | F13: SURCO | G13: 957 799 157 | H13: X | J13: 0 | N13: 0 | P13: Yadhira | Q13: =N13+O13 -> 0 | R13: REPROGRAMACIÓN
A14: =A13+1 -> 10 | B14: 46028 | C14: 41570562 | D14: Willy rabanal calderon | E14: Rabanalwilly@gmail.com | F14: Callao | G14: 991 049 152 | H14: x | I14: x | J14: 190 | K14: 190 | L14: COBR | M14: BCP JL | N14: 190 | O14: 190 | P14: Gabriela | Q14: =N14+O14 -> 380
A15: =A14+1 -> 11 | B15: 46028 | C15: 48129640 | D15: Bryan Ochoa Salas | E15: bochoa@pucp.pe | F15: Breña | G15: 917 880 991 | H15: x | J15: 175 | L15: PAGO | M15: YAPE JL | N15: 175 | P15: Gabriela | Q15: =N15+O15 -> 175
A16: =A15+1 -> 12 | B16: 46028 | C16: 70605782 | D16: Néstor Walter Villegas Macedo | E16: nestor_vm1994@hotmail.com | F16: Lince | G16: 917 880 991 | H16: x | J16: 175 | L16: PAGO | M16: YAPE JL | N16: 175 | P16: Gabriela | Q16: =N16+O16 -> 175
A17: =A16+1 -> 13 | B17: 46028 | C17: 40298292 | D17: Carlos Cuadra Macedo | E17: carlonchocuadra@gmail.com | F17: Lince | G17: 917 880 991 | H17: x | J17: 175 | L17: PAGO | M17: YAPE JL | N17: 175 | P17: Gabriela | Q17: =N17+O17 -> 175
A18: =A17+1 -> 14 | B18: 46028 | C18: 70437688 | D18: Franco Daniel Delzo Cuyubamba | E18: Delzofranco@gmail.com | F18: San Miguel | G18: 917 880 991 | H18: x | J18: 175 | L18: PAGO | M18: YAPE JL | N18: 175 | P18: Gabriela | Q18: =N18+O18 -> 175
A19: =A18+1 -> 15 | B19: 46027 | C19: 46123466 | D19: Pilar coveñas Ramos | E19: naturaquimi@gmail.com | F19: SMP | G19: 965 713 303 | I19: X | J19: 0 | L19: PAGO | M19: YAPE JL | P19: Yadhira | Q19: =N19+O19 -> 0
A20: =A19+1 -> 16 | B20: 46030 | C20: 46063723 | D20: carlos ore yufre | E20: carlosyufre29@gmail.com | F20: los olivos | G20: 948350215 | H20: x | J20: 190 | K20: 190 | L20: COBR | M20: YAPE JL | N20: 190 | O20: 190 | P20: Sofia | Q20: =N20+O20 -> 380
A21: =A20+1 -> 17 | B21: 46029 | C21: 73563073 | D21: Jesús Amir Huaccho Hidalgo | E21: ruthm_hidalgo@hotmail.com | F21: SURCO | G21: 996 757 353 | I21: X | J21: 190 | L21: PAGO | M21: YAPE JL | N21: 190 | P21: Yadhira | Q21: =N21+O21 -> 190
A22: =A21+1 -> 18 | B22: 46031 | C22: 74743912 | D22: Marco Antonio Escobar Nolazco | E22: escobar010201@gmail.com | F22: VES | G22: 926 468 622 | H22: X | I22: X | J22: 180 | K22: 180 | L22: PAGO | M22: BBVA JL | N22: 180 | O22: 180 | P22: Yadhira | Q22: =N22+O22 -> 360
A23: =A22+1 -> 19 | B23: 46031 | C23: 41552489 | D23: David Sánchez Calle | E23: davsan82@hotmail.com | F23: ATE | G23: 973 110 496 | I23: X | J23: 180 | L23: PAGO | M23: BCP EPP | N23: 180 | P23: Yadhira | Q23: =N23+O23 -> 180
A24: =A23+1 -> 20 | B24: 46031 | C24: 41878729 | D24: Carmen Casana López | E24: crcl83@hotmail.com | F24: ATE | G24: 973 110 496 | I24: X | J24: 180 | L24: PAGO | M24: BCP EPP | N24: 180 | P24: Yadhira | Q24: =N24+O24 -> 180
A25: =A24+1 -> 21 | B25: 46031 | C25: 79820823 | D25: Mariano Sánchez Casana | E25: davsan82@gmail.com | F25: ATE | G25: 973 110 496 | I25: X | J25: 100 | L25: PAGO | M25: BCP EPP | N25: 100 | P25: Yadhira | Q25: =N25+O25 -> 100
A26: =A25+1 -> 22 | B26: 46032 | C26: 40371144 | D26: Pavel N. Paredes Diaz | E26: Pavelpadiaz@gmail.com | F26: Pisco | G26: 969 732 961 | H26: X | I26: X | J26: 380 | L26: PAGO | M26: BCP JL | N26: 380 | P26: Gabriela | Q26: =N26+O26 -> 380
A27: =A26+1 -> 23 | B27: 46030 | C27: 42161125 | D27: Luis Alberto cavero alvites | H27: x | I27: x | J27: 190 | K27: 190 | L27: COBR | M27: YAPE JL | N27: 190 | O27: 190 | P27: Katherine | Q27: =N27+O27 -> 380
A28: =A27+1 -> 24 | B28: 46032 | C28: 23600914 | D28: Edgar Lenin Hernandez Ore | I28: x | J28: 220 | L28: PAGO | M28: YAPE JL | N28: 220 | P28: Katherine | Q28: =N28+O28 -> 220
A29: =A28+1 -> 25 | B29: 46032 | C29: 44204321 | D29: Gustavo Córdova nieto | E29: gustavocordova2015@gmail.com | F29: SJL | G29: 912 909 308 | H29: X | J29: 100 | K29: 100 | L29: PAGO | M29: YAPE JL | N29: 100 | O29: 100 | P29: Yadhira | Q29: =N29+O29 -> 200
A30: =A29+1 -> 26 | B30: 46033 | D30: JOSUE DEL VALLE | H30: X | J30: 0 | L30: PAGO | M30: YAPE JL | N30: 0 | P30: JL | Q30: =N30+O30 -> 0
A31: =A30+1 -> 27 | B31: 46034 | C31: 06967251 | D31: Aldo Viacava Nájera | E31: aldoviacava@msn.com | F31: SAN ISIDRO | G31: 999 207 109 | H31: X | J31: 180 | L31: PAGO | M31: YAPE JL | N31: 180 | P31: Yadhira | Q31: =N31+O31 -> 180
A32: =A31+1 -> 28 | B32: 46034 | C32: 74565573 | D32: Aldo Renzo Viacaa Benavides | E32: aldoviacava00@outlook.com | F32: SAN ISIDRO | G32: 999 207 109 | H32: X | J32: 180 | L32: PAGO | M32: YAPE JL | N32: 180 | P32: Yadhira | Q32: =N32+O32 -> 180
A33: =A32+1 -> 29 | B33: 46034 | C33: 09033925 | D33: EDGAR PANDURO | E33: ELPY1967@GMAIL.COM | F33: CAÑETE | G33: 943 368 377 | I33: X | J33: 100 | K33: 100 | L33: COBR | M33: YAPE JL | N33: 100 | O33: 100 | P33: Greici | Q33: =N33+O33 -> 200
A34: =A33+1 -> 30 | B34: 46034 | C34: 70342491 | D34: Jandir Rivera Quispe | E34: jandir.rivera10@gmail.com | F34: San Bartolo | G34: 987552563 | H34: X | J34: 180 | K34: 180 | L34: COBR | M34: MERC-PAG | N34: 180 | O34: 165 | P34: Sofia | Q34: =N34+O34 -> 345
A35: =A34+1 -> 31 | B35: 46034 | C35: 74711615 | D35: Edu Escobedo Yalico | H35: x | I35: x | J35: 350 | L35: PAGO | M35: YAPE JL | N35: 350 | P35: Katherine | Q35: =N35+O35 -> 350
A36: =A35+1 -> 32 | B36: 46034 | D36: Fernanda Yalico Canchari | H36: x | I36: x | J36: 350 | L36: PAGO | M36: YAPE JL | N36: 350 | P36: Katherine | Q36: =N36+O36 -> 350
A37: =A36+1 -> 33 | B37: 46032 | D37: Nico Suárez Loayza | H37: x | I37: x | J37: 200 | K37: 180 | L37: COBR | M37: YAPE JL | N37: 200 | O37: 180 | P37: Katherine | Q37: =N37+O37 -> 380
A38: =A37+1 -> 34 | N38: 0 | P38: Greici | Q38: =N38+O38 -> 0
A39: =A38+1 -> 35 | B39: 46034 | C39: 48194840 | D39: Fritz puente | E39: fritz_jairo@hotmail .com | F39: Los olivos | G39: 966 505 141 | H39: X | J39: 100 | K39: 100 | L39: COBR | M39: YAPE JL | N39: 100 | O39: 100 | P39: Sofia | Q39: =N39+O39 -> 200
A40: =A39+1 -> 36 | B40: 46024 | D40: Aaron Castillo | I40: x | J40: 190 | L40: PAGO | M40: YAPE JL | N40: 190 | P40: Katherine | Q40: =N40+O40 -> 190
A41: =A40+1 -> 37 | B41: 46024 | D41: Aaron Castillo | I41: x | J41: 190 | L41: PAGO | M41: YAPE JL | N41: 190 | P41: Katherine | Q41: =N41+O41 -> 190
A42: =A41+1 -> 38 | B42: 46035 | C42: 47575960 | D42: Abdul Kazan Espinoza Guerra | E42: Ka.carmed@gmail.com | F42: RIMAC | G42: 970 345 673 | H42: X | J42: 190 | L42: PAGO | M42: YAPE JL | N42: 190 | P42: Yadhira | Q42: =N42+O42 -> 190
A43: =A42+1 -> 39 | B43: 46035 | C43: 72774551 | D43: Camila Alexandra Vega Tocto | E43: camilavegatocto2102@gmail.com | F43: SURQUILLO | G43: 979 898 493 | H43: X | J43: 180 | L43: PAGO | M43: YAPE JL | N43: 180 | P43: Yadhira | Q43: =N43+O43 -> 180
A44: =A43+1 -> 40 | B44: 46035 | C44: 61066668 | D44: Juan Alfonso Vega Tocto | E44: juanvt667@gmail.com | F44: SURQUILLO | G44: 979 898 493 | H44: X | J44: 180 | L44: PAGO | M44: YAPE JL | N44: 180 | P44: Yadhira | Q44: =N44+O44 -> 180
A45: =A44+1 -> 41 | B45: 46035 | C45: 42516080 | D45: Danny Simon Gonzales | H45: x | J45: 190 | L45: PAGO | M45: YAPE JL | N45: 190 | P45: Katherine | Q45: =N45+O45 -> 190
A46: =A45+1 -> 42 | B46: 46035 | C46: 41052490 | D46: Ronald Guerrero Romero | H46: x | J46: 190 | L46: PAGO | M46: YAPE JL | N46: 190 | P46: Katherine | Q46: =N46+O46 -> 190
A47: =A46+1 -> 43 | B47: 46035 | C47: 10302642 | D47: Nestor Hugo Caceres Rosa | E47: caceresnestor869@gmail.com | F47: SURCO | G47: 952 880 580 | I47: X | J47: 100 | K47: 100 | L47: COBR | M47: YAPE JL | N47: 100 | O47: 100 | P47: Yadhira | Q47: =N47+O47 -> 200
A48: =A47+1 -> 44 | B48: 46035 | C48: ⁠48272392 | D48: Samir Edu fiestas huamanchumo | E48: samir010512@gmail.com | H48: x | I48: x | J48: 360 | L48: PAGO | M48: YAPE JL | N48: 360 | P48: Katherine | Q48: =N48+O48 -> 360
A49: =A48+1 -> 45 | B49: 46035 | C49: 73136673 | D49: Samuel pariona | E49: Samuel.pariona@urp.edu.pe | F49: Lince | I49: x | J49: 190 | L49: PAGO | N49: 190 | P49: Gabriela | Q49: =N49+O49 -> 190
A50: =A49+1 -> 46 | B50: 46035 | C50: 73136674 | D50: Edwin pariona | E50: Samuel.pariona@urp.edu.pe | F50: San Miguel | I50: x | J50: 190 | L50: PAGO | N50: 190 | P50: Gabriela | Q50: =N50+O50 -> 190
A51: =A50+1 -> 47 | B51: 46036 | C51: 21134360 | D51: Ricardo Pando Córdova | F51: lima | H51: x | I51: x | J51: 200 | K51: 180 | L51: COBR | M51: YAPE JL | N51: 200 | O51: 180 | P51: Katherine | Q51: =N51+O51 -> 380
A52: =A51+1 -> 48 | B52: 46036 | C52: 72616355 | D52: Mihel La Torre Alarcon | E52: Latorremihel@gmail.com | F52: SAN BORJA | G52: 932 340 383 | H52: X | Q52: =N52+O52 -> 0
A53: =A52+1 -> 49 | B53: 46036 | C53: 48131311 | D53: Rubí Jiménez picoy | H53: x | I53: x | J53: 150 | K53: 210 | L53: COBR | M53: YAPE JL | N53: 150 | O53: 210 | P53: Katherine | Q53: =N53+O53 -> 360
A54: =A53+1 -> 50 | B54: 46036 | C54: 22314008 | D54: Elias Campos Sanchez. | I54: x | J54: 150 | K54: 300 | L54: COBR | M54: YAPE JL | N54: 150 | O54: 300 | P54: Katherine | Q54: =N54+O54 -> 450
A55: =A54+1 -> 51 | B55: 46037 | C55: 41590522 | D55: Joao Solís Talaverano | E55: Spawn.st41@gmail.com | F55: AYACUCHO | G55: 932 006 620 | I55: X | J55: 185 | K55: 150 | L55: COBR | M55: YAPE JL | N55: 185 | O55: 150 | P55: Greici | Q55: =N55+O55 -> 335
A56: =A55+1 -> 52 | B56: 46037 | C56: 42689847 | D56: Cisneros Montes de Oca | E56: sergio14_14@hotmail.com | F56: AYACUCHO | I56: X | J56: 185 | K56: 150 | L56: COBR | M56: YAPE JL | N56: 185 | O56: 150 | P56: Greici | Q56: =N56+O56 -> 335
A57: =A56+1 -> 53 | Q57: =N57+O57 -> 0
A58: =A57+1 -> 54 | Q58: =N58+O58 -> 0
A59: =A58+1 -> 55 | Q59: =N59+O59 -> 0
A60: =A59+1 -> 56 | Q60: =N60+O60 -> 0
A61: =A60+1 -> 57 | Q61: =N61+O61 -> 0
A62: =A61+1 -> 58 | Q62: =N62+O62 -> 0
A63: =A62+1 -> 59 | Q63: =N63+O63 -> 0
A64: =A63+1 -> 60 | Q64: =N64+O64 -> 0
A65: =A64+1 -> 61 | Q65: =N65+O65 -> 0
A66: =A65+1 -> 62 | Q66: =N66+O66 -> 0
A67: =A66+1 -> 63 | Q67: =N67+O67 -> 0
A68: =A67+1 -> 64 | Q68: =N68+O68 -> 0
... A71: =A70+1 -> 67 | Q71: =N71+O71 -> 0
A72: =A71+1 -> 68 | Q72: =N72+O72 -> 0 | R72: OBSERVACION
G73: Total Registrados | H73: =COUNTIF(H4:H72,"X") -> 33 | I73: =COUNTIF(I4:I72,"X") -> 32 | J73: =SUM(J4:J72) -> 9120 | K73: =SUM(K4:K72) -> 3120 | N73: =SUM(N4:N72) -> 9120 | O73: =SUM(O4:O72) -> 3105
G74: Total Cupos | H74: 34 | I74: 34 | J74: =SUM(J73:K73) -> 12240 | N74: =SUM(N73:O73) -> 12225
G75: Cupos Libres | H75: =H74-H73 -> 1 | I75: =I74-I73 -> 2 | J75: Total Venta Fecha | N75: Venta Final Fecha
H76: 200 | I76: 200 | T76: -
H77: =H75*H76 -> 200 | I77: =I75*I76 -> 400
H78: =H77+I77 -> 600

Sheet AFI-F4
A2: CONTROL DE REGISTRO PARTICIPANTES
A3: PARRILLERO AFICIONADO | G3: 45682
A4: ID | B4: FE_ REGISTRO | C4: DNI | D4: NOMBRES Y APELLIDOS | E4: EMAIL | F4: DISTRITO | G4: WSP | H4: BB1 | I4: BB2 | J4: MONTO | K4: xCOBRAR | L4: ESTADO | M4: CUENTA | N4: INGRESO | O4: SALDO | P4: VENDEDOR | Q4: TOTAL | R4: OBSERVACION
A5: 1 | B5: 46000 | C5: 44412013 | D5: Nazaret judith abad zarco | E5: Nazaret_abad@hotmail.com | F5: SAN MIGUEL | G5: 976 096 059 | H5: X | J5: 190 | L5: PAGO | M5: YAPE JL | N5: 190 | P5: Yadhira | Q5: =N5+O5 -> 190 | R5: OBSERVACION
A6: =A5+1 -> 2 | B6: 46000 | C6: 10562497 | D6: Rubén Abad Zarco | E6: Nazaret_abad@hotmail.com | F6: SAN MIGUEL | G6: 976 096 059 | H6: X | J6: 190 | L6: PAGO | M6: YAPE JL | N6: 190 | P6: Yadhira | Q6: =N6+O6 -> 190
A7: =A6+1 -> 3 | B7: 46024 | C7: 76197577 | D7: Anderson Achata | E7: andersonachata@gmail.com | F7: SAN LUIS | G7: 913 872 010 | H7: X | J7: 190 | L7: PAGO | M7: PLIN JL | N7: 190 | P7: Yadhira | Q7: =N7+O7 -> 190
A8: =A7+1 -> 4 | B8: 46025 | C8: 41735143 | D8: Danilo Fernando Yánac Talaverano | E8: Dyanact@gmail.com | F8: LOS OLIVOS | G8: 949 727 949 | H8: X | J8: 110 | K8: 270 | L8: COBR | M8: PLIN JL | N8: 110 | O8: 0 | P8: Yadhira | Q8: =N8+O8 -> 110
A9: =A8+1 -> 5 | B9: 46018 | C9: 40893521 | D9: Rolando Farfán Gutiérrez | E9: Rolandofarfang@gmail.com | F9: CERCADO | G9: 999 143 296 | I9: X | J9: 175 | L9: PAGO | M9: PLIN JL | N9: 175 | P9: Greici | Q9: =N9+O9 -> 175 | R9: validado en diciembre, costo reprogramacion
A10: =A9+1 -> 6 | N10: 0 | P10: Sofia | Q10: =N10+O10 -> 0
A11: =A10+1 -> 7 | B11: 46028 | C11: 44384611 | D11: LUIGGI VIGO PESANTES | E11: luiggijvp@gmail.com | F11: PUEBLO LIBRE | I11: X | J11: 100 | K11: 100 | L11: COBR | M11: YAPE JL | N11: 100 | O11: 100 | P11: Greici | Q11: =N11+O11 -> 200
A12: =A11+1 -> 8 | B12: 46031 | C12: 6800803 | D12: Jorge Aguinaga Alvites | E12: jorge.aguinaga@gmail.com | F12: San miguel | G12: 961377923 | I12: x | J12: 220 | L12: PAGO | M12: YAPE JL | N12: 220 | P12: Gabriela | Q12: =N12+O12 -> 220
A13: =A12+1 -> 9 | B13: 46034 | C13: 70342491 | D13: Jandir Rivera Quispe | E13: jandir.rivera10@gmail.com | F13: San Bartolo | G13: 987552563 | H13: X | J13: 0 | N13: 0 | P13: Sofia | Q13: =N13+O13 -> 0 | R13: cobrar 17
A14: =A13+1 -> 10 | M14: YAPE JL | N14: 0 | P14: Yadhira | Q14: =N14+O14 -> 0 | R14: CANCELO EN SU BB1 EL 11/01
A15: =A14+1 -> 11 | M15: YAPE JL | N15: 0 | P15: Yadhira | Q15: =N15+O15 -> 0 | R15: CANCELO EN SU BB1 EL 11/01
A16: =A15+1 -> 12 | B16: 46034 | C16: 40493159 | D16: Manuel Grados Morales | E16: manuel.grados.gm@gmail.com | F16: SAN ISIDRO | G16: 954 580 454 | H16: X | J16: 190 | L16: PAGO | M16: YAPE JL | N16: 190 | P16: Greici | Q16: =N16+O16 -> 190
A17: =A16+1 -> 13 | B17: 46034 | C17: 45909459 | D17: Jonathan Ramírez Flor | E17: joramirezf@hotmail.com | F17: JESUS MARIA | G17: 954 580 454 | H17: X | J17: 190 | L17: PAGO | M17: YAPE JL | N17: 190 | P17: Greici | Q17: =N17+O17 -> 190
A18: =A17+1 -> 14 | B18: 46035 | C18: 47575960 | D18: Abdul Kazan Espinoza Guerra | E18: Ka.carmed@gmail.com | F18: RIMAC | G18: 970 345 673 | H18: X | J18: 190 | L18: PAGO | M18: YAPE JL | N18: 190 | P18: Yadhira | Q18: =N18+O18 -> 190
A19: =A18+1 -> 15 | B19: 46035 | C19: 15753576 | D19: Jaime Raúl Santa Cruz Culquicondor | E19: Jaimesantacruz2306@gmail.com | F19: HUARAL | G19: 998 341 966 | H19: X | I19: X | J19: 180 | K19: 180 | L19: COBR | M19: BBVA JL | N19: 180 | O19: 180 | P19: Yadhira | Q19: =N19+O19 -> 360
A20: =A19+1 -> 16 | B20: 46036 | C20: 10114558 | D20: Ricardo Francisco Florian | E20: francisco.rm@pucp.pe | F20: SJL | G20: 986 601 138 | H20: X | J20: 90 | K20: 90 | L20: COBR | M20: YAPE JL | N20: 90 | O20: 90 | P20: Yadhira | Q20: =N20+O20 -> 180
A21: =A20+1 -> 17 | B21: 46036 | C21: 75527342 | D21: Manuel Francisco Davalos | E21: francisco.rm@pucp.pe | F21: SJL | G21: 986 601 138 | H21: X | J21: 90 | K21: 90 | L21: COBR | M21: YAPE JL | N21: 90 | O21: 90 | P21: Yadhira | Q21: =N21+O21 -> 180
A22: =A21+1 -> 18 | B22: 46035 | C22: 42084574 | D22: Cesar La Rosa-Sánchez Cordero | E22: cesarlarosa_20@yahoo.com.pe | H22: x | I22: x | J22: 380 | L22: PAGO | M22: YAPE JL | N22: 380 | P22: Katherine | Q22: =N22+O22 -> 380
A23: =A22+1 -> 19 | B23: 46036 | C23: 61802066 | D23: Alexander Zambrano Vizcarra | F23: San Juan de Miraflores | H23: x | J23: 190 | L23: PAGO | M23: YAPE JL | N23: 190 | P23: Katherine | Q23: =N23+O23 -> 190
A24: =A23+1 -> 20 | B24: 46036 | C24: 61741943 | D24: Fabricio Urbina Zambrano | F24: San Juan de Miraflores | H24: x | J24: 190 | L24: PAGO | M24: YAPE JL | N24: 190 | P24: Katherine | Q24: =N24+O24 -> 190
A25: =A24+1 -> 21 | B25: 46036 | C25: 70919834 | D25: Carlos Eduardo Cumpa alayo | F25: San Juan de lurigancho | H25: x | J25: 200 | L25: PAGO | M25: YAPE JL | N25: 200 | P25: Katherine | Q25: =N25+O25 -> 200
A26: =A25+1 -> 22 | B26: 46036 | C26: 25728595 | D26: Juan Augusto Arrunátegui Paiva | E26: arrunateguijuan@gmail.com | F26: Pueblo Libre | H26: x | J26: 190 | L26: PAGO | N26: 190 | P26: Gabriela | Q26: =N26+O26 -> 190
A27: =A26+1 -> 23 | B27: 46036 | C27: 73171842 | D27: César Augusto Arrunátegui Vásquez | E27: arrunateguijuan@gmail.com | F27: Pueblo libre | H27: x | I27: x | J27: 110 | K27: 270 | L27: PAGO | N27: 110 | O27: 270 | P27: Gabriela | Q27: =N27+O27 -> 380
A28: =A27+1 -> 24 | B28: 46036 | C28: 76601657 | D28: Anthony Giancarlos rios agesto | E28: gian.agesto.tkm@gmail.com | F28: Huacho | H28: x | J28: 150 | L28: PAGO | N28: 150 | P28: Gabriela | Q28: =N28+O28 -> 150
A29: =A28+1 -> 25 | B29: 46036 | C29: 40902213 | D29: DAVID DANIEL ECOS BENAVIDES | E29: david.ecos@icloud.com | F29: Lince | G29: 923 335 713 | H29: x | I29: x | J29: 380 | L29: PAGO | M29: BCP JL | N29: 150 | P29: Gabriela | Q29: =N29+O29 -> 150
A30: =A29+1 -> 26 | B30: 46037 | C30: 77060706 | D30: ALEXIS FABIAN SANTA CRUZ QUILLAY | E30: santacruzalexis950@gmail.com | F30: HUARAL | G30: 917395017 | H30: X | I30: X | J30: 180 | K30: 180 | L30: COBR | M30: BBVA JL | N30: 180 | O30: 180 | P30: Yadhira | Q30: =N30+O30 -> 360
A31: =A30+1 -> 27 | B31: 46038 | C31: *09493577 | D31: MARCO DEL CASTILLO RUIZ CARO | E31: MMDCRC@HOTMAIL.COM | F31: Chorrillos | H31: x | I31: x | J31: 380 | L31: PAGO | M31: YAPE JL | N31: 380 | P31: Gabriela | Q31: =N31+O31 -> 380
A32: =A31+1 -> 28 | B32: 46038 | C32: 76799413 | D32: Gerson Alejandro Nogueyra Saldarriaga | E32: ng.producciones.art@gmail.com | F32: CALLAO | G32: 923 677 984 | H32: X | J32: 0 | N32: 0 | P32: Yadhira | Q32: =N32+O32 -> 0 | R32: PAGARA EN CLASE DE CYC 18/01
A33: =A32+1 -> 29 | B33: 46038 | C33: 45963559 | D33: ROSARIO TRUJILLO HIGINIO | H33: x | J33: 180 | L33: PAGO | M33: YAPE JL | N33: 180 | P33: Katherine | Q33: =N33+O33 -> 180
A34: =A33+1 -> 30 | B34: 46038 | C34: 42243221 | D34: ALFREDO LOZADA FERNANDEZ | H34: x | J34: 180 | L34: PAGO | M34: YAPE JL | N34: 180 | P34: Katherine | Q34: =N34+O34 -> 180
A35: =A34+1 -> 31 | B35: 46038 | C35: 7576311 | D35: Carlos sucasaca Vargas | E35: Carlossucasaca@gmail.com | F35: san Juan de Miraflores | G35: (347) 592-6379 | H35: x | J35: 175 | K35: 45 | L35: COBR | M35: LINK-CULQUI | N35: 166 | O35: 0 | P35: Sofia | Q35: =N35+O35 -> 166 | R35: CANCELO 50 DOLARES
A36: =A35+1 -> 32 | B36: 46038 | D36: Jonathan Ivan Espinoza Ruiz | H36: x | J36: 110 | K36: 110 | L36: COBR | M36: YAPE JL | N36: 110 | O36: 110 | P36: Katherine | Q36: =N36+O36 -> 220
A37: =A36+1 -> 33 | B37: 46038 | C37: 43567257 | D37: Marleny Quispe Vilca | H37: x | I37: x | J37: 200 | K37: 180 | L37: COBR | M37: YAPE JL | N37: 200 | O37: 180 | P37: Gabriela | Q37: =N37+O37 -> 380
A38: =A37+1 -> 34 | B38: 46038 | C38: *005367250 | D38: Andres valencia muñoz | E38: Kevinandresvalenciamunoz@gmail.com | F38: La Molina | I38: x | J38: 190 | K38: 190 | L38: COBR | M38: YAPE JL | N38: 190 | O38: 190 | P38: Gabriela | Q38: =N38+O38 -> 380
A39: =A38+1 -> 35 | B39: 46039 | C39: 10624546 | D39: Carlos Zuñiga Cabrera | E39: carlosazunigacabrera@gmail.com | F39: Jesus Maria | G39: 964 850 682 | H39: x | J39: 200 | L39: PAGO | M39: YAPE JL | N39: 200 | P39: Sofia | Q39: =N39+O39 -> 200
A40: =A39+1 -> 36 | B40: 46039 | C40: 06532689, | D40: Mack Alexis Flores Chalco, | E40: alexisflores1973@gmail.com | F40: Miraflores, | I40: x | J40: 100 | K40: 100 | L40: COBR | M40: YAPE JL | N40: 100 | O40: 100 | P40: Sofia | Q40: =N40+O40 -> 200 | R40: pago 50%
A41: =A40+1 -> 37 | B41: 46041 | C41: 45083846 | D41: Jheff Alfredo Laura Martínez | E41: simplementejheff@gmail.com | F41: SURQUILLO | G41: 954 088 624 | H41: X | J41: 95 | K41: 95 | L41: COBR | M41: YAPE JL | N41: 95 | O41: 95 | P41: Yadhira | Q41: =N41+O41 -> 190
A42: =A41+1 -> 38 | B42: 46041 | C42: 46059441 | D42: Tessy Tairo Cerrón | E42: tessy.tairo6@gmail.com | F42: SURQUILLO | G42: 980494024 | H42: X | J42: 95 | K42: 95 | L42: COBR | M42: YAPE JL | N42: 95 | O42: 95 | P42: Yadhira | Q42: =N42+O42 -> 190
A43: =A42+1 -> 39 | B43: 46041 | C43: 10874243 | D43: Julio Silverio Moreno Ruiz | E43: magne978@gmail.com | F43: Ate | G43: 977176244 | I43: x | J43: 220 | L43: PAGO | M43: YAPE JL | N43: 220 | P43: Sofia | Q43: =N43+O43 -> 220
A44: =A43+1 -> 40 | B44: 46041 | C44: 40891944 | D44: John Ronald Alvarez Achaquihui | E44: aronalito@gmail.com | F44: la victoria | G44: 982002653 | H44: x | J44: 100 | K44: 100 | L44: COBR | M44: YAPE JL | N44: 100 | O44: 0 | P44: Sofia | Q44: =N44+O44 -> 100
A45: =A44+1 -> 41 | B45: 46039 | C45: 45967311 | D45: Michael Jonathan Yaya Gutierrez | H45: x | J45: 110 | K45: 110 | L45: COBR | M45: YAPE JL | N45: 110 | O45: 110 | P45: Katherine | Q45: =N45+O45 -> 220
A46: =A45+1 -> 42 | B46: 46042 | C46: 72751542 | D46: Esteban Camarena Seminario | E46: esteban.camarena.stevejobs@gmail.com | I46: x | J46: 190 | L46: PAGO | M46: YAPE JL | N46: 190 | P46: Katherine | Q46: =N46+O46 -> 190
A47: =A46+1 -> 43 | B47: 46043 | C47: CE 009160780 | D47: Patricio Pablo Rojas Salgado | E47: Pablorojas30@hotmail.com | F47: SAN ISIDRO | G47: 936 950 655 | I47: X | J47: 220 | L47: PAGO | M47: YAPE JL | N47: 220 | P47: Yadhira | Q47: =N47+O47 -> 220
A48: =A47+1 -> 44 | B48: 46042 | C48: 41455446 | D48: Eder Genaro Estrada Montañez | E48: eder16221@gmail.com | F48: Callao | G48: =51977709418 -> 51977709418 | I48: x | J48: 190 | L48: PAGO | M48: YAPE JL | N48: 190 | P48: Sofia | Q48: =N48+O48 -> 190 | R48: pago para el 31 tmb
A49: =A48+1 -> 45 | B49: 46042 | C49: 44211612 | D49: Victor Caballero | E49: victorcaballeror@gmail.com | F49: san Borja | G49: =51944252125 -> 51944252125 | I49: x | J49: 180 | K49: 180 | L49: COBR | M49: BCP EPP | N49: 180 | O49: 180 | P49: Yadhira | Q49: =N49+O49 -> 360 | R49: 0.5
A50: =A49+1 -> 46 | B50: 46043 | C50: 73261104 | D50: Carlos Matias Chico | E50: Rosa.chico@telrad.pe | F50: BARRANCO | G50: 970 180 581 | I50: X | J50: 90 | K50: 90 | L50: COBR | M50: YAPE JL | N50: 90 | O50: 90 | P50: Greici | Q50: =N50+O50 -> 180
A51: =A50+1 -> 47 | B51: 46043 | C51: 61806520 | D51: Joaquin Matias Chico | E51: Matiaschicojoaquin@gmail.com | F51: BARRANCO | G51: 970 180 581 | I51: X | J51: 90 | K51: 90 | L51: COBR | M51: YAPE JL | N51: 90 | O51: 90 | P51: Greici | Q51: =N51+O51 -> 180
A52: =A51+1 -> 48 | B52: 46043 | C52: 41202552 | D52: José Andrés Ventura Panta | E52: Karina.chz@hotmail.com | F52: MIRAFLORES | G52: 960 258 096 | I52: X | J52: 175 | K52: 175 | L52: COBR | M52: BCP JL | N52: 175 | O52: 175 | P52: Greici | Q52: =N52+O52 -> 350 | R52: ADQUIEREN 2 CURSOS
A53: =A52+1 -> 49 | B53: 46043 | C53: 004684587 | D53: Anna Karina Colmenares Hernández | E53: Karina.chz@hotmail.com | F53: MIRAFLORES | G53: 960 258 096 | I53: X | J53: 175 | K53: 175 | L53: COBR | M53: BCP JL | N53: 175 | O53: 175 | P53: Greici | Q53: =N53+O53 -> 350 | R53: ADQUIEREN 2 CURSOS
A54: =A53+1 -> 50 | B54: 46043 | D54: Lissete Hinojosa Quiroz | F54: san miguel | I54: x | J54: 190 | L54: PAGO | M54: YAPE JL | N54: 190 | P54: Katherine | Q54: =N54+O54 -> 190
A55: =A54+1 -> 51 | B55: 46044 | D55: Christiam Vasquez | I55: x | J55: 190 | L55: PAGO | M55: YAPE JL | N55: 190 | P55: Katherine | Q55: =N55+O55 -> 190
A56: =A55+1 -> 52 | B56: 46044 | D56: Diana Honores | I56: x | J56: 190 | L56: PAGO | M56: YAPE JL | N56: 190 | P56: Katherine | Q56: =N56+O56 -> 190
A57: =A56+1 -> 53 | B57: 46044 | D57: Gustavo Alfredo Anchante Chacaltana | I57: x | J57: 110 | K57: 110 | L57: COBR | M57: YAPE JL | N57: 110 | O57: 0 | P57: Katherine | Q57: =N57+O57 -> 110
A58: =A57+1 -> 54 | B58: 46044 | D58: Lizet De Guadalupe Roque Coronado | I58: x | J58: 190 | L58: PAGO | M58: YAPE JL | N58: 190 | P58: Katherine | Q58: =N58+O58 -> 190
A59: =A58+1 -> 55 | B59: 46044 | D59: Pedro Raúl Artemio Alfaro Torres | I59: x | J59: 190 | L59: PAGO | M59: YAPE JL | N59: 190 | P59: Katherine | Q59: =N59+O59 -> 190
A60: =A59+1 -> 56 | B60: 46045 | C60: 40391708 | D60: EDWARD GALLO TORRES | E60: edwardgallo.309@gmail.com | F60: LA PERLA - CALLAO | G60: 924561456 | I60: X | J60: 175 | L60: PAGO | M60: PLIN JL | N60: 175 | P60: Sofia | Q60: =N60+O60 -> 175
A61: =A60+1 -> 57 | B61: 46045 | C61: 40532533 | D61: KATHERINE ZUNICO FLORES | E61: kattyzunicoflores@gmail.com | F61: LA PERLA - CALLAO | G61: 924561456 | I61: X | J61: 175 | L61: PAGO | M61: PLIN JL | N61: 175 | P61: Sofia | Q61: =N61+O61 -> 175
A62: =A61+1 -> 58 | B62: 46045 | C62: 44767965 | D62: Massiel Karolina Ayala Guerra | I62: x | J62: 180 | K62: 180 | L62: COBR | M62: PLIN JL | N62: 180 | O62: 180 | P62: Katherine | Q62: =N62+O62 -> 360
A63: =A62+1 -> 59 | B63: 46039 | D63: Percy Alonso Alama Porras | E63: betty2535@hotmail.com | F63: BARRANCO | G63: 995 747 995 | H63: X | J63: 90 | K63: 90 | L63: COBR | N63: 90 | O63: 90 | P63: Greici | Q63: =N63+O63 -> 180
A64: =A63+1 -> 60 | B64: 46039 | D64: CAMILA MAYHUA ALVARADO | E64: betty2535@hotmail.com | F64: BARRANCO | H64: X | J64: 90 | K64: 90 | L64: COBR | N64: 90 | O64: 90 | P64: Greici | Q64: =N64+O64 -> 180
A65: =A64+1 -> 61 | B65: 46046 | C65: 72190417 | D65: Omar Bruno Guillén Sánchez | E65: brunohuarcaya2@gmail.com | F65: SJM | I65: x | J65: 100 | K65: 280 | L65: COBR | N65: 100 | O65: 280 | P65: Katherine | Q65: =N65+O65 -> 380
A66: =A65+1 -> 62 | B66: 46039 | C66: 7975001 | D66: wilbert palomino | E66: wpa.rocaalta@gmail.com | F66: El Agustino | G66: =51987402177 -> 51987402177 | I66: x | J66: 190 | L66: PAGO | M66: YAPE JL | N66: 190 | P66: JL | Q66: =N66+O66 -> 190
A67: =A66+1 -> 63 | D67: RENZO CHAVEZ | I67: X | J67: 110 | K67: 110 | L67: COBR | M67: MERC-PAG | N67: 104.88 | O67: 110 | P67: JL | Q67: =N67+O67 -> 214.88
A68: =A67+1 -> 64 | D68: ALEJANDRO CHAUCA | I68: X | J68: 110 | K68: 110 | L68: COBR | M68: MERC-PAG | N68: 104.88 | O68: 110 | P68: JL | Q68: =N68+O68 -> 214.88
A69: =A68+1 -> 65 | Q69: =N69+O69 -> 0
A70: =A69+1 -> 66 | Q70: =N70+O70 -> 0
A71: =A70+1 -> 67 | Q71: =N71+O71 -> 0
A72: =A71+1 -> 68 | Q72: =N72+O72 -> 0 | R72: OBSERVACION
G73: Total Registrados | H73: =COUNTIF(H4:H72,"X") -> 34 | I73: =COUNTIF(I4:I72,"X") -> 34 | J73: =SUM(J4:J72) -> 10000 | K73: =SUM(K4:K72) -> 3885 | N73: =SUM(N4:N72) -> 9750.76 | O73: =SUM(O4:O72) -> 3360
G74: Total Cupos | H74: 34 | I74: 34 | J74: =SUM(J73:K73) -> 13885 | N74: =SUM(N73:O73) -> 13110.76
G75: Cupos Libres | H75: =H74-H73 -> 0 | I75: =I74-I73 -> 0 | J75: Total Venta Fecha | N75: Venta Final Fecha
H76: 200 | I76: 200 | T76: -
H77: =H75*H76 -> 0 | I77: =I75*I76 -> 0
H78: =H77+I77 -> 0

Sheet AFI-F5
A1: - | D1: J
A2: CONTROL DE REGISTRO PARTICIPANTES
A3: PARRILLERO AFICIONADO | G3: 45688
A4: ID | B4: FE_ REGISTRO | C4: DNI | D4: NOMBRES Y APELLIDOS | E4: EMAIL | F4: DISTRITO | G4: WSP | H4: BB2 | I4: BB1 | J4: MONTO | K4: xCOBRAR | L4: ESTADO | M4: CUENTA | N4: INGRESO | O4: SALDO | P4: VENDEDOR | Q4: TOTAL | R4: OBSERVACION
A5: 1 | B5: 46024 | C5: 76197577 | D5: Anderson Achata | E5: andersonachata@gmail.com | F5: SAN LUIS | G5: 913 872 010 | H5: X | J5: 190 | L5: PAGO | M5: PLIN JL | N5: 190 | P5: Yadhira | Q5: =N5+O5 -> 190 | R5: OBSERVACION
A6: =A5+1 -> 2 | B6: 46025 | C6: 41735143 | D6: Danilo Fernando Yánac Talaverano | E6: Dyanact@gmail.com | F6: LOS OLIVOS | G6: 949 727 949 | H6: X | J6: 0 | N6: 0 | P6: Yadhira | Q6: =N6+O6 -> 0 | R6: PAGARA EN SU CLASE 25/01
A7: =A6+1 -> 3 | B7: 46038 | C7: *005367250 | D7: Andres valencia muñoz | E7: Kevinandresvalenciamunoz@gmail.com | F7: La Molina | I7: x | J7: 0 | N7: 0 | P7: Yadhira | Q7: =N7+O7 -> 0
A8: =A7+1 -> 4 | B8: 46042 | C8: 72751542 | D8: Esteban Camarena Seminario | E8: esteban.camarena.stevejobs@gmail.com | Q8: =N8+O8 -> 0 | R8: reprogramo para el 07/02
A9: =A8+1 -> 5 | B9: 46030 | C9: 46063723 | D9: carlos ore yufre | E9: carlosyufre29@gmail.com | F9: los olivos | G9: 948350215 | I9: X | J9: 0 | L9: PAGO | N9: 0 | P9: Sofia | Q9: =N9+O9 -> 0 | R9: PAGO EL 17
A10: =A9+1 -> 6 | B10: 46042 | C10: 20063027 | D10: Irene Delma Calderón Marcos | E10: irene_delma11@hotmail.com | F10: CERCADO | G10: 982 593 099 | H10: X | J10: 190 | K10: 190 | L10: COBR | M10: YAPE JL | N10: 190 | O10: 190 | P10: Greici | Q10: =N10+O10 -> 380 | R10: LLEVARA 2 CURSOS, COBRAR LO RESTANTE
A11: =A10+1 -> 7 | B11: 46042 | C11: 41455446 | D11: Eder Genaro Estrada Montañez | E11: eder16221@gmail.com | F11: Callao | G11: =51977709418 -> 51977709418 | I11: x | J11: 190 | K11: 0 | L11: PAGO | N11: 190 | P11: Sofia | Q11: =N11+O11 -> 190 | R11: ya pago x 2 clases
A12: =A11+1 -> 8 | B12: 46042 | C12: 44211612 | D12: Victor Caballero | E12: victorcaballeror@gmail.com | F12: san Borja | G12: =51944252125 -> 51944252125 | I12: x | J12: 0 | K12: 0 | N12: 0 | P12: Yadhira | Q12: =N12+O12 -> 0 | R12: pagara el 25
A13: =A12+1 -> 9 | B13: 46043 | C13: 10117893 | D13: Juan Valencia León | E13: jvl.juanvalencialeon@gmail.com | F13: SJL | G13: 962 075 283 | I13: x | J13: 210 | L13: PAGO | M13: LINK-CULQUI | N13: 195 | P13: Sofia | Q13: =N13+O13 -> 195
A14: =A13+1 -> 10 | B14: 46045 | C14: 6189524 | D14: Raul plácido Villavicencio torre | E14: rpvillavicencio@hotmail.com | F14: La Molina | G14: 948 310 299 | I14: X | J14: 175 | K14: 175 | L14: COBR | M14: PLIN JL | N14: 175 | O14: 175 | P14: Sofia | Q14: =N14+O14 -> 350
A15: =A14+1 -> 11 | B15: 46045 | C15: 72903045 | D15: Raul Ricardo Villavicencio Cabrera | F15: La Molina | G15: 948 310 299 | I15: X | J15: 175 | K15: 175 | L15: COBR | M15: PLIN JL | N15: 175 | O15: 175 | P15: Sofia | Q15: =N15+O15 -> 350
A16: =A15+1 -> 12 | B16: 46044 | C16: 20538382598 | D16: César Domínguez Añanca | E16: serfafain.sac@hotmail.com | F16: Callao | G16: =+51998294866 -> 51998294866 | I16: X | J16: 100 | K16: 100 | L16: COBR | M16: YAPE JL | N16: 100 | O16: 100 | P16: Sofia | Q16: =N16+O16 -> 200
A17: =A16+1 -> 13 | N17: 180 | P17: Sofia | Q17: =N17+O17 -> 180 | R17: reprogramacion 28 febrero
A18: =A17+1 -> 14 | B18: 46045 | C18: 44767965 | D18: Massiel Karolina Ayala Guerra | I18: x | L18: PAGO | N18: 0 | P18: Katherine | Q18: =N18+O18 -> 0
A19: =A18+1 -> 15 | B19: 46046 | C19: 41855242 | D19: Jimmy Joel lizarzaburu martel | E19: Jimmijoel123@hotmail.com | F19: Huacho | G19: 934091909 | H19: X | I19: X | J19: 200 | K19: 150 | L19: COBR | M19: BBVA JL | N19: 200 | O19: 150 | P19: Sofia | Q19: =N19+O19 -> 350
A20: =A19+1 -> 16 | B20: 46047 | C20: 40 767009 | D20: Angela Geraldine quiñones granados | E20: Jimmijoel123@hotmail.com | F20: Huacho | G20: 934091909 | H20: X | I20: X | J20: 200 | K20: 150 | L20: COBR | M20: BBVA JL | N20: 200 | O20: 150 | P20: Sofia | Q20: =N20+O20 -> 350
A21: =A20+1 -> 17 | B21: 46046 | C21: 72190417 | D21: Omar Bruno Guillén Sánchez | E21: brunohuarcaya2@gmail.com | F21: SJM | I21: x | J21: 0 | N21: 0 | Q21: =N21+O21 -> 0
A22: =A21+1 -> 18 | B22: 46047 | D22: wilbert palomino | E22: wpa.rocaalta@gmail.com | F22: El Agustino | G22: =51987402177 -> 51987402177 | I22: x | J22: 190 | L22: PAGO | M22: YAPE JL | N22: 190 | P22: Sofia | Q22: =N22+O22 -> 190
A23: =A22+1 -> 19 | B23: 46048 | C23: *08537300 | D23: Fabio Martin Vilca Romero | E23: vrmartin1966@gmail.com | F23: Pueblo Libre | G23: 998 177 293 | H23: x | J23: 150 | L23: PAGO | M23: BCP JL | N23: 150 | P23: Gabriela | Q23: =N23+O23 -> 150
A24: =A23+1 -> 20 | B24: 46048 | C24: ⁠15434915 | D24: Alicia Ysabel Huaman Álvarez | E24: 4. ⁠omar_antonio_2015@hotmail.com | F24: Surco | G24: 970 363 381 | H24: x | J24: 190 | K24: 190 | N24: 190 | O24: 190 | P24: Sofia | Q24: =N24+O24 -> 380
A25: =A24+1 -> 21 | B25: 46049 | C25: 42949843 | D25: Jesús Ángel Ramos Salas | E25: ramossalasjesus@gmail.com | F25: Villa el Salvador | G25: 987 351 312 | I25: x | J25: 220 | L25: PAGO | M25: BCP JL | N25: 220 | P25: Tania | Q25: =N25+O25 -> 220
A26: =A25+1 -> 22 | B26: 46049 | C26: 43889926 | D26: Nikola Vera Torres | E26: Nikolavera26@gmail.com | F26: SJM | G26: 938 375 442 | H26: X | J26: 90 | K26: 90 | L26: COBR | M26: MERC-PAG | N26: 82.5 | O26: 0 | P26: Yadhira | Q26: =N26+O26 -> 82.5
A27: =A26+1 -> 23 | B27: 46049 | C27: 81007981 | D27: Megan Vera Tapia | E27: Nikolavera26@gmail.com | F27: SJM | G27: 938 375 442 | H27: X | J27: 90 | K27: 90 | L27: COBR | M27: MERC-PAG | N27: 82.5 | O27: 0 | P27: Yadhira | Q27: =N27+O27 -> 82.5
A28: =A27+1 -> 24 | B28: 46049 | C28: 42506745 | D28: Santiago Alex Loayza Briceño | E28: saloayzab@gmail.com | F28: Trujillo | G28: 942 839 138 | H28: x | I28: x | J28: 380 | L28: PAGO | M28: PLIN JL | N28: 380 | P28: Tania | Q28: =N28+O28 -> 380
A29: =A28+1 -> 25 | B29: 46049 | C29: 47428047 | D29: José Freundt Montoya | E29: Je.freundt@hotmail.com | F29: LINCE | G29: 944 368 518 | H29: X | J29: 200 | L29: PAGO | M29: PLIN JL | N29: 200 | P29: Greici | Q29: =N29+O29 -> 200
A30: =A29+1 -> 26 | B30: 46049 | C30: 48263528 | D30: Mercy Apaza Cayó | E30: mercyapazacayod@gmail.com | G30: 982 022 591 | H30: x | I30: x | J30: 100 | K30: 280 | L30: COBR | M30: PLIN JL | N30: 100 | O30: 280 | P30: Gabriela | Q30: =N30+O30 -> 380
A31: =A30+1 -> 27 | B31: 46050 | C31: *08057676 | D31: Cornelio ortiz jaimes | E31: cimacorsac@hotmail.com | F31: Puente Piedra | H31: x | J31: 220 | L31: PAGO | M31: BCP JL | N31: 220 | P31: Gabriela | Q31: =N31+O31 -> 220
A32: =A31+1 -> 28 | B32: 46050 | C32: 74501400 | D32: JUAN DIEGO ALBINO RAMOS | E32: 4. jdalbinoramos@gmail.com | F32: santiago de surco | G32: =+51999292184 -> 51999292184 | H32: X | J32: 90 | K32: 90 | L32: COBR | M32: PLIN JL | N32: 90 | O32: 90 | P32: Sofia | Q32: =N32+O32 -> 180
A33: =A32+1 -> 29 | B33: 46050 | C33: ⁠43278388 | D33: Michael Parraga | E33: michael.parraga@gmail.com | F33: miraflores | G33: =+51999292184 -> 51999292184 | H33: X | J33: 90 | K33: 90 | L33: COBR | M33: PLIN JL | N33: 90 | O33: 90 | P33: Sofia | Q33: =N33+O33 -> 180
A34: =A33+1 -> 30 | B34: 46050 | C34: 41967125 | D34: Luis Manuel villa solis | E34: lvillasolis@gmail.com | F34: SJM | G34: 997 788 156 | H34: X | J34: 100 | K34: 100 | L34: COBR | M34: BBVA JL | N34: 100 | O34: 100 | P34: Yadhira | Q34: =N34+O34 -> 200
A35: =A34+1 -> 31 | B35: 46050 | D35: Leonel villa abril | E35: lvillasolis@gmail.com | F35: SJM | G35: 997 788 156 | H35: X | J35: 50 | K35: 50 | L35: COBR | M35: BBVA JL | N35: 50 | O35: 50 | P35: Yadhira | Q35: =N35+O35 -> 100 | R35: MENOR DE 8 AÑOS
A36: =A35+1 -> 32 | B36: 46050 | C36: 73180684 | D36: Diana Vicuña | F36: surco | H36: x | J36: 180 | L36: PAGO | M36: PLIN JL | N36: 180 | P36: Katherine | Q36: =N36+O36 -> 180
A37: =A36+1 -> 33 | B37: 46050 | C37: 47810241 | D37: Franco Leon | F37: surco | H37: x | J37: 180 | L37: PAGO | M37: PLIN JL | N37: 180 | P37: Katherine | Q37: =N37+O37 -> 180
A38: =A37+1 -> 34 | B38: 46050 | C38: 7508517 | D38: Miguel Nicho Pacheco | F38: smp | I38: x | J38: 200 | L38: PAGO | M38: BCP JL | N38: 200 | P38: Katherine | Q38: =N38+O38 -> 200
A39: =A38+1 -> 35 | B39: 46051 | C39: 4295 3767 | D39: Jose Elías López Acostupa | E39: Joseelíaslopezacostupa@gmail.com | F39: Miraflores | G39: =+51963748480 -> 51963748480 | H39: x | J39: 180 | K39: 180 | L39: COBR | M39: BCP JL | N39: 180 | O39: 180 | P39: Sofia | Q39: =N39+O39 -> 360
A40: =A39+1 -> 36 | B40: 46051 | C40: 9601263 | D40: MARCO ANTONIO PRADO VALERA | I40: x | J40: 200 | L40: PAGO | M40: BBVA JL | N40: 200 | P40: Katherine | Q40: =N40+O40 -> 200
A41: =A40+1 -> 37 | B41: 46051 | C41: 72510875 | D41: Héctor paul peña ajalcriña | E41: Hectorpaul_18@hotmail.com | F41: Pueblo libre | G41: 955 737 238 | I41: x | J41: 220 | L41: PAGO | M41: PLIN JL | N41: 220 | P41: Gabriela | Q41: =N41+O41 -> 220
A42: =A41+1 -> 38 | B42: 46051 | C42: 43154748 | D42: Jose Luis Ñahui Ñiquen | E42: Jnahuiniquen@gmail.com | F42: LINCE | G42: 948 714 975 | H42: X | J42: 180 | K42: 180 | L42: COBR | M42: PLIN JL | N42: 180 | O42: 180 | P42: Yadhira | Q42: =N42+O42 -> 360
A43: =A42+1 -> 39 | B43: 46378 | C43: 2908730 | D43: Gino Garamendi | I43: x | J43: 220 | L43: PAGO | M43: PLIN JL | N43: 220 | P43: Katherine | Q43: =N43+O43 -> 220
A44: =A43+1 -> 40 | B44: 46051 | C44: 42312770 | D44: Edson Palomino Santillan | I44: x | J44: 220 | L44: PAGO | M44: PLIN JL | N44: 220 | P44: Katherine | Q44: =N44+O44 -> 220
A45: =A44+1 -> 41 | B45: 46051 | C45: 08163189 | D45: Rossana Casella | E45: rossanacasellav@hotmail.com | F45: RIMAC | G45: 990 040 557 | I45: X | J45: 175 | K45: 175 | L45: COBR | M45: PLIN JL | N45: 175 | O45: 175 | P45: Greici | Q45: =N45+O45 -> 350 | R45: PROMO 2 CURSOS AFI
A46: =A45+1 -> 42 | B46: 46051 | C46: 08139122 | D46: Danilo Véliz | E46: dmvelizs@hotmail.com | F46: RIMAC | I46: X | J46: 175 | K46: 175 | L46: COBR | M46: PLIN JL | N46: 175 | O46: 175 | P46: Greici | Q46: =N46+O46 -> 350 | R46: PROMO 2 CURSOS AFI
A47: =A46+1 -> 43 | B47: 46052 | D47: Deyvi la rosa abarca | F47: LINCE | I47: x | J47: 190 | L47: PAGO | M47: PLIN JL | N47: 190 | P47: Katherine | Q47: =N47+O47 -> 190
A48: =A47+1 -> 44 | B48: 46052 | D48: Rosa arica chinguel | F48: LINCE | I48: x | J48: 190 | L48: PAGO | M48: PLIN JL | N48: 190 | P48: Katherine | Q48: =N48+O48 -> 190
A49: =A48+1 -> 45 | B49: 46052 | C49: 60758869 | D49: Ivan Ramirez | E49: ir253302@gmail.com | F49: PUEBLO LIBRE | G49: 999 666 042 | I49: X | J49: 25 | K49: 155 | L49: COBR | M49: PLIN JL | N49: 25 | O49: 155 | P49: Yadhira | Q49: =N49+O49 -> 180
A50: =A49+1 -> 46 | B50: 46052 | C50: 10038690 | D50: Marta Ventura | E50: martaventura4242@gmail.com | F50: PUEBLO LIBRE | G50: 999 666 042 | I50: X | J50: 25 | K50: 155 | L50: COBR | M50: BBVA JL | N50: 25 | O50: 155 | P50: Yadhira | Q50: =N50+O50 -> 180
A51: =A50+1 -> 47 | B51: 46052 | C51: 9980577 | D51: Luís Antonio Cruz Gargate | E51: gargate_74@hotmail.com | F51: CARABAYLLO | G51: 998 165 695 | I51: X | J51: 200 | L51: PAGO | M51: PLIN JL | N51: 200 | P51: FH | Q51: =N51+O51 -> 200
A52: =A51+1 -> 48 | B52: 46052 | C52: 2- 47608434 | D52: Jherson Zapata Quintana | E52: - jhersonzapata@gmail.com | F52: 3- Cercado de Lima | G52: 938 960 593 | I52: X | J52: 85 | K52: 85 | L52: COBR | M52: PLIN JL | N52: 85 | O52: 85 | P52: Sofia | Q52: =N52+O52 -> 170
A53: =A52+1 -> 49 | B53: 46052 | C53: 40585729 | D53: Marco Burgos | F53: 3- Cercado de Lima | G53: 939 960 593 | I53: X | J53: 85 | K53: 85 | L53: COBR | M53: PLIN JL | N53: 85 | O53: 85 | P53: Sofia | Q53: =N53+O53 -> 170
A54: =A53+1 -> 50 | B54: 46052 | C54: 77204820 | D54: Edwin Osorio | F54: 3- Cercado de Lima | G54: 940 960 593 | I54: X | J54: 85 | K54: 85 | L54: COBR | M54: PLIN JL | N54: 85 | O54: 85 | P54: Sofia | Q54: =N54+O54 -> 170
A55: =A54+1 -> 51 | B55: 46052 | D55: RICARDO RUIZ CHAVEZ | G55: 955 880 422 | H55: X | J55: 50 | K55: 125 | L55: COBR | M55: PLIN JL | N55: 50 | O55: 125 | P55: Greici | Q55: =N55+O55 -> 175 | R55: SON 4 PERSONAS, ADELANTARON 350 Y RESTA 350
A56: =A55+1 -> 52 | B56: 46052 | D56: RAFAEL RUIZ VASQUEZ | G56: 955 880 422 | H56: X | J56: 50 | K56: 125 | L56: COBR | M56: PLIN JL | N56: 50 | O56: 125 | P56: Greici | Q56: =N56+O56 -> 175 | R56: SON 4 PERSONAS, ADELANTARON 350 Y RESTA 350
A57: =A56+1 -> 53 | B57: 46052 | C57: 72186264 | D57: LUIS BARRA | H57: x | J57: 100 | K57: 100 | L57: COBR | M57: PLIN JL | N57: 100 | O57: 100 | P57: Katherine | Q57: =N57+O57 -> 200
A58: =A57+1 -> 54 | B58: 46052 | D58: Elio Huayllani candenas | F58: LA VICTORIA | G58: 950 228 116 | H58: X | J58: 50 | K58: 150 | L58: COBR | M58: PLIN JL | N58: 50 | O58: 150 | P58: Yadhira | Q58: =N58+O58 -> 200
A59: =A58+1 -> 55 | B59: 46052 | C59: 75968050 | D59: Alberto Jara | G59: =51986381281 -> 51986381281 | I59: X | J59: 90 | K59: 90 | L59: COBR | M59: PLIN JL | N59: 90 | O59: 90 | P59: Sofia | Q59: =N59+O59 -> 180
A60: =A59+1 -> 56 | B60: 46052 | C60: 74609696 | D60: Brigitte Oviedo Pérez | G60: =+51986381281 -> 51986381281 | I60: X | J60: 90 | K60: 90 | L60: COBR | M60: PLIN JL | N60: 90 | O60: 90 | P60: Sofia | Q60: =N60+O60 -> 180
A61: =A60+1 -> 57 | B61: 46052 | D61: Lucas Antonio prado Guerrero | I61: x | J61: 160 | L61: PAGO | M61: PLIN JL | N61: 160 | P61: Katherine | Q61: =N61+O61 -> 160
A62: =A61+1 -> 58 | B62: 46052 | D62: Camila Marroqui | H62: x | J62: 0 | Q62: =N62+O62 -> 0 | R62: comercial
A63: =A62+1 -> 59 | B63: 46052 | D63: Américo Ruiz Gutierrez | H63: X | J63: 125 | K63: 50 | L63: COBR | N63: 125 | O63: 50 | P63: Greici | Q63: =N63+O63 -> 175 | R63: SON 4 PERSONAS, ADELANTARON 350 Y RESTA 350
A64: =A63+1 -> 60 | B64: 46052 | D64: Frank Goytisolo Ruiz | H64: X | J64: 125 | K64: 50 | L64: COBR | N64: 125 | O64: 50 | P64: Greici | Q64: =N64+O64 -> 175 | R64: SON 4 PERSONAS, ADELANTARON 350 Y RESTA 350
A65: =A64+1 -> 61 | B65: 46053 | D65: ALISON PALOMINO | H65: X | J65: 190 | L65: PAGO | N65: 190 | P65: JL | Q65: =N65+O65 -> 190
A66: =A65+1 -> 62 | B66: 46053 | D66: JAIME ALBAN | H66: X | J66: 190 | L66: PAGO | N66: 190 | P66: JL | Q66: =N66+O66 -> 190
A67: =A66+1 -> 63 | Q67: =N67+O67 -> 0
A68: =A67+1 -> 64 | Q68: =N68+O68 -> 0
A69: =A68+1 -> 65 | Q69: =N69+O69 -> 0
A70: =A69+1 -> 66 | Q70: =N70+O70 -> 0
A71: =A70+1 -> 67 | Q71: =N71+O71 -> 0
A72: =A71+1 -> 68 | Q72: =N72+O72 -> 0 | R72: OBSERVACION
G73: Total Registrados | H73: =COUNTIF(H4:H72,"X") -> 30 | I73: =COUNTIF(I4:I72,"X") -> 34 | J73: =SUM(J4:J72) -> 8025 | K73: =SUM(K4:K72) -> 3975 | N73: =SUM(N4:N72) -> 8175 | O73: =SUM(O4:O72) -> 3795
G74: Total Cupos | H74: 34 | I74: 34 | J74: =SUM(J73:K73) -> 12000 | N74: =SUM(N73:O73) -> 11970
G75: Cupos Libres | H75: =H74-H73 -> 4 | I75: =I74-I73 -> 0 | J75: Total Venta Fecha | N75: Venta Final Fecha
H76: 200 | I76: 200 | T76: -
H77: =H75*H76 -> 800 | I77: =I75*I76 -> 0
H78: =H77+I77 -> 800

Sheet AFI-F6
A2: CONTROL DE REGISTRO PARTICIPANTES
A3: CILINDRO Y CAJA CHINA | G3: CYC
A4: ID | B4: FE_ REGISTRO | C4: DNI | D4: NOMBRES Y APELLIDOS | E4: EMAIL | F4: DISTRITO | G4: WSP | H4: 46046 | J4: MONTO | K4: xCOBRAR | L4: ESTADO | M4: CUENTA | N4: INGRESO | O4: SALDO | P4: VENDEDOR | Q4: TOTAL | R4: OBSERVACION
A5: 1 | B5: 46026 | C5: 6855160 | D5: ELIZABETH CAMONES SALVADOR | E5: JOSELYOVI@GMAIL.COM | F5: SURCO | G5: 949 900 144 | H5: X | J5: 100 | K5: 80 | L5: COBR | M5: YAPE JL | N5: 100 | O5: 0 | P5: Greici | Q5: =N5+O5 -> 100
A6: =A5+1 -> 2 | B6: 46026 | C6: 25430091 | D6: María Paucar Almeyda | E6: marialpa05@gmail.com | F6: SMP | H6: X | J6: 100 | K6: 90 | L6: COBR | M6: YAPE JL | N6: 100 | O6: 90 | P6: Greici | Q6: =N6+O6 -> 190
A7: =A6+1 -> 3 | B7: 46041 | D7: Néstor Vega Santaria | H7: x | J7: 160 | L7: PAGO | M7: YAPE JL | N7: 160 | P7: Katherine | Q7: =N7+O7 -> 160
A8: =A7+1 -> 4 | B8: 46042 | C8: 15983731 | D8: Rita María Pau Salguero | F8: comas | H8: x | J8: 190 | L8: PAGO | M8: MERC-PAG | N8: 180.99 | P8: Katherine | Q8: =N8+O8 -> 180.99
A9: =A8+1 -> 5 | B9: 46043 | C9: 46343807 | D9: Liliana yuchin lung timana | F9: lince | H9: x | J9: 75 | K9: 75 | L9: COBR | M9: YAPE JL | N9: 75 | O9: 75 | P9: Katherine | Q9: =N9+O9 -> 150
A10: =A9+1 -> 6 | B10: 46043 | C10: 43705747 | D10: Francisco Daniel Kawashita Okuyama | F10: lince | H10: x | J10: 75 | K10: 75 | L10: COBR | M10: YAPE JL | N10: 75 | O10: 75 | P10: Katherine | Q10: =N10+O10 -> 150
A11: =A10+1 -> 7 | B11: 46044 | C11: 46178506 | D11: Jennifer Ríos gil | E11: Sinjul887@gmail.com | H11: x | J11: 150 | L11: PAGO | M11: YAPE JL | N11: 150 | P11: Katherine | Q11: =N11+O11 -> 150
A12: =A11+1 -> 8 | B12: 46044 | C12: 10709192308 | D12: Carlos Ignacio Efraín Matamoros Cartolin | E12: altcg73@gmail.com | F12: sjl | H12: x | J12: 190 | L12: PAGO | M12: YAPE JL | N12: 190 | P12: Katherine | Q12: =N12+O12 -> 190
A13: =A12+1 -> 9 | B13: 46044 | C13: 48015781 | D13: Yoel Chávez nilupu | E13: Axelnilupu@gmail.com | F13: SJL | G13: 913 305 733 | H13: x | J13: 190 | L13: PAGO | M13: BCP JL | N13: 190 | P13: Gabriela | Q13: =N13+O13 -> 190
A14: =A13+1 -> 10 | B14: 46045 | C14: 09444421 | D14: Carola Ramorez Sanchez | E14: ccaro280@hotmail.com | F14: CERCADO | G14: 987 117 592 | H14: X | J14: 150 | L14: PAGO | M14: YAPE JL | N14: 150 | P14: Greici | Q14: =N14+O14 -> 150
A15: =A14+1 -> 11 | B15: 46045 | C15: 10475612 | D15: Jorge Napoleon Mercado Vilca | E15: Jnmercado1008@gmail.com | F15: CERCADO | G15: 987 117 592 | H15: X | J15: 150 | L15: PAGO | M15: YAPE JL | N15: 150 | P15: Greici | Q15: =N15+O15 -> 150
A16: =A15+1 -> 12 | B16: 46045 | D16: Daniel Espejo | H16: x | J16: 160 | L16: PAGO | M16: PLIN JL | N16: 160 | P16: Katherine | Q16: =N16+O16 -> 160
A17: =A16+1 -> 13 | B17: 46046 | C17: O5375028 | D17: María Ysabel Ruiz López | E17: maisarulo@gmail.com | G17: 965 661 435 | H17: X | J17: 190 | L17: PAGO | M17: PLIN JL | N17: 190 | P17: Greici | Q17: =N17+O17 -> 190
A18: =A17+1 -> 14 | Q18: =N18+O18 -> 0
A19: =A18+1 -> 15 | Q19: =N19+O19 -> 0
A20: =A19+1 -> 16 | Q20: =N20+O20 -> 0
A21: =A20+1 -> 17 | Q21: =N21+O21 -> 0
A22: =A21+1 -> 18 | Q22: =N22+O22 -> 0
A23: =A22+1 -> 19 | Q23: =N23+O23 -> 0
A24: =A23+1 -> 20 | Q24: =N24+O24 -> 0
A25: =A24+1 -> 21 | Q25: =N25+O25 -> 0
A26: =A25+1 -> 22 | Q26: =N26+O26 -> 0
A27: =A26+1 -> 23 | Q27: =N27+O27 -> 0
A28: =A27+1 -> 24 | Q28: =N28+O28 -> 0
A29: =A28+1 -> 25 | Q29: =N29+O29 -> 0
... A71: =A70+1 -> 67 | Q71: =N71+O71 -> 0
A72: =A71+1 -> 68 | Q72: =N72+O72 -> 0 | R72: OBSERVACION
G73: Total Registrados | H73: =COUNTIF(H4:H72,"X") -> 13 | I73: =COUNTIF(I4:I72,"X") -> 0 | J73: =SUM(J4:J72) -> 1880 | K73: =SUM(K4:K72) -> 320 | N73: =SUM(N4:N72) -> 1870.99 | O73: =SUM(O4:O72) -> 240
G74: Total Cupos | H74: 34 | I74: 34 | J74: =SUM(J73:K73) -> 2200 | N74: =SUM(N73:O73) -> 2110.99
G75: Cupos Libres | H75: =H74-H73 -> 21 | I75: =I74-I73 -> 34 | J75: Total Venta Fecha | N75: Venta Final Fecha
H76: 200 | I76: 200 | T76: -
H77: =H75*H76 -> 4200 | I77: =I75*I76 -> 6800
H78: =H77+I77 -> 11000

Sheet Burger-F7-F8
A2: CONTROL DE REGISTRO PARTICIPANTES
A3: BURGER | G3: burger
A4: ID | B4: FE_ REGISTRO | C4: DNI | D4: NOMBRES Y APELLIDOS | E4: EMAIL | F4: DISTRITO | G4: WSP | H4: 45668 | I4: 45675 | J4: MONTO | K4: xCOBRAR | L4: ESTADO | M4: CUENTA | N4: INGRESO | O4: SALDO | P4: VENDEDOR | Q4: TOTAL | R4: OBSERVACION
A5: 1 | B5: 46013 | C5: 10619586 | D5: Marleny Juipa Quiñónez | E5: ma46ju@gmail.com | F5: SMP | G5: 922 835 447 | H5: x | J5: 0 | K5: 75 | L5: COBR | M5: YAPE JL | N5: 0 | P5: Yadhira | Q5: =N5+O5 -> 0 | R5: REPROGRAMACIÓN
A6: =A5+1 -> 2 | B6: 46015 | D6: Eddy Dumler Lazo | E6: renzo.dumler@gmail.com | H6: x | J6: 140 | L6: PAGO | M6: YAPE JL | N6: 140 | P6: Katherine | Q6: =N6+O6 -> 140
A7: =A6+1 -> 3 | B7: 46015 | D7: Antonio Javier García Marocho | E7: aj.garciamarocho@gmail.com | H7: x | J7: 140 | L7: PAGO | M7: YAPE JL | N7: 140 | P7: Katherine | Q7: =N7+O7 -> 140
A8: =A7+1 -> 4 | B8: 46015 | C8: 76324543 | D8: Maggio Fabricio Yañez Carrion | H8: x | J8: 150 | L8: PAGO | M8: YAPE JL | N8: 150 | P8: Katherine | Q8: =N8+O8 -> 150
A9: =A8+1 -> 5 | B9: 46021 | D9: Gonzalo Aponte | H9: x | J9: 150 | L9: PAGO | M9: YAPE JL | N9: 150 | P9: Sofia | Q9: =N9+O9 -> 150 | R9: SOFIA
A10: =A9+1 -> 6 | B10: 46021 | C10: 47618556 | D10: Jeanfranco Ruiz Suarez | E10: Jeanfranco.Suarez507@gmail.com | F10: SMP | G10: 962956122 | H10: x | J10: 150 | L10: PAGO | M10: MERC-PAG | N10: 142.64 | P10: Greici | Q10: =N10+O10 -> 142.64
A11: =A10+1 -> 7 | B11: 46027 | C11: 41925594 | D11: Piero Velarde | H11: x | J11: 150 | L11: PAGO | M11: BCP JL | N11: 150 | P11: Katherine | Q11: =N11+O11 -> 150
A12: =A11+1 -> 8 | B12: 46028 | D12: Jessy Barrenachea | H12: x | J12: 125 | L12: PAGO | M12: BCP JL | N12: 125 | P12: Katherine | Q12: =N12+O12 -> 125
A13: =A12+1 -> 9 | B13: 46028 | D13: Elizabeth Álvarez | H13: x | J13: 125 | L13: PAGO | M13: BCP JL | N13: 125 | P13: Katherine | Q13: =N13+O13 -> 125
A14: =A13+1 -> 10 | B14: 6686137 | C14: 42492557 | D14: Carlos Adolfo Cano Aquino | E14: Nijachi28681@gmail.com | F14: Comas | G14: 944646368 | H14: x | J14: 150 | L14: PAGO | M14: YAPE JL | N14: 150 | P14: Gabriela | Q14: =N14+O14 -> 150
A15: =A14+1 -> 11 | B15: 46029 | C15: 30422127 | D15: Ynes Mendoza Justo | H15: x | J15: 140 | L15: PAGO | M15: YAPE JL | N15: 140 | P15: Katherine | Q15: =N15+O15 -> 140
A16: =A15+1 -> 12 | B16: 46029 | C16: 40249280 | D16: Cynthian Milagros Lazo Chauca | E16: sharmony047@gmail.com | F16: Callao | G16: 938 121 803 | H16: x | J16: 140 | L16: PAGO | M16: YAPE JL | N16: 140 | P16: Gabriela | Q16: =N16+O16 -> 140
A17: =A16+1 -> 13 | B17: 46029 | C17: 71434270 | D17: Diego Sebastián Aranda Lazo | E17: sharmony047@gmail.com | F17: Callao | G17: 938 121 803 | H17: x | J17: 140 | L17: PAGO | M17: YAPE JL | N17: 140 | P17: Gabriela | Q17: =N17+O17 -> 140
A18: =A17+1 -> 14 | B18: 46028 | C18: ´03663755 | D18: LUPITA QUINTANA SILVA | F18: CALLAO | G18: 933 070 617 | H18: X | J18: 50 | K18: 100 | L18: COBR | M18: YAPE JL | N18: 50 | O18: 100 | P18: Greici | Q18: =N18+O18 -> 150
A19: =A18+1 -> 15 | B19: 46028 | C19: 000326987 | D19: Dalia Del. Socorro Carvajal. | F19: RIMAC | G19: 965 713 303 | H19: X | J19: 80 | K19: 80 | L19: COBR | M19: YAPE JL | N19: 80 | O19: 80 | P19: Greici | Q19: =N19+O19 -> 160
A20: =A19+1 -> 16 | B20: 46029 | C20: 45484567 | D20: Alfredo reza Matos | E20: Alfredorezamatos@gmail.com | F20: SJL | G20: 999 084 715 | H20: X | J20: 125 | L20: PAGO | M20: BCP EPP | N20: 125 | P20: Yadhira | Q20: =N20+O20 -> 125
A21: =A20+1 -> 17 | B21: 46029 | C21: 46988012 | D21: Elizabeth condori de la Peña | E21: Nathaly.2305.3@gmail.com | F21: SJL | G21: 999 084 715 | H21: X | J21: 125 | L21: PAGO | M21: BCP EPP | N21: 125 | P21: Yadhira | Q21: =N21+O21 -> 125
A22: =A21+1 -> 18 | B22: 46029 | C22: 73563073 | D22: Jesús Amir Huaccho Hidalgo | E22: ruthm_hidalgo@hotmail.com | F22: SURCO | G22: 996 757 353 | H22: X | J22: 150 | L22: PAGO | M22: YAPE JL | N22: 150 | P22: Yadhira | Q22: =N22+O22 -> 150
A23: =A22+1 -> 19 | B23: 46028 | C23: 48550749 | D23: Brandon Barros Vizano | E23: brandon_honor2@outlook.com | F23: LOS OLIVOS | H23: X | J23: 50 | K23: 100 | L23: COBR | M23: YAPE JL | N23: 50 | O23: 100 | P23: Greici | Q23: =N23+O23 -> 150
A24: =A23+1 -> 20 | B24: 46031 | C24: 41914080 | D24: Yulisa Quispe Cuba | F24: EL AGUSTINO | G24: 968 148 037 | H24: X | J24: 50 | K24: 90 | L24: COBR | M24: YAPE JL | N24: 50 | O24: 90 | P24: Greici | Q24: =N24+O24 -> 140
A25: =A24+1 -> 21 | B25: 46031 | C25: 47915079 | D25: Juan Carlos borja | E25: Jcarlos.borjah@gmail.com | F25: Villa el salvador | G25: 976 057 552 | H25: X | J25: 100 | K25: 350 | L25: COBR | M25: YAPE JL | N25: 100 | O25: 0 | P25: Greici | Q25: =N25+O25 -> 100
A26: =A25+1 -> 22 | B26: 46031 | D26: Helen llanos | H26: x | J26: 125 | L26: PAGO | M26: YAPE JL | N26: 125 | P26: Katherine | Q26: =N26+O26 -> 125
A27: =A26+1 -> 23 | B27: 46031 | D27: Nancy Tamani | H27: x | J27: 125 | L27: PAGO | M27: YAPE JL | N27: 125 | P27: Katherine | Q27: =N27+O27 -> 125
A28: =A27+1 -> 24 | B28: 46031 | D28: Oscar Vega | H28: x | J28: 150 | L28: PAGO | M28: EFECTIVO | N28: 150 | P28: Katherine | Q28: =N28+O28 -> 150
A29: =A28+1 -> 25 | Q29: =N29+O29 -> 0
A30: =A29+1 -> 26 | Q30: =N30+O30 -> 0
A31: =A30+1 -> 27 | Q31: =N31+O31 -> 0
A32: =A31+1 -> 28 | Q32: =N32+O32 -> 0 | R32: OBSERVACION
A33: x
A34: x
A35: x
A36: 1 | B36: 46034 | C36: Rimac | D36: Nataly Cristina Aparicio Perez | I36: x | J36: 150 | L36: PAGO | M36: YAPE JL | N36: 150 | P36: Katherine | Q36: =N36+O36 -> 150 | R36: OBSERVACION
A37: =A36+1 -> 2 | B37: 46034 | C37: 47915079 | D37: JUAN CARLOS BORJA | E37: Jcarlos.borjah@gmail.com | F37: VILLA EL SALVADOR | G37: 976 057 552 | I37: X | N37: 0 | P37: Greici | Q37: =N37+O37 -> 0
A38: =A37+1 -> 3 | B38: 46034 | C38: 41151304 | D38: Edwin Quichiz Bernal | E38: edwinquichiz@gmail.com | F38: HUACHO | G38: 983849673 | I38: X | J38: 140 | L38: PAGO | M38: YAPE JL | N38: 140 | P38: Greici | Q38: =N38+O38 -> 140
A39: =A38+1 -> 4 | B39: 46034 | C39: 43903012 | D39: Fernando Quichiz Bernal | E39: Fernando4822@hotmail.com | F39: HUACHO | G39: 983849673 | I39: X | J39: 140 | L39: PAGO | M39: YAPE JL | N39: 140 | P39: Greici | Q39: =N39+O39 -> 140
A40: =A39+1 -> 5 | B40: 46034 | C40: 42333620 | D40: Oscar Quichiz Bernal | E40: aosquibe@gmail.com | F40: HUACHO | G40: 983849673 | I40: X | J40: 140 | L40: PAGO | M40: YAPE JL | N40: 140 | P40: Greici | Q40: =N40+O40 -> 140
A41: =A40+1 -> 6 | B41: 46035 | C41: 08202850 | D41: Teófila Sánchez mellado | F41: LURIN | G41: 972 814 258 | I41: X | J41: 150 | L41: PAGO | M41: BCP EPP | N41: 150 | P41: Greici | Q41: =N41+O41 -> 150
A42: =A41+1 -> 7 | B42: 46036 | C42: 15607314737 | D42: Jocsahel jose Valera morales | E42: jocsahel912@gmail.com | F42: ATE | G42: 983 486 695 | I42: X | J42: 62.5 | K42: 62.5 | L42: COBR | M42: YAPE JL | N42: 62.5 | O42: 62.5 | P42: Greici | Q42: =N42+O42 -> 125
A43: =A42+1 -> 8 | B43: 46036 | C43: 007629170 | D43: Jocsmar José Valera Osorio | E43: kosorio270876@gmail.com | F43: ATE | I43: X | J43: 62.5 | K43: 62.5 | L43: COBR | M43: YAPE JL | N43: 62.5 | O43: 62.5 | P43: Greici | Q43: =N43+O43 -> 125
A44: =A43+1 -> 9 | B44: 46036 | C44: 72901811 | D44: flor María esperanza Urtecho rabines | E44: esperanzah1994.flor@gmail.com | F44: ATE | G44: 923894374 | I44: X | J44: 140 | L44: PAGO | M44: YAPE JL | N44: 140 | P44: Greici | Q44: =N44+O44 -> 140
A45: =A44+1 -> 10 | B45: 46013 | C45: 10619586 | D45: Marleny Juipa Quiñónez | E45: ma46ju@gmail.com | F45: SMP | G45: 922 835 447 | I45: X | J45: 0 | K45: 75 | L45: COBR | M45: YAPE JL | N45: 0 | O45: 75 | P45: Yadhira | Q45: =N45+O45 -> 75 | R45: REPROGRAMACION
A46: =A45+1 -> 11 | B46: 46036 | C46: 28316449 | D46: Almonacid Lujan shonin | F46: RIMAC | G46: 907 531 070 | I46: X | J46: 50 | K46: 90 | L46: COBR | M46: YAPE JL | N46: 50 | O46: 0 | P46: Greici | Q46: =N46+O46 -> 50
A47: =A46+1 -> 12 | B47: 46036 | C47: 76601657 | D47: Anthony Giancarlos rios agesto | E47: gian.agesto.tkm@gmail.com | F47: Huacho | I47: x | J47: 150 | N47: 150 | P47: Gabriela | Q47: =N47+O47 -> 150
A48: =A47+1 -> 13 | B48: 46038 | C48: 76799413 | D48: Gerson Alejandro Nogueyra Saldarriaga | E48: ng.producciones.art@gmail.com | F48: CALLAO | G48: 923 677 984 | I48: X | J48: 0 | N48: 0 | P48: Yadhira | Q48: =N48+O48 -> 0 | R48: PAGARA EN CLASE DE CYC 18/01
A49: =A48+1 -> 14 | B49: 46038 | D49: Janet Quincho Ruiz | I49: x | J49: 70 | K49: 70 | L49: COBR | M49: YAPE JL | N49: 70 | O49: 70 | P49: Katherine | Q49: =N49+O49 -> 140
A50: =A49+1 -> 15 | B50: 46038 | D50: Gloria Stefany Garcia López | I50: x | J50: 75 | K50: 75 | L50: COBR | M50: YAPE JL | N50: 75 | O50: 0 | P50: Katherine | Q50: =N50+O50 -> 75
A51: =A50+1 -> 16 | B51: 46038 | D51: JEAN CARLOS CARDENAS CALMA | I51: x | J51: 140 | L51: PAGO | M51: YAPE JL | N51: 140 | P51: Katherine | Q51: =N51+O51 -> 140
A52: =A51+1 -> 17 | Q52: =N52+O52 -> 0
A53: =A52+1 -> 18 | Q53: =N53+O53 -> 0
A54: =A53+1 -> 19 | Q54: =N54+O54 -> 0
A55: =A54+1 -> 20 | Q55: =N55+O55 -> 0
A56: =A55+1 -> 21 | Q56: =N56+O56 -> 0
A57: =A56+1 -> 22 | Q57: =N57+O57 -> 0
A58: =A57+1 -> 23 | Q58: =N58+O58 -> 0
A59: =A58+1 -> 24 | Q59: =N59+O59 -> 0
A60: =A59+1 -> 25 | Q60: =N60+O60 -> 0
A61: =A60+1 -> 26 | Q61: =N61+O61 -> 0
A62: =A61+1 -> 27 | Q62: =N62+O62 -> 0
A63: =A62+1 -> 28 | Q63: =N63+O63 -> 0 | R63: OBSERVACION
A64: x
A65: x
A66: x
G67: Total Registrados | H67: =COUNTIF(H4:H66,"X") -> 24 | I67: =COUNTIF(I4:I66,"X") -> 16 | J67: =SUM(J4:J66) -> 4300 | K67: =SUM(K4:K66) -> 1230 | N67: =SUM(N4:N66) -> 4292.64 | O67: =SUM(O4:O66) -> 640
G68: Total Cupos | H68: 28 | I68: 28 | J68: =SUM(J67:K67) -> 5530 | N68: =SUM(N67:O67) -> 4932.64
G69: Cupos Libres | H69: =H68-H67 -> 4 | I69: =I68-I67 -> 12 | J69: Total Venta Fecha | N69: Venta Final Fecha
H70: 140 | I70: 140 | T70: -
H71: =H69*H70 -> 560 | I71: =I69*I70 -> 1680
H72: =SUM(H71:I71) -> 2240

Sheet Burger-F9-F10
A2: CONTROL DE REGISTRO PARTICIPANTES
A3: BURGER | G3: BURGER
A4: ID | B4: FE_ REGISTRO | C4: DNI | D4: NOMBRES Y APELLIDOS | E4: EMAIL | F4: DISTRITO | G4: WSP | H4: 46046 | J4: MONTO | K4: xCOBRAR | L4: ESTADO | M4: CUENTA | N4: INGRESO | O4: SALDO | P4: VENDEDOR | Q4: TOTAL | R4: OBSERVACION
A5: 1 | B5: 46027 | C5: 46123466 | D5: Pilar coveñas Ramos | E5: naturaquimi@gmail.com | F5: SMP | G5: 965 713 303 | H5: X | J5: 0 | L5: PAGO | M5: YAPE JL | N5: 0 | P5: Greici | Q5: =N5+O5 -> 0
A6: =A5+1 -> 2 | B6: 46036 | C6: 22314008 | D6: Elias Campos Sanchez. | H6: x | J6: 0 | N6: 0 | P6: Katherine | Q6: =N6+O6 -> 0
A7: =A6+1 -> 3 | B7: 46037 | C7: 10421776631 | D7: Karin Chacon Gonzales | E7: Karinchacong@gmail.com | F7: PACHACAMAC | G7: 959 264 231 | H7: X | J7: 150 | K7: 0 | L7: PAGO | M7: YAPE JL | N7: 150 | P7: Greici | Q7: =N7+O7 -> 150
A8: =A7+1 -> 4 | B8: 46042 | C8: 71523029 | D8: Aaron Castillo | H8: x | J8: 130 | L8: PAGO | M8: YAPE JL | N8: 130 | P8: Katherine | Q8: =N8+O8 -> 130
A9: =A8+1 -> 5 | B9: 46042 | C9: 40171540 | D9: Norita Isabel Uraco Acho | E9: noritauraco024@gmail.com | F9: SURQUILLO | G9: 969 047 205 | H9: X | J9: 140 | L9: PAGO | M9: YAPE JL | N9: 140 | P9: Greici | Q9: =N9+O9 -> 140
A10: =A9+1 -> 6 | B10: 46043 | C10: 20613656058 | D10: Miguel Rios López | E10: cuatroburgueses@gmail.com | F10: Pueblo Libre | G10: 962 202 597 | H10: X | J10: 62.5 | K10: 62.5 | L10: COBR | M10: YAPE JL | N10: 62.5 | O10: 62.5 | P10: Greici | Q10: =N10+O10 -> 125
A11: =A10+1 -> 7 | B11: 46043 | C11: 20613656058 | D11: Diana Mora Terrones | E11: cuatroburgueses@gmail.com | F11: Pueblo Libre | G11: 962 202 597 | H11: X | J11: 62.5 | K11: 62.5 | L11: COBR | M11: YAPE JL | N11: 62.5 | O11: 62.5 | P11: Greici | Q11: =N11+O11 -> 125
A12: =A11+1 -> 8 | B12: 46043 | C12: 70954105 | D12: Jesús Geldres Pérez | E12: jesusgeldres7@gmail.com | F12: SJL | G12: 960 621 786 | H12: X | J12: 80 | K12: 70 | L12: COBR | M12: YAPE JL | N12: 80 | O12: 70 | P12: Greici | Q12: =N12+O12 -> 150
A13: =A17+1 -> 10 | B13: 46045 | C13: 4475965 | D13: Henry Manuel Miranda Cuya | E13: Henrymc23@gmail.com | F13: SMP | G13: 973 905 000 | H13: X | J13: 62.5 | K13: 62.5 | L13: COBR | M13: BCP EPP | N13: 62.5 | O13: 62.5 | P13: Yadhira | Q13: =N13+O13 -> 125
A14: =A13+1 -> 11 | B14: 46045 | C14: 46210391 | D14: Sthefany Milagros Alata Romero | E14: Sthefany2321@gmail.com | F14: SMP | G14: 973 905 000 | H14: X | J14: 62.5 | K14: 62.5 | L14: COBR | M14: BCP EPP | N14: 62.5 | O14: 62.5 | P14: Yadhira | Q14: =N14+O14 -> 125
A15: =A14+1 -> 12 | B15: 46044 | C15: 74471041 | D15: JESUS ENRIQUE MEDINA LAZO | E15: jesus_8_n@hotmail.com | F15: VILLA EL SALVADOR | G15: 944807550 | H15: x | J15: 140 | L15: PAGO | M15: YAPE JL | N15: 140 | P15: Sofia | Q15: =N15+O15 -> 140
A16: =A15+1 -> 13 | B16: 46044 | C16: 41062653 | D16: Milagros Lazo Osorio | E16: lazoosoriomilagros@gmail.com | F16: VILLA EL SALVADOR | G16: 944807550 | H16: x | J16: 140 | L16: PAGO | M16: YAPE JL | N16: 140 | P16: Sofia | Q16: =N16+O16 -> 140
A17: =A12+1 -> 9 | B17: 46044 | C17: 46178506 | D17: Jennifer Ríos gil | E17: Sinjul887@gmail.com | H17: x | J17: 150 | L17: PAGO | M17: YAPE JL | N17: 150 | P17: Katherine | Q17: =N17+O17 -> 150
A18: =A16+1 -> 14 | B18: 46045 | C18: 47699885 | D18: Luz Fabiola Rodriguez Guerrero | E18: luzfabiolaa1603@gmail.com | F18: HUARAL | G18: 989 823 869 | H18: X | J18: 125 | L18: PAGO | M18: YAPE JL | N18: 125 | P18: Greici | Q18: =N18+O18 -> 125
A19: =A18+1 -> 15 | B19: 46045 | C19: 42601788 | D19: Andre Geusepee Cruz Barzola | E19: andrecruzbarzola@hotmail.com | F19: MIRAFLORES | G19: 989 823 869 | H19: X | J19: 125 | L19: PAGO | M19: YAPE JL | N19: 125 | P19: Greici | Q19: =N19+O19 -> 125
A20: =A19+1 -> 16 | B20: 46045 | D20: Anderson Meneses Vilca | F20: huachipa | H20: x | J20: 50 | K20: 100 | L20: COBR | M20: YAPE JL | N20: 50 | O20: 100 | P20: Katherine | Q20: =N20+O20 -> 150
A21: =A20+1 -> 17 | B21: 46043 | C21: 10096401286 | D21: ROXANA PACCINI | E21: luis.perez@rems.pe | F21: SURCO | H21: X | J21: 62.5 | K21: 62.5 | L21: COBR | M21: YAPE JL | N21: 62.5 | O21: 62.5 | P21: Greici | Q21: =N21+O21 -> 125
A22: =A21+1 -> 18 | B22: 46043 | C22: 9935937 | D22: LUIS PEREZ | E22: luis.perez@rems.pe | F22: SURCO | H22: X | J22: 62.5 | K22: 62.5 | L22: COBR | M22: YAPE JL | N22: 62.5 | O22: 62.5 | P22: Greici | Q22: =N22+O22 -> 125
A23: =A22+1 -> 19 | Q23: =N23+O23 -> 0
A24: =A23+1 -> 20 | Q24: =N24+O24 -> 0
A25: =A24+1 -> 21 | Q25: =N25+O25 -> 0
A26: =A25+1 -> 22 | Q26: =N26+O26 -> 0
A27: =A26+1 -> 23 | Q27: =N27+O27 -> 0
A28: =A27+1 -> 24 | Q28: =N28+O28 -> 0
A29: =A28+1 -> 25 | Q29: =N29+O29 -> 0
A30: =A29+1 -> 26 | Q30: =N30+O30 -> 0
A31: =A30+1 -> 27 | Q31: =N31+O31 -> 0
A32: =A31+1 -> 28 | Q32: =N32+O32 -> 0
A33: x
A34: x
A35: x
A36: 1 | Q36: =N36+O36 -> 0
A37: =A36+1 -> 2 | Q37: =N37+O37 -> 0
A38: =A37+1 -> 3 | Q38: =N38+O38 -> 0
A39: =A38+1 -> 4 | Q39: =N39+O39 -> 0
A40: =A39+1 -> 5 | Q40: =N40+O40 -> 0
A41: =A40+1 -> 6 | Q41: =N41+O41 -> 0
A42: =A41+1 -> 7 | Q42: =N42+O42 -> 0
A43: =A42+1 -> 8 | Q43: =N43+O43 -> 0
A44: =A43+1 -> 9 | Q44: =N44+O44 -> 0
A45: =A44+1 -> 10 | Q45: =N45+O45 -> 0
A46: =A45+1 -> 11 | Q46: =N46+O46 -> 0
A47: =A46+1 -> 12 | Q47: =N47+O47 -> 0
A48: =A47+1 -> 13 | Q48: =N48+O48 -> 0
... A63: =A62+1 -> 28 | Q63: =N63+O63 -> 0
A64: x
A65: x
A66: x
G67: Total Registrados | H67: =COUNTIF(H4:H66,"X") -> 18 | I67: =COUNTIF(I4:I66,"X") -> 0 | J67: =SUM(J4:J66) -> 1605 | K67: =SUM(K4:K66) -> 545 | N67: =SUM(N4:N66) -> 1605 | O67: =SUM(O4:O66) -> 545
G68: Total Cupos | H68: 28 | I68: 28 | J68: =SUM(J67:K67) -> 2150 | N68: =SUM(N67:O67) -> 2150
G69: Cupos Libres | H69: =H68-H67 -> 10 | I69: =I68-I67 -> 28 | J69: Total Venta Fecha | N69: Venta Final Fecha
H70: 140 | I70: 140 | T70: -
H71: =H69*H70 -> 1400 | I71: =I69*I70 -> 3920
H72: =H71+I71 -> 5320

Sheet ONLINE
A2: CONTROL DE REGISTRO PARTICIPANTES
A3: ONLINE | G3: online
A4: ID | B4: FE_ REGISTRO | C4: DNI | D4: NOMBRES Y APELLIDOS | E4: EMAIL | F4: DEPARTAMENTO | G4: WSP | H4: X | I4: X | J4: MONTO | K4: xCOBRAR | L4: ESTADO | M4: CUENTA | N4: INGRESO | O4: SALDO | P4: VENDEDOR | Q4: TOTAL | R4: OBSERVACION
A5: 1 | B5: 46030 | C5: 72323085 | D5: Miguel Angel Minaya Gonzalez | E5: mi.minaya.go@hotmail.com | H5: x | J5: 150 | L5: PAGO | M5: YAPE JL | N5: 150 | P5: Katherine | Q5: =N5+O5 -> 150
A6: =A5+1 -> 2 | B6: 46036 | C6: 71825325 | D6: Edinson grower lostaunau padilla | E6: Mikelacayetana23@gmail.com | F6: LIMA | G6: 983 486 695 | H6: X | J6: 150 | L6: PAGO | M6: YAPE JL | N6: 150 | P6: Greici | Q6: =N6+O6 -> 150
A7: =A6+1 -> 3 | B7: 46038 | C7: 47901451 | D7: Mauro ore | E7: Fernando_ore92@hotmail.com | F7: SJL | H7: x | J7: 150 | L7: PAGO | M7: BCP JL | N7: 150 | P7: Gabriela | Q7: =N7+O7 -> 150
A8: =A7+1 -> 4 | B8: 46038 | C8: 42371088 | D8: Jherardina Ore Rengifo | E8: jhera84.jor@gmail.com | H8: x | J8: 50 | L8: PAGO | M8: YAPE JL | N8: 50 | P8: Katherine | Q8: =N8+O8 -> 50
A9: =A8+1 -> 5 | B9: 46038 | C9: 42567710 | D9: Juvenal Zamalloa Aguirre | E9: juvicha.z@gmail.com | H9: x | J9: 150 | L9: PAGO | M9: YAPE JL | N9: 150 | P9: Katherine | Q9: =N9+O9 -> 150
A10: =A9+1 -> 6 | B10: 46043 | C10: 44931185 | D10: Joel flores jacinto | E10: Joe1430156@gmail.com | F10: Huanuco | H10: x | J10: 150 | L10: PAGO | M10: BCP JL | N10: 150 | P10: Gabriela | Q10: =N10+O10 -> 150
A11: =A10+1 -> 7 | B11: 46050 | C11: 70678890 | D11: Ricardo franco davila nuñez | E11: ricardodavilanu07@gmail.com | F11: CAMANÁ | G11: 966 463 572 | H11: X | J11: 70 | L11: PAGO | M11: PLIN JL | N11: 70 | P11: Tania | Q11: =N11+O11 -> 70 | R11: SOLO ACCEDE A CURSO ONLINE DE HAMBURGUESAS
A12: =A11+1 -> 8 | B12: 45687 | C12: 20725023 | D12: César Juan Cortijo Villalobos | F12: Junin | H12: x | J12: 150 | L12: PAGO | M12: PLIN JL | N12: 150 | P12: Gabriela | Q12: =N12+O12 -> 150
A13: =A12+1 -> 9 | B13: 46051 | C13: 9377789 | D13: Benjamin Lau Chiong | E13: benjalau@yahoo.com | H13: X | J13: 150 | L13: PAGO | N13: 150 | P13: Katherine | Q13: =N13+O13 -> 150
A14: =A13+1 -> 10 | B14: 46053 | C14: 45287120 | D14: Fredy Condori Hancco | E14: Fredycondorihancco62@gmail.com | H14: x | J14: 150 | L14: PAGO | M14: PLIN JL | N14: 150 | P14: Gabriela | Q14: =N14+O14 -> 150
A15: =A14+1 -> 11 | Q15: =N15+O15 -> 0
A16: =A15+1 -> 12 | Q16: =N16+O16 -> 0
A17: =A16+1 -> 13 | Q17: =N17+O17 -> 0
A18: =A17+1 -> 14 | Q18: =N18+O18 -> 0
A19: =A18+1 -> 15 | Q19: =N19+O19 -> 0
A20: =A19+1 -> 16 | Q20: =N20+O20 -> 0
A21: =A20+1 -> 17 | Q21: =N21+O21 -> 0
A22: =A21+1 -> 18 | Q22: =N22+O22 -> 0
A23: =A22+1 -> 19 | Q23: =N23+O23 -> 0
A24: =A23+1 -> 20 | Q24: =N24+O24 -> 0
A25: =A24+1 -> 21 | Q25: =N25+O25 -> 0
A26: =A25+1 -> 22 | Q26: =N26+O26 -> 0
... A204: =A203+1 -> 200 | Q204: =N204+O204 -> 0
G205: Total Registrados | H205: =COUNTIF(H4:H204,"X") -> 11 | I205: =COUNTIF(I4:I204,"X") -> 1 | J205: =SUM(J4:J204) -> 1320 | N205: =SUM(N4:N204) -> 1320 | O205: =SUM(O4:O204) -> 0
G206: Total Cupos | H206: 50 | I206: 50 | J206: =SUM(J205) -> 1320 | N206: =SUM(N205:O205) -> 1320
G207: Cupos Libres | H207: =H206-H205 -> 39 | I207: =I206-I205 -> 49 | J207: Total Venta Fecha | N207: Venta Final Fecha
H208: 150 | I208: 150 | T208: -
H209: =H207*H208 -> 5850 | I209: =I207*I208 -> 7350
H210: =H209+I209 -> 13200

Sheet CyC-F11-F12
A2: CONTROL DE REGISTRO PARTICIPANTES
A3: CILINDRO Y CAJA CHINA | G3: CyC F9
A4: ID | B4: FE_ REGISTRO | C4: DNI | D4: NOMBRES Y APELLIDOS | E4: EMAIL | F4: DISTRITO | G4: WSP | H4: 45667 | I4: 46040 | J4: MONTO | K4: xCOBRAR | L4: ESTADO | M4: CUENTA | N4: INGRESO | O4: SALDO | P4: VENDEDOR | Q4: TOTAL | R4: OBSERVACION
A5: 1 | B5: 46013 | C5: 44402809 | D5: Pedro Gonzales Correa | E5: pegc68@gmail.com | F5: SANTA ANITA | G5: 959379754 | H5: x | J5: 185 | L5: PAGO | M5: YAPE JL | N5: 185 | P5: Yadhira | Q5: =N5+O5 -> 185
A6: =A5+1 -> 2 | B6: 46015 | C6: 43328710 | D6: Fernando García Rojas | E6: anthonygb89@gmail.com | F6: MIRAFLORES | G6: 985 546 938 | H6: x | J6: 100 | K6: 90 | L6: COBR | M6: YAPE JL | N6: 100 | O6: 90 | P6: Greici | Q6: =N6+O6 -> 190
A7: =A6+1 -> 3 | B7: 46016 | D7: HILDA MERCEDES ZAVALA RAMOS | E7: Julio.aliagaz@pucp.edu.pe | H7: x | J7: 80 | K7: 85 | L7: PAGO | M7: YAPE JL | N7: 80 | O7: 85 | P7: Katherine | Q7: =N7+O7 -> 165 | R7: Completo pago el 10/01
A8: =A7+1 -> 4 | B8: 46016 | D8: JULIO GODOFREDO ALIAGA SUÁREZ | E8: Julio.aliagaz@pucp.edu.pe | H8: x | J8: 80 | K8: 85 | L8: PAGO | M8: YAPE JL | N8: 80 | O8: 85 | P8: Katherine | Q8: =N8+O8 -> 165 | R8: Completo pago el 10/01
A9: =A8+1 -> 5 | B9: 46024 | C9: 40030613 | D9: Elio Rios Cardenas | E9: emz2011@hotmail.com | F9: SAN ISIDRO | G9: 991 708 648 | H9: x | J9: 190 | L9: PAGO | M9: PLIN JL | N9: 190 | P9: Yadhira | Q9: =N9+O9 -> 190
A10: =A9+1 -> 6 | B10: 46022 | C10: 9257561 | D10: Haydee Loayza | E10: naturaquimi@gmail.com | F10: SJM | G10: 995 755 666 | H10: x | J10: 185 | L10: PAGO | M10: PLIN JL | N10: 185 | P10: Greici | Q10: =N10+O10 -> 185
A11: =A10+1 -> 7 | B11: 46027 | C11: 42048172 | D11: Luis Esteban Ramos Nicoll | E11: luisramosnicoll@gmail.com | F11: JM | H11: x | J11: 190 | L11: PAGO | M11: YAPE JL | N11: 190 | P11: Gabriela | Q11: =N11+O11 -> 190
A12: =A11+1 -> 8 | B12: 46027 | D12: Karen Sánchez vilcamiche | H12: x | J12: 50 | K12: 130 | L12: COBR | M12: YAPE JL | N12: 50 | O12: 130 | P12: Katherine | Q12: =N12+O12 -> 180
A13: =A12+1 -> 9 | B13: 46028 | D13: Luis Alberto Neyra Coveñas | H13: x | J13: 160 | L13: PAGO | M13: YAPE JL | N13: 160 | P13: Katherine | Q13: =N13+O13 -> 160
A14: =A13+1 -> 10 | Q14: =N14+O14 -> 0
A15: =A14+1 -> 11 | B15: 46029 | C15: 46819641 | D15: Andres Lucana | E15: Andres.lucanal@gmail.com | F15: CERCADO | G15: 942 808 819 | H15: X | J15: 190 | L15: PAGO | M15: YAPE JL | N15: 190 | P15: Yadhira | Q15: =N15+O15 -> 190
A16: =A15+1 -> 12 | B16: 46027 | C16: 46123466 | D16: Pilar coveñas Ramos | E16: naturaquimi@gmail.com | F16: SMP | G16: 965 713 303 | H16: X | J16: 225 | K16: 225 | L16: COBR | M16: YAPE JL | N16: 225 | O16: 225 | P16: Greici | Q16: =N16+O16 -> 450
A17: =A16+1 -> 13 | B17: 46026 | C17: 44836199 | D17: CINDY ARAUCANO | E17: elibenaraucano@gmail.com | F17: CARABAYLLO | G17: 904 312 283 | H17: X | J17: 50 | K17: 120 | L17: COBR | M17: YAPE JL | N17: 50 | O17: 120 | P17: Greici | Q17: =N17+O17 -> 170
A18: =A17+1 -> 14 | B18: 46029 | C18: 76240906 | D18: Kelly Jahuira Centeno | E18: Kelly.jahuiracenteno123@gmail.com | F18: Comas | G18: 950 523 640 | H18: x | J18: 166.66 | L18: PAGO | M18: YAPE JL | N18: 166.66 | P18: Gabriela | Q18: =N18+O18 -> 166.66
A19: =A18+1 -> 15 | B19: 46029 | C19: 71461985 | D19: Annie Jahuira Centeno | E19: Jahuiraannie123@gmail.com | F19: Comas | G19: 950 523 640 | H19: x | J19: 166.66 | L19: PAGO | M19: YAPE JL | N19: 166.66 | P19: Gabriela | Q19: =N19+O19 -> 166.66
A20: =A19+1 -> 16 | B20: 46029 | C20: 10183460 | D20: Dina Centeno Cruz | E20: Dinacenteno66@gmail.com | F20: Comas | G20: 950 523 640 | H20: x | J20: 166.66 | L20: PAGO | M20: YAPE JL | N20: 166.6 | P20: Gabriela | Q20: =N20+O20 -> 166.6
A21: =A20+1 -> 17 | B21: 46030 | D21: Victor Alfonso Garcia Castro | F21: La Victoria | H21: x | J21: 190 | L21: PAGO | M21: YAPE JL | N21: 190 | P21: Katherine | Q21: =N21+O21 -> 190
A22: =A21+1 -> 18 | B22: 46030 | C22: 7524514 | D22: Magaly Díaz | E22: Moyobamba051116@gmail.com | F22: La Victoria | G22: 991 031 685 | H22: x | J22: 95 | K22: 95 | L22: COBR | M22: YAPE JL | N22: 95 | O22: 95 | P22: Gabriela | Q22: =N22+O22 -> 190
A23: =A22+1 -> 19 | B23: 46027 | D23: Luis Alberto Marquina Arias | H23: x | J23: 0 | L23: PAGO | M23: YAPE JL | N23: 0 | Q23: =N23+O23 -> 0
A24: =A23+1 -> 20 | B24: 46027 | D24: María Luisa Díaz García | H24: x | J24: 0 | L24: PAGO | M24: YAPE JL | N24: 0 | Q24: =N24+O24 -> 0
A25: =A24+1 -> 21 | B25: 46030 | C25: 42945424 | D25: EDUARDO LARIOS SALAZAR | E25: Lariossalazar1926@gmail.com | F25: SJM | H25: X | J25: 85 | K25: 85 | L25: COBR | M25: YAPE JL | N25: 85 | O25: 85 | P25: Greici | Q25: =N25+O25 -> 170
A26: =A25+1 -> 22 | B26: 46031 | C26: 70919834 | D26: Carlos Eduardo Cumpa alayo | E26: Carloscumpa195@hotmail.com | H26: x | J26: 190 | L26: PAGO | M26: YAPE JL | N26: 190 | P26: Katherine | Q26: =N26+O26 -> 190
A27: =A26+1 -> 23 | B27: 46031 | C27: *005862518 | D27: Andres Felipe Jurado Aguilar | E27: afelipe.jurado@gmail.com | F27: Miraflores | G27: 949 706 975 | H27: x | J27: 190 | L27: PAGO | N27: 190 | P27: Gabriela | Q27: =N27+O27 -> 190
A28: =A27+1 -> 24 | B28: 46031 | C28: 25661264 | D28: Juana Alejandrina Pallaca Mallqui | F28: CALLAO | H28: X | J28: 190 | L28: PAGO | M28: YAPE JL | N28: 190 | P28: Yadhira | Q28: =N28+O28 -> 190
A29: =A28+1 -> 25 | B29: 46031 | D29: Oscar Vega | H29: x | J29: 150 | L29: PAGO | M29: EFECTIVO | N29: 150 | P29: Katherine | Q29: =N29+O29 -> 150
A30: =A29+1 -> 26 | Q30: =N30+O30 -> 0
A31: =A30+1 -> 27 | Q31: =N31+O31 -> 0
A32: X
A33: X
A34: X
A35: X
A36: 1 | B36: 46008 | C36: 44681923 | D36: Rodrigo Bustamante Moquillaza | E36: Roodj88@gmail.com | F36: SURQUILLO | G36: 995 586 556 | I36: X | J36: 0 | N36: 0 | P36: Yadhira | Q36: =N36+O36 -> 0 | R36: PAGRA EN SU TALLER AFI 11/01
A37: =A36+1 -> 2 | B37: 46008 | D37: Philip Wenter Bustamante | E37: Roodj88@gmail.com | F37: SURQUILLO | G37: 995 586 556 | I37: X | J37: 0 | N37: 0 | P37: Yadhira | Q37: =N37+O37 -> 0 | R37: PAGRA EN SU TALLER AFI 11/01
A38: =A37+1 -> 3 | B38: 46032 | D38: Janeth mayhuasca lapa | I38: X | J38: 95 | K38: 95 | L38: COBR | M38: YAPE JL | N38: 95 | O38: 95 | P38: Katherine | Q38: =N38+O38 -> 190
A39: =A38+1 -> 4 | B39: 46028 | C39: 09683891 | D39: Julio la cerna Roncal | E39: Galvimetall@yahoo.es | F39: CERCADO | G39: 982 569 272 | I39: x | J39: 100 | K39: 90 | L39: COBR | M39: YAPE JL | N39: 100 | O39: 0 | P39: Yadhira | Q39: =N39+O39 -> 100
A40: =A39+1 -> 5 | B40: 46035 | C40: 20029573 | D40: Williams Fredy Sanabria Reyes | E40: wsananria073@gmail.com | F40: JUNIN | G40: 944 542 158 | I40: X | J40: 95 | K40: 95 | L40: COBR | M40: YAPE JL | N40: 95 | O40: 95 | P40: Yadhira | Q40: =N40+O40 -> 190
A41: =A40+1 -> 6 | B41: 46035 | C41: 49035262 | D41: Rafael Antony Urbina Peña | E41: Rafaelurbi18@gmail.com | F41: LOS OLIVOS | G41: 927 235 029 | I41: X | J41: 190 | L41: PAGO | M41: YAPE JL | N41: 190 | P41: Yadhira | Q41: =N41+O41 -> 190
A42: =A41+1 -> 7 | B42: 46036 | C42: 22314008 | D42: Elias Campos Sanchez. | I42: x | J42: 0 | N42: 0 | P42: Katherine | Q42: =N42+O42 -> 0
A43: =A42+1 -> 8 | B43: 46036 | C43: 76601657 | D43: Anthony Giancarlos rios agesto | E43: gian.agesto.tkm@gmail.com | F43: Huacho | I43: x | J43: 150 | L43: PAGO | N43: 150 | P43: Gabriela | Q43: =N43+O43 -> 150
A44: =A43+1 -> 9 | B44: 46037 | C44: 10477399 | D44: Francisco José Mesía Liau | I44: x | J44: 95 | K44: 95 | L44: COBR | M44: YAPE JL | N44: 95 | O44: 95 | P44: Katherine | Q44: =N44+O44 -> 190
A45: =A44+1 -> 10 | B45: 46037 | C45: 41271985 | D45: Lesly chumbiriza chacon | E45: leslyrosachumbirizachacon@gmail.com | F45: SJL | G45: 917 313 781 | I45: X | J45: 50 | K45: 140 | L45: COBR | M45: YAPE JL | N45: 50 | O45: 140 | P45: Yadhira | Q45: =N45+O45 -> 190
A46: =A45+1 -> 11 | B46: 46037 | C46: 41590522 | D46: Joao Solís Talaverano | E46: Spawn.st41@gmail.com | F46: AYACUCHO | G46: 932 006 620 | I46: X | J46: 0 | N46: 0 | P46: Greici | Q46: =N46+O46 -> 0 | R46: PAGARÁ EN CLASE DEL 17/01
A47: =A46+1 -> 12 | B47: 46037 | C47: 42689847 | D47: Cisneros Montes de Oca | E47: sergio14_14@hotmail.com | F47: AYACUCHO | I47: X | J47: 0 | N47: 0 | P47: Greici | Q47: =N47+O47 -> 0
A48: =A47+1 -> 13 | B48: 46037 | C48: 46314782 | D48: brenda lahura vento | I48: x | J48: 190 | L48: PAGO | M48: MERC-PAG | N48: 174.28 | P48: Katherine | Q48: =N48+O48 -> 174.28
A49: =A48+1 -> 14 | B49: 46372 | C49: 751447752 | D49: Darlen Estupiñan Euscate | E49: dar.val13@hotmail.com | F49: HUAURA | I49: X | J49: 185 | L49: PAGO | M49: YAPE JL | N49: 185 | P49: Yadhira | Q49: =N49+O49 -> 185
A50: =A49+1 -> 15 | B50: 46038 | C50: 07336007 | D50: Luis Checa Alayza | E50: comcheca@gmail.com | F50: LA VICTORIA | G50: 998 366 203 | I50: X | J50: 190 | L50: PAGO | M50: BBVA JL | N50: 190 | P50: Yadhira | Q50: =N50+O50 -> 190
A51: =A50+1 -> 16 | B51: 46038 | C51: 76799413 | D51: Gerson Alejandro Nogueyra Saldarriaga | E51: ng.producciones.art@gmail.com | F51: CALLAO | G51: 923 677 984 | I51: X | J51: 100 | K51: 350 | L51: COBR | M51: YAPE JL | N51: 100 | O51: 350 | P51: Yadhira | Q51: =N51+O51 -> 450
A52: =A51+1 -> 17 | B52: 46038 | C52: 40369991 | D52: Félix Uriarte Barranazuela | I52: x | J52: 100 | K52: 90 | L52: COBR | M52: YAPE JL | N52: 100 | O52: 90 | P52: Katherine | Q52: =N52+O52 -> 190
A53: =A52+1 -> 18 | B53: 46039 | C53: 74551908 | D53: Linda Aponte Huaman | E53: Leydi359aponte@gmail.com | F53: HUACHO | I53: X | J53: 180 | L53: PAGO | M53: YAPE JL | N53: 180 | P53: Yadhira | Q53: =N53+O53 -> 180
A54: =A53+1 -> 19 | B54: 46039 | C54: 41831539 | D54: Deysi Quezada Trujillo | E54: Luimertaboada@gmail.com | F54: San Juan de Miraflores | G54: 933 357 463 | I54: X | J54: 190 | L54: PAGO | M54: YAPE JL | N54: 190 | P54: Tania | Q54: =N54+O54 -> 190
A55: =A54+1 -> 20 | Q55: =N55+O55 -> 0
A56: =A55+1 -> 21 | Q56: =N56+O56 -> 0
A57: =A56+1 -> 22 | Q57: =N57+O57 -> 0
A58: =A57+1 -> 23 | Q58: =N58+O58 -> 0
A59: =A58+1 -> 24 | Q59: =N59+O59 -> 0
A60: =A59+1 -> 25 | Q60: =N60+O60 -> 0
A61: =A60+1 -> 26 | Q61: =N61+O61 -> 0
A62: =A61+1 -> 27 | Q62: =N62+O62 -> 0
A63: X | Q63: =N63+O63 -> 0
A64: X | Q64: =N64+O64 -> 0
A65: X | Q65: =N65+O65 -> 0
A66: X | Q66: =N66+O66 -> 0
G67: Total Registrados | H67: =COUNTIF(H4:H66,"X") -> 24 | I67: =COUNTIF(I4:I66,"X") -> 19 | J67: =SUM(J4:J66) -> 5184.98 | K67: =SUM(K4:K66) -> 1870 | N67: =SUM(N4:N66) -> 5169.2 | O67: =SUM(O4:O66) -> 1780
G68: Total Cupos | H68: 27 | I68: 27 | J68: =SUM(J67:K67) -> 7054.98 | N68: =SUM(N67:O67) -> 6949.2
G69: Cupos Libres | H69: =H68-H67 -> 3 | I69: =I68-I67 -> 8 | J69: Total Venta Fecha | N69: Venta Final Fecha
H70: 150 | I70: 150 | T70: -
H71: =H69*H70 -> 450 | I71: =I69*I70 -> 1200
H72: =SUM(H71:I71) -> 1650

Sheet GN-Completo
A2: CONTROL DE REGISTRO PARTICIPANTES
A3: GESTION DE NEGOCIOS | G3: GN
A4: ID | B4: FE_ REGISTRO | C4: DNI | D4: NOMBRES Y APELLIDOS | E4: EMAIL | F4: DISTRITO | G4: WSP | H4: 46028 | I4: 46042 | J4: MONTO | K4: xCOBRAR | L4: ESTADO | M4: CUENTA | N4: INGRESO | O4: SALDO | P4: VENDEDOR | Q4: TOTAL | R4: OBSERVACION
A5: 1 | B5: 46001 | C5: 72685604 | D5: Roberto Gabriel Flores Butron | E5: floresrgb97@gmail.com | F5: Yanahuara-Arequipa | G5: 950 536 721 | H5: x | J5: 0 | Q5: =N5+O5 -> 0 | R5: Regalo GB
A6: =A5+1 -> 2 | B6: 46002 | C6: 46749055 | D6: Eber huayhua vargas | E6: Huayhuavargase@gmail.com | F6: Chorrillos | G6: 902 779 238 | H6: x | J6: 0 | Q6: =N6+O6 -> 0 | R6: Regalo GB
A7: =A6+1 -> 3 | B7: 46009 | C7: 1240711 | D7: Andrés Sebastian Ordenes Lobatón | E7: andresordeneslo@gmail.com | F7: San isidro | G7: 999 508 901 | H7: x | J7: 0 | Q7: =N7+O7 -> 0 | R7: Regalo GB
A8: =A7+1 -> 4 | B8: 46016 | C8: 71412900 | D8: Jordan Aaron Suarez Acuña | E8: sjordanaaron@gmail.com | F8: Comas | G8: 972453322 | H8: x | J8: 0 | Q8: =N8+O8 -> 0 | R8: Regalo GB
A9: =A8+1 -> 5 | B9: 46017 | C9: 73851205 | D9: Miguel Angel Peña Mata | E9: penamata90@gmail.com | F9: SURQUILLO | G9: 946856472 | H9: x | J9: 0 | Q9: =N9+O9 -> 0 | R9: Regalo GB
A10: =A9+1 -> 6 | B10: 46018 | C10: 7454502 | D10: Carlos Díaz Ocaña | E10: cd1030741@gmail.com | F10: San Borja | G10: 995951313 | H10: x | J10: 0 | Q10: =N10+O10 -> 0 | R10: Regalo GB
A11: =A10+1 -> 7 | B11: 46018 | C11: 20609390264 | D11: Lucia Jessica Chávez Ramírez | E11: Elchicharrondechavez@gmail.com | F11: Los Olivos | G11: 957 435 806 | H11: x | J11: 0 | Q11: =N11+O11 -> 0 | R11: Regalo GB
A12: =A11+1 -> 8 | B12: 46020 | C12: 60393570 | D12: Maycol Jonathan paz Retamozo | E12: Pazm20481@gmail.com | F12: SJL | G12: 901 686 803 | H12: x | J12: 0 | Q12: =N12+O12 -> 0 | R12: Regalo GB
A13: =A12+1 -> 9 | B13: 46020 | C13: 43712509 | D13: Brian portilla orquiz | E13: brianportilla.bp@gmail.com | F13: Comas | G13: 954 423 850 | H13: x | J13: 0 | Q13: =N13+O13 -> 0 | R13: Regalo GB
A14: =A13+1 -> 10 | B14: 46022 | C14: 71176371 | D14: César Miguel Oré Astorga | E14: orec.1602@gmail.com | F14: Cercado de Lima | G14: 932 401 077 | H14: x | J14: 0 | N14: 0 | Q14: =N14+O14 -> 0 | R14: Regalo GB
A15: =A14+1 -> 11 | B15: 46019 | C15: 47729335 | D15: Jorge luis padilla zapata | E15: j.l.padilla_93@hotmail.com | F15: Huaral | G15: 916 155 109 | H15: x | J15: 0 | N15: 0 | Q15: =N15+O15 -> 0 | R15: Regalo GB
A16: =A15+1 -> 12 | B16: 46013 | C16: 47162261 | D16: Abraham Basilio Rojas | E16: Abr.2012@gmail.com | F16: San miguel | G16: 997 630 428 | H16: x | J16: 0 | N16: 0 | Q16: =N16+O16 -> 0 | R16: Regalo GB
A17: =A16+1 -> 13 | B17: 7716111 | C17: 42588957 | D17: Ricardo Junior Boza Valdiviezo | F17: Comas | G17: 963 037 833 | H17: x | J17: 0 | N17: 0 | Q17: =N17+O17 -> 0 | R17: Regalo GB
A18: =A17+1 -> 14 | B18: 46023 | C18: 75014725 | D18: Piero André Damas Salhuana | E18: piero27022000@gmail.com | F18: Carabayllo | G18: 927 991 306 | H18: x | J18: 0 | N18: 0 | Q18: =N18+O18 -> 0 | R18: Regalo GB
A19: =A18+1 -> 15 | B19: 46024 | C19: *09837904 | D19: María Bertha Chavarría rios | E19: mariachavarria079@gmail.com | F19: Chosica | G19: 962 916 978 | H19: x | J19: 0 | N19: 0 | Q19: =N19+O19 -> 0 | R19: Regalo GB
A20: =A19+1 -> 16 | B20: 46024 | C20: 41364774 | D20: Magda Rosa Aguilar Vigo | E20: Magdaaguilar4@gmail.com | F20: San Isidro | G20: 983630248 | H20: x | J20: 0 | N20: 0 | Q20: =N20+O20 -> 0 | R20: Regalo GB
A21: =A20+1 -> 17 | B21: 46024 | C21: 73487354 | D21: Yessire Meneses Bellido | E21: yess.menesesbellido@gmail.com | F21: Ate Salamanca | G21: 918 819 213 | H21: x | J21: S/.180.00 | L21: PAGO | M21: PLIN JL | N21: 180 | P21: Tania | Q21: =N21+O21 -> 180
A22: =A21+1 -> 18 | B22: 46026 | C22: 42048172 | D22: Luis Esteban Ramos Nicoll | E22: luisramosnicoll@gmail.com | F22: Jesús María | G22: 990 040 484 | H22: x | J22: 0 | N22: 0 | Q22: =N22+O22 -> 0 | R22: Regalo GB
A23: =A22+1 -> 19 | B23: 46027 | C23: *09902780 | D23: Miguel Angel Gutti Huaman | E23: miguelgutti74@gmail.com | F23: SMP | G23: 977 198 257 | H23: x | J23: 0 | N23: 0 | Q23: =N23+O23 -> 0 | R23: Regalo GB
A24: =A23+1 -> 20 | B24: 46027 | C24: ´005508766 | D24: Pablo Fernandez | E24: Thepointcellima@gmail.com | F24: Los olivos | G24: 997 936 197 | H24: x | J24: S/.180.00 | L24: PAGO | M24: PLIN JL | N24: 100 | P24: Tania | Q24: =N24+O24 -> 100
A25: =A24+1 -> 21 | B25: 46030 | C25: ´02438088 | D25: Robert Montilla | E25: robertmontilla02@gmail.com | F25: Ate | G25: 945 928 161 | J25: S/.180.00 | L25: PAGO | M25: YAPE JL | N25: 180 | P25: Tania | Q25: =N25+O25 -> 180
A26: =A25+1 -> 22 | B26: 46030 | C26: 77087419 | D26: Jessica Escarlen | E26: Escarlen.mrkdigital@gmail.com | G26: 955 805 382 | I26: x | Q26: =N26+O26 -> 0
A27: =A26+1 -> 23 | B27: 46030 | C27: 76785683 | D27: Anderson Denis López López | E27: fcanlelnubf@gmail.com | F27: Callao | G27: 942 580 187 | I27: x | J27: 0 | L27: PAGO | N27: 0 | Q27: =N27+O27 -> 0 | R27: Regalo GB
A28: =A27+1 -> 24 | B28: 46032 | C28: 26728586 | D28: Luis Ivan Novoa Espinoza | E28: ivannovoa@gmail.com | F28: La Molina | G28: 986 191 035 | I28: x | J28: S/.160.00 | L28: PAGO | M28: PLIN JL | N28: 160 | P28: Tania | Q28: =N28+O28 -> 160
A29: =A28+1 -> 25 | B29: 46032 | C29: 71131738 | D29: Aldair fuentes castro | E29: aldair321703@gmail.com | F29: Pachacamac | G29: 991 957 123 | I29: x | J29: S/.180.00 | L29: PAGO | N29: 180 | P29: Tania | Q29: =N29+O29 -> 180
A30: =A29+1 -> 26 | B30: 46034 | C30: 10741489142 | D30: James Enrique Ccaira Quispe | E30: jams.enri@hotmail.com | F30: AREQUIPA | G30: 982 702 847 | I30: x | J30: 180 | L30: PAGO | M30: YAPE JL | N30: 180 | P30: Greici | Q30: =N30+O30 -> 180
A31: =A30+1 -> 27 | B31: 46035 | C31: 10719169 | D31: Jorge Luis cabrera Montenegro | E31: ventas@espacioalexandra.com | F31: San miguel | G31: 990494288 | I31: x | J31: 0 | L31: PAGO | N31: 0 | Q31: =N31+O31 -> 0
A32: X | B32: 46035 | C32: 70919834 | D32: Carlos Eduardo Cumpa alayo | E32: carlossmithh21@gmail.com | F32: San Juan de Lurigancho | G32: 956 899 742 | I32: x | J32: 180 | L32: PAGO | M32: BCP JL | N32: 180 | P32: Tania | Q32: =N32+O32 -> 180
A33: X | D33: Ricardo Boza | E33: Richiebzv@gmail.com | G33: 963 037 833 | H33: x | J33: 0 | M33: 0 | N33: 0 | Q33: =N33+O33 -> 0 | R33: GB
A34: X | B34: 46040 | C34: 71474780 | D34: Martha lucia Gutiérrez Pacheco | E34: marthaluciagutierrezpacheco@gmail.com | F34: Nasca Ica | G34: 922 607 372 | I34: x | J34: 180 | L34: PAGO | M34: YAPE JL | N34: 180 | P34: Tania | Q34: =N34+O34 -> 180
A35: X | B35: 46042 | C35: 42944658 | D35: Osmar Rosas Tomas | E35: rosastomasosmar@gmail.com | F35: Trujillo | G35: 921 548 092 | I35: x | J35: 180 | L35: PAGO | M35: YAPE JL | N35: 180 | P35: Tania | Q35: =N35+O35 -> 180
A36: 1 | B36: 46042 | C36: 41229116 | D36: Edver luna goñi | E36: Lunaedver@gmail.com | F36: Carabayllo | G36: 936 928 510 | I36: x | J36: 180 | L36: PAGO | M36: YAPE JL | N36: 180 | P36: Tania | Q36: =N36+O36 -> 180
A37: =A36+1 -> 2 | Q37: =N37+O37 -> 0
A38: =A37+1 -> 3 | B38: 46035 | C38: 72505663 | D38: Luna Alejandra Peláez Egoavil | E38: lunapelaez.25.11@gmail.com | F38: SMP | I38: x | J38: 180 | L38: PAGO | M38: YAPE JL | N38: 180 | P38: Gabriela | Q38: =N38+O38 -> 180
A39: =A38+1 -> 4 | Q39: =N39+O39 -> 0
A40: =A39+1 -> 5 | D40: Walter Seyfarth | E40: walterseyfarthbsn@gmail.com | G40: 962 372 707 | I40: x | J40: 0 | N40: 0 | Q40: =N40+O40 -> 0 | R40: GB
A41: =A40+1 -> 6 | Q41: =N41+O41 -> 0
A42: =A41+1 -> 7 | Q42: =N42+O42 -> 0
A43: =A42+1 -> 8 | Q43: =N43+O43 -> 0
A44: =A43+1 -> 9 | Q44: =N44+O44 -> 0
A45: =A44+1 -> 10 | Q45: =N45+O45 -> 0
A46: =A45+1 -> 11 | Q46: =N46+O46 -> 0
A47: =A46+1 -> 12 | Q47: =N47+O47 -> 0
A48: =A47+1 -> 13 | Q48: =N48+O48 -> 0
A49: =A48+1 -> 14 | Q49: =N49+O49 -> 0
A50: =A49+1 -> 15 | Q50: =N50+O50 -> 0
A51: =A50+1 -> 16 | Q51: =N51+O51 -> 0
A52: =A51+1 -> 17 | Q52: =N52+O52 -> 0
... A61: =A60+1 -> 26 | Q61: =N61+O61 -> 0
A62: =A61+1 -> 27 | Q62: =N62+O62 -> 0 | R62: OBSERVACION
A63: X | Q63: =N63+O63 -> 0
A64: X | Q64: =N64+O64 -> 0
A65: X | Q65: =N65+O65 -> 0
A66: X | Q66: =N66+O66 -> 0
G67: Total Registrados | H67: =COUNTIF(H4:H66,"X") -> 21 | I67: =COUNTIF(I4:I66,"X") -> 12 | J67: =SUM(J4:J66) -> 1080 | K67: =SUM(K4:K66) -> 0 | N67: =SUM(N4:N66) -> 1880 | O67: =SUM(O4:O66) -> 0
G68: Total Cupos | H68: 27 | I68: 27 | J68: =SUM(J67:K67) -> 1080 | N68: =SUM(N67:O67) -> 1880
G69: Cupos Libres | H69: =H68-H67 -> 6 | I69: =I68-I67 -> 15 | J69: Total Venta Fecha | N69: Venta Final Fecha
H70: 150 | I70: 150 | T70: -
H71: =H69*H70 -> 900 | I71: =I69*I70 -> 2250
H72: =SUM(H71:I71) -> 3150

Sheet Corporativo
A2: CONTROL DE REGISTRO PARTICIPANTES
A3: CORPORATIVO | G3: CORPORATIVO
A4: ID | B4: FE_ REGISTRO | C4: RUC | D4: EMPRESA | E4: EMAIL | F4: DISTRITO | G4: WSP | J4: MONTO | K4: xCOBRAR | L4: ESTADO | M4: CUENTA | N4: INGRESO | O4: SALDO | P4: VENDEDOR | Q4: TOTAL | R4: OBSERVACION
A5: 1 | B5: 46045 | C5: Catering | D5: Jorge | F5: San isidro | H5: x | J5: 1700 | K5: 720 | L5: COBR | M5: BCP EPP | N5: 1700 | O5: 720 | P5: Katherine | Q5: =N5+O5 -> 2420
A6: =A5+1 -> 2 | B6: 46044 | C6: Catering | D6: BRENDA FARAON | F6: SURCO | H6: X | J6: 1724 | L6: PAGO | N6: 1724 | P6: FH | Q6: =N6+O6 -> 1724
A7: =A6+1 -> 3 | D7: JULIO GELDRES | H7: X | J7: 500 | N7: 500 | P7: FH | Q7: =N7+O7 -> 500
A8: =A7+1 -> 4 | Q8: =N8+O8 -> 0
A9: =A8+1 -> 5 | Q9: =N9+O9 -> 0
A10: =A9+1 -> 6 | Q10: =N10+O10 -> 0
A11: =A10+1 -> 7 | Q11: =N11+O11 -> 0
A12: =A11+1 -> 8 | Q12: =N12+O12 -> 0
A13: =A12+1 -> 9 | Q13: =N13+O13 -> 0
A14: =A13+1 -> 10 | Q14: =N14+O14 -> 0
G15: Total Registrados | H15: =COUNTIF(H4:H14,"X") -> 3 | I15: =COUNTIF(I4:I14,"X") -> 0 | J15: =SUM(J4:J14) -> 3924 | K15: =SUM(K4:K14) -> 720 | N15: =SUM(N4:N14) -> 3924 | O15: =SUM(O4:O14) -> 720
G16: Total Cupos | H16: 28 | I16: 28 | J16: =SUM(J15:K15) -> 4644 | N16: =SUM(N15:O15) -> 4644
G17: Cupos Libres | H17: =H16-H15 -> 25 | I17: =I16-I15 -> 28 | J17: Total Venta Fecha | N17: Venta Final Fecha
H18: 140 | I18: 140 | T18: -
H19: =H17*H18 -> 3500 | I19: =I17*I18 -> 3920
H20: =H19+I19 -> 7420

Sheet GB1
A2: CONTROL DE REGISTRO PARTICIPANTES
A3: GASTRONOMIA EN BRASAS | G3: GB
A4: ID | B4: FE_ REGISTRO | C4: DNI | D4: NOMBRES Y APELLIDOS | E4: EMAIL | F4: DISTRITO | G4: WSP | H4: GB-21 | I4: GB - 22 | J4: MONTO | K4: xCOBRAR | L4: ESTADO | M4: CUENTA | N4: INGRESO | P4: SALDO | Q4: VENDEDOR | R4: TOTAL | S4: OBSERVACION
A5: 1 | B5: 45991 | C5: 41318618 | D5: Wilder francisco hurtado torres | E5: Willyht072@gmail.com | F5: Bellavista | G5: 980 199 023 | H5: x | J5: =300+1100 -> 1400 | L5: PAGO | M5: YAPE JL | N5: 300 | O5: 1100 | Q5: Gabriela | R5: =N5+O5 -> 1400
A6: =A5+1 -> 2 | B6: 45960 | D6: Geoffrey Mogollon | G6: 920 385 441 | I6: x | J6: 100 | L6: PAGO | N6: 100 | Q6: Gabriela | R6: =N6+O6 -> 100 | S6: GB16 pago total - reprogramacion
A7: =A6+1 -> 3 | B7: 45994 | C7: 10257770 | D7: Ynalia Noemí Quispe Valdivia | E7: ynalianoemi@gmail.com | F7: Ate | G7: 982 215 485 | I7: x | J7: =300+1100 -> 1400 | L7: PAGO | N7: 300 | O7: 1100 | Q7: Gabriela | R7: =N7+O7 -> 1400
A8: =A7+1 -> 4 | B8: 46000 | C8: 44028083 | D8: Isolina Ruiz roman | E8: isolinachef@gmail.com | F8: SMP | G8: 987 868 627 | H8: x | J8: =100+200+1000 -> 1300 | L8: PAGO | N8: 300 | O8: 1000 | Q8: Gabriela | R8: =N8+O8 -> 1300
A9: =A8+1 -> 5 | B9: 46001 | C9: 72685604 | D9: Roberto Gabriel Flores Butron | E9: floresrgb97@gmail.com | F9: Yanahuara-Arequipa | G9: 950 536 721 | H9: x | J9: =300+1140+60 -> 1500 | L9: PAGO | N9: 300 | O9: 1200 | Q9: Gabriela | R9: =N9+O9 -> 1500
A10: =A9+1 -> 6 | B10: 46002 | C10: 46749055 | D10: Eber huayhua vargas | E10: Huayhuavargase@gmail.com | F10: Chorrillos | G10: 902 779 238 | H10: x | J10: =100+1400 -> 1500 | L10: PAGO | N10: 100 | O10: 1400 | Q10: Gabriela | R10: =N10+O10 -> 1500
A11: =A10+1 -> 7 | B11: 41260 | C11: 75240792 | D11: Victor Mario Zapata Vilchez | E11: qjazminmilagros@gmail.com | F11: Cieneguilla | G11: 991 548 337 | I11: x | J11: =300+500+500 -> 1300 | L11: PAGO | N11: =300+500 -> 800 | O11: 500 | Q11: Gabriela | R11: =N11+O11 -> 1300
A12: =A11+1 -> 8 | B12: 46009 | C12: 1240711 | D12: Andrés Sebastian Ordenes Lobatón | E12: andresordeneslo@gmail.com | F12: San isidro | G12: 999 508 901 | I12: x | J12: =300+1200 -> 1500 | L12: PAGO | N12: 300 | O12: 1200 | Q12: Gabriela | R12: =N12+O12 -> 1500
A13: =A12+1 -> 9 | B13: 46011 | C13: 72543662 | D13: Rodrigo Romero León | E13: christian_romleo@hotmail.com | F13: SJL | G13: 991177495 | H13: x | J13: =200+1100 -> 1300 | L13: PAGO | N13: 200 | O13: 1100 | Q13: Gabriela | R13: =N13+O13 -> 1300
A14: =A13+1 -> 10 | B14: 46016 | C14: 71412900 | D14: Jordan Aaron Suarez Acuña | E14: sjordanaaron@gmail.com | F14: Comas | G14: 972453322 | H14: x | J14: =200+1300 -> 1500 | L14: PAGO | M14: YAPE JL | N14: 200 | O14: 1300 | Q14: Gabriela | R14: =N14+O14 -> 1500
A15: =A14+1 -> 11 | B15: 44540 | C15: 46847985 | D15: Nilber Eduardo portocarrero López | E15: e.portocarrero_10@hotmail.com | F15: Callao | I15: x | J15: 300 | K15: 500 | L15: COBR | M15: YAPE JL | N15: 300 | Q15: Katherine | R15: =N15+O15 -> 300 | S15: CUOTAS
A16: =A15+1 -> 12 | B16: 46013 | C16: 44048290 | D16: Ronald Rene cuya lozano | E16: ronaldcuya61@gmail.com | G16: 957 347 807 | H16: x | J16: 1400 | L16: PAGO | M16: YAPE JL | N16: 1400 | Q16: Katherine | R16: =N16+O16 -> 1400
A17: =A16+1 -> 13 | G17: 966 205 316 | L17: PAGO | M17: YAPE JL | N17: 0 | Q17: Katherine | R17: =N17+O17 -> 0
A18: =A17+1 -> 14 | B18: 46017 | C18: 73851205 | D18: Miguel Angel Peña Mata | E18: penamata90@gmail.com | F18: SURQUILLO | G18: 946856472 | I18: X | J18: =300+1200 -> 1500 | L18: PAGO | M18: BCP JL | N18: 300 | O18: 1200 | Q18: Gabriela | R18: =N18+O18 -> 1500
A19: =A18+1 -> 15 | B19: 46018 | C19: 7454502 | D19: Carlos Díaz Ocaña | F19: San Borja | G19: 995951313 | I19: x | J19: =300+1200 -> 1500 | L19: PAGO | M19: PLIN JL | N19: 300 | O19: 1200 | Q19: Gabriela | R19: =N19+O19 -> 1500
A20: =A19+1 -> 16 | B20: 46018 | C20: 20609390264 | D20: Lucia Jessica Chávez Ramírez | E20: Elchicharrondechavez@gmail.com | F20: Los Olivos | G20: 957 435 806 | H20: x | J20: =300+1200 -> 1500 | L20: PAGO | M20: PLIN JL | N20: 300 | O20: 1200 | Q20: Gabriela | R20: =N20+O20 -> 1500
A21: =A20+1 -> 17 | B21: 46019 | C21: 47729335 | D21: Jorge luis padilla zapata | E21: j.l.padilla_93@hotmail.com | F21: Huaral | G21: 916 155 109 | I21: x | J21: 1400 | L21: PAGO | M21: BCP JL | N21: 1400 | Q21: Gabriela | R21: =N21+O21 -> 1400
A22: =A21+1 -> 18 | B22: 46020 | C22: 48371859 | D22: Miguel Angel Martinez Galvez | E22: mg.martinezgalvez@gmail.com | F22: Lince | G22: 922 518 814 | H22: x | J22: =300+1000 -> 1300 | L22: PAGO | M22: PLIN JL | N22: 300 | O22: 1000 | Q22: Gabriela | R22: =N22+O22 -> 1300
A23: =A22+1 -> 19 | B23: 46020 | C23: 60393570 | D23: Maycol Jonathan paz Retamozo | E23: Pazm20481gmail.com | F23: SJL | G23: 901 686 803 | H23: x | J23: =200+1300 -> 1500 | L23: PAGO | M23: PLIN JL | N23: 200 | O23: 1300 | Q23: Gabriela | R23: =N23+O23 -> 1500
A24: =A23+1 -> 20 | B24: 46020 | C24: 43712509 | D24: Brian portilla orquiz | E24: brianportilla.bp@gmail.com | F24: Comas | G24: 954 423 850 | H24: x | J24: 1500 | L24: PAGO | M24: BCP JL | N24: 1500 | Q24: Gabriela | R24: =N24+P24 -> 1500
A25: =A24+1 -> 21 | B25: 46022 | C25: 71176371 | D25: César Miguel Oré Astorga | E25: orec.1602@gmail.com | F25: Cercado de Lima | G25: 932 401 077 | H25: x | J25: =300+1200 -> 1500 | L25: PAGO | M25: BCP JL | N25: 300 | O25: 1200 | Q25: Gabriela | R25: =N25+O25 -> 1500
A26: =A25+1 -> 22 | B26: 46023 | C26: 75014725 | D26: Piero André Damas Salhuana | E26: piero27022000@gmail.com | F26: Carabayllo | G26: 927 991 306 | H26: x | J26: 1500 | L26: PAGO | M26: BCP JL | N26: 1500 | Q26: Gabriela | R26: =N26+P26 -> 1500
A27: =A26+1 -> 23 | B27: 46024 | C27: *09837904 | D27: María Bertha Chavarría rios | E27: mariachavarria079@gmail.com | F27: Chosica | G27: 962 916 978 | H27: x | J27: =200+1300 -> 1500 | L27: PAGO | M27: YAPE JL | N27: 200 | O27: 1300 | Q27: Gabriela | R27: =N27+O27 -> 1500
A28: =A27+1 -> 24 | B28: 45659 | C28: 41364774 | D28: Magda Rosa Aguilar Vigo | E28: Magdaaguilar4@gmail.com | F28: San Isidro | I28: x | J28: =250+1250 -> 1500 | L28: PAGO | M28: PLIN JL | N28: 250 | O28: 1250 | Q28: Gabriela | R28: =N28+O28 -> 1500
A29: =A28+1 -> 25 | B29: 46026 | C29: 42048172 | D29: Luis Esteban Ramos Nicoll | E29: luisramosnicoll@gmail.com | F29: Jesús María | I29: x | J29: =200+1200 -> 1400 | L29: PAGO | M29: YAPE JL | N29: 200 | O29: 1200 | Q29: Gabriela | R29: =N29+O27 -> 1500
A30: =A29+1 -> 26 | B30: 46027 | C30: *09902780 | D30: Miguel Angel Gutti Huaman | E30: miguelgutti74@gmail.com | F30: SMP | I30: x | J30: =300+1200 -> 1500 | L30: PAGO | M30: YAPE JL | N30: 300 | O30: 1200 | Q30: Gabriela | R30: =N30+O30 -> 1500
A31: =A30+1 -> 27 | B31: 46027 | C31: 47415409 | D31: Julio cesar Nalbarte villar | E31: Dieguito.2203.jnv@gmail.com | H31: x | J31: 250 | K31: 500 | L31: COBR | M31: BCP JL | N31: 250 | Q31: Katherine | R31: =N31+P31 -> 250 | S31: CUOTAS
A32: =A31+1 -> 28 | B32: 46029 | C32: 21000873 | D32: Demetrio Ramos Mancilla | E32: joshua_rexar@hotmail.com | F32: Chorrillos | G32: 954 270 991 | I32: x | J32: 1300 | L32: PAGO | M32: BCP JL | N32: 1300 | Q32: Gabriela | R32: =N32+P32 -> 1300
A33: =A32+1 -> 29 | B33: 46031 | C33: 44975220 | D33: Oscar Vega Orue | E33: oscar85.vo@gmail.com | F33: Rimac | G33: 938 515 034 | I33: x | J33: =300+1000 -> 1300 | L33: PAGO | M33: YAPE JL | N33: 300 | O33: 1000 | Q33: Gabriela | R33: =N33+O33 -> 1300
A34: =A33+1 -> 30 | B34: 46032 | C34: 61176942 | D34: Rodrigo Sebastian Salazar Palacios | F34: SJL | G34: 934205812 | I34: x | J34: =300+1000 -> 1300 | L34: PAGO | M34: BCP JL | N34: 300 | O34: 1000 | Q34: Gabriela | R34: =N34+O34 -> 1300
G35: Total Registrados | H35: =COUNTIF(H4:H34,"X") -> 15 | I35: =COUNTIF(I4:I34,"X") -> 14 | J35: =SUM(J4:J34) -> 37750 | K35: =SUM(K4:K34) -> 1000 | N35: =SUM(N4:N34) -> 13800 | P35: =SUM(P4:P34) -> 0
G36: Total Cupos | H36: 27 | I36: 27 | J36: =SUM(J35:K35) -> 38750 | N36: =SUM(N35:P35) -> 13800
G37: Cupos Libres | H37: =H36-H35 -> 12 | I37: =I36-I35 -> 13 | J37: Total Venta Fecha | N37: Venta Final Fecha
H38: 150 | I38: 150 | U38: -
H39: =H37*H38 -> 1800 | I39: =I37*I38 -> 1950
H40: =SUM(H39:I39) -> 3750

Sheet GB2
A2: CONTROL DE REGISTRO PARTICIPANTES
A3: GASTRONOMIA EN BRASAS | G3: GB
A4: ID | B4: FE_ REGISTRO | C4: DNI | D4: NOMBRES Y APELLIDOS | E4: EMAIL | F4: DISTRITO | G4: WSP | H4: GB 23 | I4: GB 24 | J4: MONTO | K4: xCOBRAR | L4: ESTADO | M4: CUENTA | N4: INGRESO | O4: SALDO | P4: VENDEDOR | Q4: TOTAL | R4: OBSERVACION
A5: 1 | B5: 46011 | C5: 44579272 | D5: Ruedi Mazuelos | E5: bs1@jeanmazuelos.com | F5: San Luis | G5: 921899103 | I5: x | J5: =200+1200 -> 1400 | L5: PAGO | M5: YAPE JL | N5: =200+1200 -> 1400 | P5: Gabriela | Q5: =N5+O5 -> 1400
A6: =A5+1 -> 2 | B6: 46011 | C6: 18149957 | D6: Richard Carlo Rodriguez Balcazar | E6: rcrbalcazar@hotmail.com | F6: Surco | G6: 997953249 | I6: x | J6: =200+1200 -> 1400 | L6: PAGO | M6: YAPE JL | N6: =200+1200 -> 1400 | P6: Gabriela | Q6: =N6+O6 -> 1400
A7: =A6+1 -> 3 | B7: 46013 | C7: 47162261 | D7: Abraham Basilio Rojas | E7: Abr.2012@gmail.com | F7: San miguel | G7: 997 630 428 | I7: x | J7: =200+1300 -> 1500 | L7: PAGO | M7: PLIN JL | N7: =200+1300 -> 1500 | P7: Gabriela | Q7: =N7+O7 -> 1500
A8: =A7+1 -> 4 | L8: COBR | Q8: =N8+O8 -> 0 | R8: va cambiar de grupo
A9: =A8+1 -> 5 | B9: 7716111 | C9: 42588957 | D9: Ricardo Junior Boza Valdiviezo | E9: richievzb@gmail.com | F9: Comas | G9: 963 037 833 | H9: x | J9: =500+500+200+300 -> 1500 | L9: PAGO | M9: PLIN JL | N9: =500+500+200+300 -> 1500 | P9: Gabriela | Q9: =N9+O9 -> 1500
A10: =A9+1 -> 6 | B10: 46030 | C10: 76785683 | D10: Anderson Denis López López | E10: fcanlelnubf@gmail.com | F10: Callao | G10: 942 580 187 | I10: x | J10: =200+1300 -> 1500 | L10: PAGO | M10: YAPE JL | N10: =200+1300 -> 1500 | P10: Gabriela | Q10: =N10+O10 -> 1500
A11: =A10+1 -> 7 | B11: 46030 | C11: 61790541 | D11: Gabriel Maximiliano Sánchez Castro | E11: gabrielsanchezcastro67@gmail.com | F11: San Miguel | G11: 926827849 | H11: x | J11: =300+500+500+200 -> 1500 | L11: PAGO | M11: YAPE JL | N11: 1500 | P11: Gabriela | Q11: =N11+O11 -> 1500
A12: =A11+1 -> 8 | B12: 46030 | C12: 48020635 | D12: Jhon Eduardo Ruiz Sachun | F12: Independencia | G12: 931198369 | I12: x | J12: =200+200+400 -> 800 | K12: 1000 | L12: COBR | M12: YAPE JL | N12: =200+600 -> 800 | P12: Gabriela | Q12: =N12+O12 -> 800 | R12: CUOTAS
A13: =A12+1 -> 9 | B13: 46031 | C13: 46636853 | D13: Luis Alberto Pérez zevallos | E13: Perezze@hotmail.com | F13: Ate | G13: 965 480 780 | H13: x | J13: 1400 | L13: PAGO | M13: BCP JL | N13: 1400 | P13: Gabriela | Q13: =N13+O13 -> 1400
A14: =A13+1 -> 10 | B14: 46032 | C14: 43382092 | D14: Pedro Chavez | E14: pedro.chavz@gmail.com | G14: 989 884 998 | H14: x | J14: =500+1000 -> 1500 | L14: PAGO | M14: BBVA JL | N14: =500+500+500 -> 1500 | P14: Gabriela | Q14: =N14+O14 -> 1500
A15: =A14+1 -> 11 | B15: 46034 | C15: 73158664 | D15: Fabrizzio Mijael Lima Obregón | E15: mijaellima140@gmail.com | F15: San Luis | G15: 915352766 | H15: x | J15: =300+1200 -> 1500 | L15: PAGO | M15: BCP JL | N15: =300+1200 -> 1500 | P15: Gabriela | Q15: =N15+O15 -> 1500
A16: =A15+1 -> 12 | B16: 46035 | C16: 47843276 | D16: Elvis Gustavo lluen Torres | E16: elvislluentorres@gmail.com | F16: SJL | G16: 988 407 264 | I16: x | J16: =300+1000 -> 1300 | L16: PAGO | M16: BCP JL | N16: 300 | O16: 1000 | P16: Gabriela | Q16: =N16+O16 -> 1300
A17: =A16+1 -> 13 | B17: 46035 | C17: 10719169 | D17: Jorge Luis cabrera Montenegro | E17: ventas@espacioalexandra.com | F17: San miguel | G17: 990494288 | I17: x | J17: =600+900 -> 1500 | L17: PAGO | M17: BCP JL | N17: =600+900 -> 1500 | P17: Gabriela | Q17: =N17+O17 -> 1500
A18: =A17+1 -> 14 | P18: Katherine | Q18: =N18+O18 -> 0
A19: =A18+1 -> 15 | B19: 46037 | C19: 10107901791 | D19: Peter Günther Kost Soto | E19: peterpgks80@gmail.com | F19: San borja | G19: 979 389 674 | H19: x | J19: =300+1200 -> 1500 | L19: PAGO | M19: BCP JL | N19: 300 | O19: 1200 | P19: Gabriela | Q19: =N19+O19 -> 1500
A20: =A19+1 -> 16 | B20: 46038 | C20: 77087419 | D20: Jessica Escarlen | E20: Escarlen.mrkdigital@gmail.com | G20: 955 805 382 | I20: x | J20: 300 | K20: 1000 | L20: COBR | M20: YAPE JL | N20: 300 | P20: Tania | Q20: =N20+O20 -> 300 | R20: CUOTAS
A21: =A20+1 -> 17 | B21: 46041 | C21: 77438358 | D21: Mirko jesus neyra solis | E21: Mirkoneyrasolis@gmail.com | F21: La victoria | G21: 927 163 904 | I21: x | J21: 1500 | L21: PAGO | M21: BCP EPP | N21: 1500 | P21: Sofia | Q21: =N21+O21 -> 1500
A22: =A21+1 -> 18 | B22: 46042 | C22: 40641102, | D22: Edward Crispín paredes | E22: ecocrispinparedes@gmail.com | G22: 958 989 904 | I22: x | J22: 300 | K22: 1000 | L22: COBR | M22: YAPE JL | N22: 300 | P22: Katherine | Q22: =N22+O22 -> 300 | R22: CUOTAS
A23: =A22+1 -> 19 | B23: 46043 | C23: 40988719 | D23: Milton Fuentes Guerrero | E23: sican.eirl.2025@gmail.com | F23: Callao | G23: 999 507 967 | I23: x | J23: =200+1100 -> 1300 | L23: PAGO | M23: YAPE JL | N23: 200 | O23: 1100 | P23: Gabriela | Q23: =N23+O23 -> 1300
A24: =A23+1 -> 20 | B24: 46045 | C24: 40780085 | D24: eva bendezú gallegos | E24: jesusabendezu18@gmail.com | G24: 951 952 324 | H24: x | J24: =200+1100 -> 1300 | L24: PAGO | M24: BBVA JL | N24: 200 | O24: 1100 | P24: Gabriela | Q24: =N24+O24 -> 1300
A25: =A24+1 -> 21 | B25: 46045 | C25: 25789881 | D25: Alberto Gallegos Arias | E25: agallegos197681@gmail.com | G25: 981 020 021 | H25: X | J25: =300+500 -> 800 | K25: 500 | L25: COBR | M25: BCP EPP | N25: =300 -> 300 | O25: 500 | P25: Yadhira | Q25: =N25+O25 -> 800 | R25: CUOTAS
A26: =A25+1 -> 22 | B26: 46046 | C26: 74730077 | D26: mateo quispe solis | E26: math_leo.u@hotmail.com | F26: El agustino | L26: COBR | P26: Gabriela | Q26: =N26+O26 -> 0
A27: =A26+1 -> 23 | B27: 46046 | C27: 42161125 | D27: Luis Alberto cavero alvites | E27: luisalbertocaveroalvites@gmail.com | F27: Villa El Salvador | G27: 989 665 617 | H27: x | J27: =200+500+400+200 -> 1300 | L27: PAGO | M27: PLIN JL | N27: =200+500+400 -> 1100 | O27: 200 | P27: Gabriela | Q27: =N27+O27 -> 1300
A28: =A27+1 -> 24 | Q28: =N28+O28 -> 0
A29: =A28+1 -> 25 | Q29: =N29+O29 -> 0
A30: =A29+1 -> 26 | Q30: =N30+O30 -> 0
A31: =A30+1 -> 27 | Q31: =N31+O31 -> 0
A32: =A31+1 -> 28 | Q32: =N32+O32 -> 0
A33: =A32+1 -> 29 | Q33: =N33+O33 -> 0
A34: =A33+1 -> 30 | Q34: =N34+O34 -> 0
G35: Total Registrados | H35: =COUNTIF(H4:H34,"X") -> 9 | I35: =COUNTIF(I4:I34,"X") -> 11 | J35: =SUM(J4:J34) -> 25100 | K35: =SUM(K4:K34) -> 3500 | N35: =SUM(N4:N34) -> 20000 | O35: =SUM(O4:O34) -> 5100
G36: Total Cupos | H36: 27 | I36: 27 | J36: =SUM(J35:K35) -> 28600 | N36: =SUM(N35:O35) -> 25100
G37: Cupos Libres | H37: =H36-H35 -> 18 | I37: =I36-I35 -> 16 | J37: Total Venta Fecha | N37: Venta Final Fecha
H38: 150 | I38: 150 | T38: -
H39: =H37*H38 -> 2700 | I39: =I37*I38 -> 2400
H40: =SUM(H39:I39) -> 5100

Sheet GB3
A2: CONTROL DE REGISTRO PARTICIPANTES
A3: GASTRONOMIA EN BRASAS | G3: GB
A4: ID | B4: FE_ REGISTRO | C4: DNI | D4: NOMBRES Y APELLIDOS | E4: EMAIL | F4: DISTRITO | G4: WSP | H4: 45492 | I4: 45492 | J4: MONTO | K4: xCOBRAR | L4: ESTADO | M4: CUENTA | N4: INGRESO | O4: SALDO | P4: VENDEDOR | Q4: TOTAL | R4: OBSERVACION
A5: 1 | B5: 46026 | D5: Rafael Torres - GB15 | J5: 200 | L5: PAGO | N5: 200 | P5: Gabriela | Q5: =N5+O5 -> 200 | R5: OBSERVACION
A6: =A5+1 -> 2 | B6: 46031 | D6: Renato Jurado Vilchez- GB16 | J6: 400 | L6: PAGO | M6: EFECTIVO | N6: 400 | P6: Gabriela | Q6: =N6+O6 -> 400
A7: =A6+1 -> 3 | B7: 46028 | D7: Antonio martin hidalgo alencar GB-20 | J7: 500 | L7: PAGO | M7: EFECTIVO | N7: 500 | P7: Gabriela | Q7: =N7+O7 -> 500
A8: =A7+1 -> 4 | B8: 46030 | D8: Rolando, Cristobal Alarcon GB-20 | J8: 500 | L8: PAGO | N8: 500 | P8: Gabriela | Q8: =N8+O8 -> 500
A9: =A8+1 -> 5 | D9: Denis Walter roman cataño GB-19 | E9: Dejo el curso | K9: 500 | L9: COBR | N9: 0 | P9: Gabriela | Q9: =N9+O9 -> 0
A10: =A9+1 -> 6 | B10: 46035 | D10: Juan manuel gallardo Escalante GB-20 | J10: =200+400 -> 600 | L10: PAGO | N10: =400+200 -> 600 | P10: Gabriela | Q10: =N10+O10 -> 600
A11: =A10+1 -> 7 | Q11: =N11+O11 -> 0
A12: =A11+1 -> 8 | Q12: =N12+O12 -> 0
A13: =A12+1 -> 9 | Q13: =N13+O13 -> 0
A14: =A13+1 -> 10 | Q14: =N14+O14 -> 0
A15: =A14+1 -> 11 | Q15: =N15+O15 -> 0
A16: =A15+1 -> 12 | Q16: =N16+O16 -> 0
A17: =A16+1 -> 13 | Q17: =N17+O17 -> 0
A18: =A17+1 -> 14 | Q18: =N18+O18 -> 0
A19: =A18+1 -> 15 | Q19: =N19+O19 -> 0
A20: =A19+1 -> 16 | Q20: =N20+O20 -> 0
A21: =A20+1 -> 17 | Q21: =N21+O21 -> 0
A22: =A21+1 -> 18 | Q22: =N22+O22 -> 0
... A33: =A32+1 -> 29 | Q33: =N33+O33 -> 0
A34: =A33+1 -> 30 | Q34: =N34+O34 -> 0 | R34: OBSERVACION
G35: Total Registrados | H35: =COUNTIF(H4:H34,"X") -> 0 | I35: =COUNTIF(I4:I34,"X") -> 0 | J35: =SUM(J4:J34) -> 2200 | K35: =SUM(K4:K34) -> 500 | N35: =SUM(N4:N34) -> 2200 | O35: =SUM(O4:O34) -> 0
G36: Total Cupos | H36: 27 | I36: 27 | J36: =SUM(J35:K35) -> 2700 | N36: =SUM(N35:O35) -> 2200
G37: Cupos Libres | H37: =H36-H35 -> 27 | I37: =I36-I35 -> 27 | J37: Total Venta Fecha | N37: Venta Final Fecha
H38: 150 | I38: 150 | T38: -
H39: =H37*H38 -> 4050 | I39: =I37*I38 -> 4050
H40: =SUM(H39:I39) -> 8100

Sheet GB4
A2: CONTROL DE REGISTRO PARTICIPANTES
A3: GASTRONOMIA EN BRASAS | G3: GB
A4: ID | B4: FE_ REGISTRO | C4: DNI | D4: NOMBRES Y APELLIDOS | E4: EMAIL | F4: DISTRITO | G4: WSP | H4: 45492 | I4: 45492 | J4: MONTO | K4: xCOBRAR | L4: ESTADO | M4: CUENTA | N4: INGRESO | O4: SALDO | P4: VENDEDOR | Q4: TOTAL | R4: OBSERVACION
A5: 1 | B5: 1214 | C5: 190 | D5: 150 | E5: 190 | G5: 349.8 | K5: 349.8 | Q5: =N5+O5 -> 0 | R5: OBSERVACION
A6: =A5+1 -> 2 | B6: 90 | C6: 200 | D6: 380 | E6: 450 | G6: 180 | K6: 180 | Q6: =N6+O6 -> 0
A7: =A6+1 -> 3 | B7: 10 | C7: 380 | D7: 290 | E7: 190 | G7: 100 | K7: 100 | Q7: =N7+O7 -> 0
A8: =A7+1 -> 4 | B8: 120 | C8: 180 | D8: 165 | E8: 360 | G8: 300 | K8: 300 | Q8: =N8+O8 -> 0
A9: =A8+1 -> 5 | B9: 20 | C9: 100 | D9: 170 | E9: 350 | G9: 200 | K9: 200 | Q9: =N9+O9 -> 0
A10: =A9+1 -> 6 | B10: 150 | C10: 160 | D10: 330 | E10: 160 | G10: 180 | K10: 180 | Q10: =N10+O10 -> 0
A11: =A10+1 -> 7 | B11: 180 | C11: 200 | D11: 139.76 | E11: 200 | G11: 125 | K11: 125 | Q11: =N11+O11 -> 0
A12: =A11+1 -> 8 | B12: 100 | C12: 180 | D12: 190 | E12: 380 | G12: 380 | I12: 3490 | K12: 380 | Q12: =N12+O12 -> 0
A13: =A12+1 -> 9 | B13: 250 | C13: 250 | D13: 180 | E13: 300 | G13: 200 | I13: 349.8 | K13: 200 | Q13: =N13+O13 -> 0
A14: =A13+1 -> 10 | B14: 139.76 | C14: 330 | D14: 100 | I14: 344 | Q14: =N14+O14 -> 0
A15: =A14+1 -> 11 | B15: 200 | C15: 280 | D15: 50 | Q15: =N15+O15 -> 0
A16: =A15+1 -> 12 | B16: 150 | C16: 500 | D16: 1439 | Q16: =N16+O16 -> 0
A17: =A16+1 -> 13 | B17: 380 | F17: 349.8 | H17: 693.8 | Q17: =N17+O17 -> 0
A18: =A17+1 -> 14 | B18: 37.9 | C18: 180 | F18: 344 | Q18: =N18+O18 -> 0
A19: =A18+1 -> 15 | C19: 360 | E19: 3490 | Q19: =N19+O19 -> 0
A20: =A19+1 -> 16 | E20: 693.8 | Q20: =N20+O20 -> 0
A21: =A20+1 -> 17 | Q21: =N21+O21 -> 0
A22: =A21+1 -> 18 | Q22: =N22+O22 -> 0
A23: =A22+1 -> 19 | Q23: =N23+O23 -> 0
A24: =A23+1 -> 20 | Q24: =N24+O24 -> 0
A25: =A24+1 -> 21 | Q25: =N25+O25 -> 0
A26: =A25+1 -> 22 | Q26: =N26+O26 -> 0
A27: =A26+1 -> 23 | Q27: =N27+O27 -> 0
A28: =A27+1 -> 24 | Q28: =N28+O28 -> 0
A29: =A28+1 -> 25 | Q29: =N29+O29 -> 0
A30: =A29+1 -> 26 | Q30: =N30+O30 -> 0
A31: =A30+1 -> 27 | Q31: =N31+O31 -> 0
A32: =A31+1 -> 28 | Q32: =N32+O32 -> 0
A33: =A32+1 -> 29 | Q33: =N33+O33 -> 0
A34: =A33+1 -> 30 | Q34: =N34+O34 -> 0 | R34: OBSERVACION
G35: Total Registrados | H35: =COUNTIF(H4:H34,"X") -> 0 | I35: =COUNTIF(I4:I34,"X") -> 0 | J35: =SUM(J4:J34) -> 0 | K35: =SUM(K4:K34) -> 2014.8 | N35: =SUM(N4:N34) -> 0 | O35: =SUM(O4:O34) -> 0
G36: Total Cupos | H36: 27 | I36: 27 | J36: =SUM(J35:K35) -> 2014.8 | N36: =SUM(N35:O35) -> 0
G37: Cupos Libres | H37: =H36-H35 -> 27 | I37: =I36-I35 -> 27 | J37: Total Venta Fecha | N37: Venta Final Fecha
H38: 150 | I38: 150 | T38: -
H39: =H37*H38 -> 4050 | I39: =I37*I38 -> 4050
H40: =SUM(H39:I39) -> 8100

Sheet CONTROL
A1: P
B2: GRADUACIÓN GASTRONOMIA EN BRASAS - 19
B3: LISTA DE INVITADOS
B4: DOMINGO 01/02 - 2:00PM
B5: ID | C5: DNI | D5: NOMBRES Y APELLIDOS | E5: QR | F5: FIRMA
B6: 1 | D6: Stephanie Ysabel Guerra Uribe
B7: 2 | D7: Felix isanu Huapaya Atencio
B8: 3 | D8: Astrid Hassel Criales Johnson
B9: 4 | D9: Roger Vargas Morales
B10: 5 | D10: Elio Campos Ramos
B11: 6 | D11: Ángel Huamán Ccopa
B12: 7 | D12: Fiorella Guevara Ampuero
B13: 8
B14: 9
B15: 10
B16: 11
B17: 12
B18: 13
B19: 14
B20: 15
B21: 16
B22: 17
B23: 18
B24: 19
... B44: 39

Sheet VARIABLE
B3: CUENTAS | D3: VENDEDOR | F3: SITUACION | H3: CURSOS
B4: BCP JL | D4: Katherine | F4: PAGO | H4: CILINDRO Y CAJA
B5: SCOT JL | D5: Mariel | F5: COBR | H5: PARRILLA T1
B6: BBVA JL | D6: Yadhira | F6: DESC | H6: PARRILLA T2
B7: YAPE JL | D7: Gabriela | F7: INTER | H7: PARRILLA 2 TURNOS
B8: PLIN JL | D8: Greici | H8: AMBOS
B9: EFECTIVO | D9: Yerika
B10: MERC-PAG | D10: Sergio
B11: BCP EPP | D11: Sofia
B12: LINK-CULQUI | D12: Tania
B13: BCP CP | D13: FH
D14: JL
